Workbook

Sheet 2027 会议主表
A1: 序号 | B1: 简称 | C1: 全称 | D1: 研究主题 | E1: 方向 | F1: CCF | G1: 摘要截稿 (北京) | H1: 正文截稿 (北京) | I1: 轮次 | J1: 原始时区 | K1: Rebuttal (北京) | L1: 录用通知 (北京) | M1: 状态 | N1: 剩余 天数 | O1: 会期 | P1: 地点 | Q1: 举办形式 | R1: 是否必须到场 | S1: 远程参会 | T1: 投稿上限 (篇) | U1: 上限口径 | V1: 新人作者条款 | W1: 官网核查 | X1: 信息缺口 | Y1: 官网 | Z1: 备注
A2: 1 | B2: AAAI | C2: AAAI Conference on Artificial Intelligence | D2: AI 综合顶会，符号推理与规划传统强，也收 ML 各方向应用 | E2: 人工智能 | F2: A | G2: 46225.833 | H2: 46232.833 | I2: 单轮 | J2: UTC-12 | K2: 46321.833 | L2: 2026-11-30 | M2: =IF(ISNUMBER(H2),IF(H2>'_轮次'!$A$1,"未截止","已截止"),"TBD") | N2: =IF(ISNUMBER(H2),IF(H2>'_轮次'!$A$1,INT(H2-'_轮次'!$A$1),"—"),"—") | O2: February 16-23, 2027 | P2: Montréal, Québec, Canada | Q2: 线下 | R2: 必须到场 | S2: 提供付费 virtual 参会 | T2: 不限 | U2: — | V2: 未找到 | W2: 已核实 | X2: 新人条款 | Y2: https://aaai.org/conference/aaai/aaai-27/ | Z2: 近年投稿量极大，录取率约 20% 上下；核查:摘要07-21，全文07-28；日程页未写宣讲与远程政策
A3: 2 | B3: ACL | C3: Annual Meeting of the Association for Computational Linguistics | D3: 自然语言处理第一大会，句法语义到 LLM 应用全覆盖，重视评测 | E3: 人工智能 | F3: A | G3: — | H3: 46392.833 | I3: ARR Submission | J3: UTC-12 | K3: — | L3: 待公布 | M3: =IF(ISNUMBER(H3),IF(H3>'_轮次'!$A$1,"未截止","已截止"),"TBD") | N3: =IF(ISNUMBER(H3),IF(H3>'_轮次'!$A$1,INT(H3-'_轮次'!$A$1),"—"),"—") | O3: August 17-22, 2027 | P3: Kyoto, Japan | Q3: 线下 | R3: 允许远程 | S3: in-person 与 virtual 两种宣讲均可 | T3: 不限 | U3: — | V3: 未找到 | W3: 已核实 | X3: 新人条款 | Y3: https://2027.aclweb.org/ | Z3: 经 ACL Rolling Review 提交，再承诺至会议；核查:须至少一位作者注册并宣讲；录用通知日TBD
A4: 3 | B4: CVPR | C4: IEEE/CVF Conference on Computer Vision and Pattern Recognition | D4: 计算机视觉第一大会，识别/检测/生成/三维全覆盖，看重实验规模 | E4: 人工智能 | F4: A | G4: 46337.833 | H4: 46343.833 | I4: 单轮 | J4: UTC-12 | K4: 46420.833 | L4: 2027-02-25 | M4: =IF(ISNUMBER(H4),IF(H4>'_轮次'!$A$1,"未截止","已截止"),"TBD") | N4: =IF(ISNUMBER(H4),IF(H4>'_轮次'!$A$1,INT(H4-'_轮次'!$A$1),"—"),"—") | O4: June 20-25, 2027 | P4: Seattle, WA, United States | Q4: 线下 | R4: 必须到场 | S4: 不设线上报告通道 | T4: 不限 | U4: — | V4: 硬性｜全体作者须应召担任审稿人，豁免须事前申请 | W4: 已核实 | X4: — | Y4: https://cvpr.thecvf.com/Conferences/2027 | Z4: 每年 11 月截稿，6 月开会；核查:论文注册11-10；CFP未明写现场宣讲要求
A5: 4 | B5: ICCV | C5: IEEE International Conference on Computer Vision | D5: 计算机视觉三大顶会之一，偏重算法创新与理论分析，两年一届 | E5: 人工智能 | F5: A | G5: — | H5: 待公布 | I5: — | J5: AoE | K5: — | L5: 待公布 | M5: =IF(ISNUMBER(H5),IF(H5>'_轮次'!$A$1,"未截止","已截止"),"TBD") | N5: =IF(ISNUMBER(H5),IF(H5>'_轮次'!$A$1,INT(H5-'_轮次'!$A$1),"—"),"—") | O5: October 2-8, 2027 | P5: Hong Kong, China | Q5: 线下 | R5: 必须到场 | S5: 不设线上报告通道 | T5: 不限 | U5: — | V5: CFP未发布 | W5: 2027CFP未发布 | X5: 截稿日、新人条款 | Y5: https://iccv.thecvf.com/Conferences/2027 | Z5: 奇数年举办，2027 届正常召开；核查:官网仅公布时间地点(10/3-7)，CFP未出
A6: 5 | B6: ICLR | C6: International Conference on Learning Representations | D6: 表征学习与深度学习前沿阵地，LLM 时代影响力最大，开放评审 | E6: 人工智能 | F6: A | G6: 46284.833 | H6: 46291.833 | I6: 单轮 | J6: AoE | K6: 46345.833 | L6: 2026-12-16 | M6: =IF(ISNUMBER(H6),IF(H6>'_轮次'!$A$1,"未截止","已截止"),"TBD") | N6: =IF(ISNUMBER(H6),IF(H6>'_轮次'!$A$1,INT(H6-'_轮次'!$A$1),"—"),"—") | O6: April 26-30, 2027 | P6: San Francisco, CA, USA | Q6: 混合 | R6: 允许远程 | S6: 免费线上参会并可远程报告 | T6: 20 | U6: 每届 | V6: 硬性｜须指定作者注册审稿≥3 篇，否则直接拒稿 | W6: 已核实 | X6: — | Y6: https://iclr.cc/Conferences/2027 | Z6: 评审意见与讨论全程公开；核查:署名≥3篇须审6篇；出席形式未明示
A7: 6 | B7: ACM SIGGRAPH | C7: ACM SIGGRAPH Annual Conference | D7: 图形学与交互技术第一大会，渲染/几何/动画，重系统与艺术表达 | E7: 图形学与多媒体 | F7: A | G7: — | H7: 待公布 | I7: — | J7: UTC+0 | K7: — | L7: 待公布 | M7: =IF(ISNUMBER(H7),IF(H7>'_轮次'!$A$1,"未截止","已截止"),"TBD") | N7: =IF(ISNUMBER(H7),IF(H7>'_轮次'!$A$1,INT(H7-'_轮次'!$A$1),"—"),"—") | O7: August 8 - 12, 2027 | P7: Anaheim, California | Q7: 线下 | R7: 必须到场 | S7: 提供付费线上参会 | T7: 不限 | U7: — | V7: CFP未发布 | W7: 2027CFP未发布 | X7: 截稿日、新人条款 | Y7: https://s2027.siggraph.org/ | Z7: 分技术论文与 Art Papers 等多轨道；核查:第三方站点称Stage1为2027-01-21，官网未见
A8: 7 | B8: IEEE VR | C8: IEEE Virtual Reality | D8: 虚拟现实与增强现实顶会，追踪/显示/交互/感知，偏系统与用户研究 | E8: 图形学与多媒体 | F8: A | G8: 46259.833 | H8: 46266.833 | I8: 单轮 | J8: AoE | K8: — | L8: 2027-01-07 | M8: =IF(ISNUMBER(H8),IF(H8>'_轮次'!$A$1,"未截止","已截止"),"TBD") | N8: =IF(ISNUMBER(H8),IF(H8>'_轮次'!$A$1,INT(H8-'_轮次'!$A$1),"—"),"—") | O8: February 27 - March 3, 2027 | P8: Melbourne, Australia | Q8: 线下 | R8: 必须到场 | S8: 仅特殊情况允许线上宣讲 | T8: 不限 | U8: — | V8: 硬性｜资深作者须注册审稿，评审数≥投稿数，失责可拒稿 | W8: 已核实 | X8: — | Y8: https://ieeevr.org/2027/ | Z8: 期刊轨与会议轨并行，TVCG 出版；核查:截稿已过(2026-08-31)；资深作者须任审稿人
A9: 8 | B9: CAV | C9: International Conference on Computer-Aided Verification | D9: 计算机辅助验证顶会，模型检验/程序验证/SMT，形式化方法核心 | E9: 计算机科学理论 | F9: A | G9: — | H9: 46408.833 | I9: 单轮 | J9: AoE | K9: 46486.833 | L9: 2027-04-23 | M9: =IF(ISNUMBER(H9),IF(H9>'_轮次'!$A$1,"未截止","已截止"),"TBD") | N9: =IF(ISNUMBER(H9),IF(H9>'_轮次'!$A$1,INT(H9-'_轮次'!$A$1),"—"),"—") | O9: July 19-23, 2027 | P9: KIT, Amsterdam, The Netherlands | Q9: 线下 | R9: 待确认 | S9: 待确认 | T9: 5 | U9: 每届 | V9: 无专属条款 | W9: 已核实 | X9: 是否到场 | Y9: https://conferences.i-cav.org/2027/ | Z9: LNCS 出版，另设 artifact 评审；核查:全文2027-01-20；每作者限投5篇（含三类）
A10: 9 | B10: LICS | C10: IEEE Symposium on Logic in Computer Science | D10: 逻辑与计算机科学交叉顶会，证明论/语义/类型论，理论性强 | E10: 计算机科学理论 | F10: A | G10: — | H10: 待公布 | I10: — | J10: AoE | K10: — | L10: 待公布 | M10: =IF(ISNUMBER(H10),IF(H10>'_轮次'!$A$1,"未截止","已截止"),"TBD") | N10: =IF(ISNUMBER(H10),IF(H10>'_轮次'!$A$1,INT(H10-'_轮次'!$A$1),"—"),"—") | O10: June 21-24, 2027 | P10: Montréal, Canada | Q10: 线下 | R10: 待确认 | S10: 待确认 | T10: 不限 | U10: — | V10: CFP未发布 | W10: 2027CFP未发布 | X10: 截稿日、是否到场、新人条款 | Y10: https://lics.siglog.org/lics27/ | Z10: 常与 ICALP 等逻辑类会议联办；核查:官网仅占位页，注明信息稍后公布
A11: 10 | B11: SODA | C11: ACM-SIAM Symposium on Discrete Algorithms | D11: 离散算法理论顶会，算法设计与下界证明，与 STOC/FOCS 互补 | E11: 计算机科学理论 | F11: A | G11: — | H11: 46213.833 | I11: 单轮 | J11: UTC-12 | K11: 46270.833 | L11: 待公布 | M11: =IF(ISNUMBER(H11),IF(H11>'_轮次'!$A$1,"未截止","已截止"),"TBD") | N11: =IF(ISNUMBER(H11),IF(H11>'_轮次'!$A$1,INT(H11-'_轮次'!$A$1),"—"),"—") | O11: January 24-27, 2027 | P11: Philadelphia, Pennsylvania, USA | Q11: 线下 | R11: 必须到场 | S11: 不接受远程或录播报告 | T11: 不限 | U11: — | V11: 利好｜通道 最佳学生论文奖（全学生作者可评） | W11: 已核实 | X11: — | Y11: https://www.siam.org/conferences-events/siam-conferences/soda27/ | Z11: 与 ALENEX/ANALCO 同期同地举办；核查:录用通知仅写2026年10月，无具体日
A12: 11 | B12: STOC | C12: ACM Symposium on the Theory of Computing | D12: 理论计算机科学最高级别会议，复杂度/算法/密码基础理论 | E12: 计算机科学理论 | F12: A | G12: — | H12: 46329.833 | I12: 单轮 | J12: UTC-12 | K12: — | L12: 2027-02-01 | M12: =IF(ISNUMBER(H12),IF(H12>'_轮次'!$A$1,"未截止","已截止"),"TBD") | N12: =IF(ISNUMBER(H12),IF(H12>'_轮次'!$A$1,INT(H12-'_轮次'!$A$1),"—"),"—") | O12: June 6-11, 2027 | P12: Atlanta, Georgia, USA | Q12: 线下 | R12: 必须到场 | S12: 无正式远程，需提前联系主席 | T12: 5 | U12: 每届 | V12: 硬性｜配额 5 篇（每位作者各自计，适用于所有作者） | W12: 已核实 | X12: — | Y12: https://acm-stoc.org/stoc2027/ | Z12: 与 FOCS 并列为理论两大顶会；核查:强制公开发布投稿并提交20-30分钟视频
A13: 12 | B13: ICDE | C13: IEEE International Conference on Data Engineering | D13: 数据工程三大顶会之一，数据库系统/查询优化/数据管理全方向 | E13: 数据库/数据挖掘 | F13: A | G13: =IF(ISNUMBER(H13),IF(N(INDEX('_轮次'!$N$13:$Y$13,MATCH(H13,'_轮次'!$B$13:$M$13,0)))=0,"—",INDEX('_轮次'!$N$13:$Y$13,MATCH(H13,'_轮次'!$B$13:$M$13,0))),"—") | H13: =IF(COUNT('_轮次'!$B$13:$M$13)=0,"待公布",IF(COUNTIF('_轮次'!$B$13:$M$13,">"&'_轮次'!$A$1)>0,SMALL('_轮次'!$B$13:$M$13,COUNTIF('_轮次'!$B$13:$M$13,"<="&'_轮次'!$A$1)+1),MAX('_轮次'!$B$13:$M$13))) | I13: =IF(ISNUMBER(H13),INDEX('_轮次'!$AX$13:$BI$13,MATCH(H13,'_轮次'!$B$13:$M$13,0)),"—") | J13: PT | K13: =IF(ISNUMBER(H13),IF(N(INDEX('_轮次'!$Z$13:$AK$13,MATCH(H13,'_轮次'!$B$13:$M$13,0)))=0,"—",INDEX('_轮次'!$Z$13:$AK$13,MATCH(H13,'_轮次'!$B$13:$M$13,0))),"—") | L13: =IF(ISNUMBER(H13),IF(N(INDEX('_轮次'!$AL$13:$AW$13,MATCH(H13,'_轮次'!$B$13:$M$13,0)))=0,"—",INDEX('_轮次'!$AL$13:$AW$13,MATCH(H13,'_轮次'!$B$13:$M$13,0))),"—") | M13: =IF(ISNUMBER(H13),IF(H13>'_轮次'!$A$1,"未截止","已截止"),"TBD") | N13: =IF(ISNUMBER(H13),IF(H13>'_轮次'!$A$1,INT(H13-'_轮次'!$A$1),"—"),"—") | O13: May 17-21, 2027 | P13: Copenhagen, Denmark | Q13: 线下 | R13: 必须到场 | S13: 待确认 | T13: 不限 | U13: — | V13: 硬性｜配额 5 篇（每轮，研究轨道） | W13: 已核实 | X13: — | Y13: https://icde2027.github.io/ | Z13: IEEE 主办，分研究轨与工业轨；核查:研究主会两轮，第一轮2026-06-11已截；全部轮次 first round:2026-06-12 / second round:2026-11-12
A14: 13 | B14: SIGIR | C14: International Conference on Research on Development in Information Retrieval | D14: 信息检索第一大会，检索模型/排序/推荐/对话式检索，评测导向 | E14: 数据库/数据挖掘 | F14: A | G14: 46402.833 | H14: 46409.833 | I14: 单轮 | J14: AoE | K14: — | L14: 2027-04-05 | M14: =IF(ISNUMBER(H14),IF(H14>'_轮次'!$A$1,"未截止","已截止"),"TBD") | N14: =IF(ISNUMBER(H14),IF(H14>'_轮次'!$A$1,INT(H14-'_轮次'!$A$1),"—"),"—") | O14: July 18-24, 2027 | P14: San Jose, California, USA | Q14: 线下 | R14: 必须到场 | S14: 待确认 | T14: 不限 | U14: — | V14: 利好｜通道 Doctoral Consortium | W14: 已核实 | X14: — | Y14: https://sigir2027.org/ | Z14: 设 Resource、Demo、Industry 等子轨道；核查:摘要2027-01-14；短论文等日期标TBA
A15: 14 | B15: SIGKDD | C15: ACM Knowledge Discovery and Data Mining | D15: 数据挖掘第一大会，图学习/推荐/时序/大模型数据应用，工业界重 | E15: 数据库/数据挖掘 | F15: A | G15: 46223.833 | H15: 46230.833 | I15: 1st round of 2 total rounds | J15: AoE | K15: 46309.833 | L15: 2026-11-14 | M15: =IF(ISNUMBER(H15),IF(H15>'_轮次'!$A$1,"未截止","已截止"),"TBD") | N15: =IF(ISNUMBER(H15),IF(H15>'_轮次'!$A$1,INT(H15-'_轮次'!$A$1),"—"),"—") | O15: August 1-5, 2027 | P15: San Jose, California, USA | Q15: 线下 | R15: 必须到场 | S15: 待确认 | T15: 7 | U15: 每届 | V15: 硬性｜须提名 1 名合格审稿人（KDD 等≥3 篇） | W15: 已核实 | X15: — | Y15: https://kdd2027.kdd.org/ | Z15: 研究轨与 Applied Data Science 轨分开投；核查:第一轮；每轮每作者最多7篇，第二轮日期未公布
A16: 15 | B16: SIGMOD | C16: ACM Conference on Management of Data | D16: 数据库第一大会，数据系统/存储引擎/事务与查询处理，系统实现重 | E16: 数据库/数据挖掘 | F16: A | G16: =IF(ISNUMBER(H16),IF(N(INDEX('_轮次'!$N$16:$Y$16,MATCH(H16,'_轮次'!$B$16:$M$16,0)))=0,"—",INDEX('_轮次'!$N$16:$Y$16,MATCH(H16,'_轮次'!$B$16:$M$16,0))),"—") | H16: =IF(COUNT('_轮次'!$B$16:$M$16)=0,"待公布",IF(COUNTIF('_轮次'!$B$16:$M$16,">"&'_轮次'!$A$1)>0,SMALL('_轮次'!$B$16:$M$16,COUNTIF('_轮次'!$B$16:$M$16,"<="&'_轮次'!$A$1)+1),MAX('_轮次'!$B$16:$M$16))) | I16: =IF(ISNUMBER(H16),INDEX('_轮次'!$AX$16:$BI$16,MATCH(H16,'_轮次'!$B$16:$M$16,0)),"—") | J16: AoE | K16: =IF(ISNUMBER(H16),IF(N(INDEX('_轮次'!$Z$16:$AK$16,MATCH(H16,'_轮次'!$B$16:$M$16,0)))=0,"—",INDEX('_轮次'!$Z$16:$AK$16,MATCH(H16,'_轮次'!$B$16:$M$16,0))),"—") | L16: =IF(ISNUMBER(H16),IF(N(INDEX('_轮次'!$AL$16:$AW$16,MATCH(H16,'_轮次'!$B$16:$M$16,0)))=0,"—",INDEX('_轮次'!$AL$16:$AW$16,MATCH(H16,'_轮次'!$B$16:$M$16,0))),"—") | M16: =IF(ISNUMBER(H16),IF(H16>'_轮次'!$A$1,"未截止","已截止"),"TBD") | N16: =IF(ISNUMBER(H16),IF(H16>'_轮次'!$A$1,INT(H16-'_轮次'!$A$1),"—"),"—") | O16: June 13-19, 2027 | P16: Huntington Beach, CA, USA | Q16: 线下 | R16: 必须到场 | S16: 待确认 | T16: 10 | U16: 每届 | V16: 未找到 | W16: 已核实 | X16: 新人条款 | Y16: https://2027.sigmod.org/ | Z16: 一年两轮投稿，PACMMOD 出版；核查:四轮截稿，取末轮R4；终审通知2027-03-12；全部轮次 round 1:2026-01-18 / round 2:2026-04-18 / round 3:2026-07-18 / round 4:2026-10-18
A17: 16 | B17: VLDB | C17: International Conference on Very Large Data Bases | D17: 数据库与数据管理顶会，系统/存储/查询/新型硬件，工业论文占比高 | E17: 数据库/数据挖掘 | F17: A | G17: =IF(ISNUMBER(H17),IF(N(INDEX('_轮次'!$N$17:$Y$17,MATCH(H17,'_轮次'!$B$17:$M$17,0)))=0,"—",INDEX('_轮次'!$N$17:$Y$17,MATCH(H17,'_轮次'!$B$17:$M$17,0))),"—") | H17: =IF(COUNT('_轮次'!$B$17:$M$17)=0,"待公布",IF(COUNTIF('_轮次'!$B$17:$M$17,">"&'_轮次'!$A$1)>0,SMALL('_轮次'!$B$17:$M$17,COUNTIF('_轮次'!$B$17:$M$17,"<="&'_轮次'!$A$1)+1),MAX('_轮次'!$B$17:$M$17))) | I17: =IF(ISNUMBER(H17),INDEX('_轮次'!$AX$17:$BI$17,MATCH(H17,'_轮次'!$B$17:$M$17,0)),"—") | J17: PT | K17: =IF(ISNUMBER(H17),IF(N(INDEX('_轮次'!$Z$17:$AK$17,MATCH(H17,'_轮次'!$B$17:$M$17,0)))=0,"—",INDEX('_轮次'!$Z$17:$AK$17,MATCH(H17,'_轮次'!$B$17:$M$17,0))),"—") | L17: =IF(ISNUMBER(H17),IF(N(INDEX('_轮次'!$AL$17:$AW$17,MATCH(H17,'_轮次'!$B$17:$M$17,0)))=0,"—",INDEX('_轮次'!$AL$17:$AW$17,MATCH(H17,'_轮次'!$B$17:$M$17,0))),"—") | M17: =IF(ISNUMBER(H17),IF(H17>'_轮次'!$A$1,"未截止","已截止"),"TBD") | N17: =IF(ISNUMBER(H17),IF(H17>'_轮次'!$A$1,INT(H17-'_轮次'!$A$1),"—"),"—") | O17: August 23 - August 27, 2027 | P17: Athens, Greece | Q17: 线下 | R17: 必须到场 | S17: 待确认 | T17: 12 | U17: 每年（每月≤2） | V17: 硬性｜须提名 1 名合格审稿人（VLDB 等≥2 篇） | W17: 已核实 | X17: — | Y17: https://www.vldb.org/2027/ | Z17: 按月滚动投稿，PVLDB 出版；核查:每月1日滚动截稿，此处取最终截稿日；全部轮次 轮:2026-04-02 / 轮:2026-05-02 / 轮:2026-06-02 / 轮:2026-07-02 / 轮:2026-08-02 / 轮:2026-09-02 / 轮:2026-10-02 / 轮:2026-11-02 / 轮:2026-12-02 / 轮:2027-01-02 / 轮:2027-02-02 / 轮:2027-03-02
A18: 17 | B18: ASPLOS | C18: International Conference on Architectural Support for Programming Languages and Operating Systems | D18: 系统结构顶会，体系结构/编译/操作系统交叉，硬件软件协同设计 | E18: 体系结构/并行/存储 | F18: A | G18: =IF(ISNUMBER(H18),IF(N(INDEX('_轮次'!$N$18:$Y$18,MATCH(H18,'_轮次'!$B$18:$M$18,0)))=0,"—",INDEX('_轮次'!$N$18:$Y$18,MATCH(H18,'_轮次'!$B$18:$M$18,0))),"—") | H18: =IF(COUNT('_轮次'!$B$18:$M$18)=0,"待公布",IF(COUNTIF('_轮次'!$B$18:$M$18,">"&'_轮次'!$A$1)>0,SMALL('_轮次'!$B$18:$M$18,COUNTIF('_轮次'!$B$18:$M$18,"<="&'_轮次'!$A$1)+1),MAX('_轮次'!$B$18:$M$18))) | I18: =IF(ISNUMBER(H18),INDEX('_轮次'!$AX$18:$BI$18,MATCH(H18,'_轮次'!$B$18:$M$18,0)),"—") | J18: AoE | K18: =IF(ISNUMBER(H18),IF(N(INDEX('_轮次'!$Z$18:$AK$18,MATCH(H18,'_轮次'!$B$18:$M$18,0)))=0,"—",INDEX('_轮次'!$Z$18:$AK$18,MATCH(H18,'_轮次'!$B$18:$M$18,0))),"—") | L18: =IF(ISNUMBER(H18),IF(N(INDEX('_轮次'!$AL$18:$AW$18,MATCH(H18,'_轮次'!$B$18:$M$18,0)))=0,"—",INDEX('_轮次'!$AL$18:$AW$18,MATCH(H18,'_轮次'!$B$18:$M$18,0))),"—") | M18: =IF(ISNUMBER(H18),IF(H18>'_轮次'!$A$1,"未截止","已截止"),"TBD") | N18: =IF(ISNUMBER(H18),IF(H18>'_轮次'!$A$1,INT(H18-'_轮次'!$A$1),"—"),"—") | O18: April 11-15, 2027 | P18: Crete, Greece | Q18: 线下 | R18: 必须到场 | S18: 待确认 | T18: 4 | U18: 每届 | V18: 无专属条款 | W18: 已核实 | X18: — | Y18: https://www.asplos-conference.org/asplos2027/cfp/ | Z18: 一年两轮截稿，ACM 出版；核查:两轮截稿(4/15、9/9)，此处取九月周期；全部轮次 April Cycle Submission Deadline:2026-04-16 / September Cycle Submission Deadline:2026-09-10
A19: 18 | B19: DAC | C19: Design Automation Conference | D19: EDA 领域第一会，芯片设计/验证/物理设计为主，兼收 AI 加速器与硬件安全 | E19: 体系结构/并行/存储 | F19: A | G19: 46338.375 | H19: 46345.375 | I19: 单轮 | J19: UTC-8 | K19: — | L19: 2027-03-08 | M19: =IF(ISNUMBER(H19),IF(H19>'_轮次'!$A$1,"未截止","已截止"),"TBD") | N19: =IF(ISNUMBER(H19),IF(H19>'_轮次'!$A$1,INT(H19-'_轮次'!$A$1),"—"),"—") | O19: July 11-14, 2027 | P19: San Jose, CA | Q19: 线下 | R19: 必须到场 | S19: 待确认 | T19: 不限 | U19: — | V19: 无专属条款 | W19: 已核实 | X19: — | Y19: https://dac.com/2027/authors/call-for-contributions | Z19: 工业界参与度高，有设计竞赛与展览；核查:摘要2026-11-11；须注册并现场海报报告
A20: 19 | B20: EuroSys | C20: European Conference on Computer Systems | D20: 欧洲系统顶会，操作系统/分布式/云与虚拟化，重工程实现与真实测量 | E20: 体系结构/并行/存储 | F20: A | G20: =IF(ISNUMBER(H20),IF(N(INDEX('_轮次'!$N$20:$Y$20,MATCH(H20,'_轮次'!$B$20:$M$20,0)))=0,"—",INDEX('_轮次'!$N$20:$Y$20,MATCH(H20,'_轮次'!$B$20:$M$20,0))),"—") | H20: =IF(COUNT('_轮次'!$B$20:$M$20)=0,"待公布",IF(COUNTIF('_轮次'!$B$20:$M$20,">"&'_轮次'!$A$1)>0,SMALL('_轮次'!$B$20:$M$20,COUNTIF('_轮次'!$B$20:$M$20,"<="&'_轮次'!$A$1)+1),MAX('_轮次'!$B$20:$M$20))) | I20: =IF(ISNUMBER(H20),INDEX('_轮次'!$AX$20:$BI$20,MATCH(H20,'_轮次'!$B$20:$M$20,0)),"—") | J20: AoE | K20: =IF(ISNUMBER(H20),IF(N(INDEX('_轮次'!$Z$20:$AK$20,MATCH(H20,'_轮次'!$B$20:$M$20,0)))=0,"—",INDEX('_轮次'!$Z$20:$AK$20,MATCH(H20,'_轮次'!$B$20:$M$20,0))),"—") | L20: =IF(ISNUMBER(H20),IF(N(INDEX('_轮次'!$AL$20:$AW$20,MATCH(H20,'_轮次'!$B$20:$M$20,0)))=0,"—",INDEX('_轮次'!$AL$20:$AW$20,MATCH(H20,'_轮次'!$B$20:$M$20,0))),"—") | M20: =IF(ISNUMBER(H20),IF(H20>'_轮次'!$A$1,"未截止","已截止"),"TBD") | N20: =IF(ISNUMBER(H20),IF(H20>'_轮次'!$A$1,INT(H20-'_轮次'!$A$1),"—"),"—") | O20: April 19-23, 2027 | P20: Rabat, Morocco | Q20: 线下 | R20: 必须到场 | S20: 待确认 | T20: 3 | U20: 每届 | V20: 无专属条款 | W20: 已核实 | X20: — | Y20: https://2027.eurosys.org/ | Z20: 看重可复现性，鼓励 artifact 提交；核查:春秋两轮，取秋季轮；每篇需一份全费注册；全部轮次 Spring Submission Deadline:2026-05-15 / Fall Submission Deadline:2026-09-25
A21: 20 | B21: FAST | C21: USENIX Conference on File and Storage Technologies | D21: 存储领域第一会，文件系统/闪存/分布式存储，重实测与可复现性 | E21: 体系结构/并行/存储 | F21: A | G21: =IF(ISNUMBER(H21),IF(N(INDEX('_轮次'!$N$21:$Y$21,MATCH(H21,'_轮次'!$B$21:$M$21,0)))=0,"—",INDEX('_轮次'!$N$21:$Y$21,MATCH(H21,'_轮次'!$B$21:$M$21,0))),"—") | H21: =IF(COUNT('_轮次'!$B$21:$M$21)=0,"待公布",IF(COUNTIF('_轮次'!$B$21:$M$21,">"&'_轮次'!$A$1)>0,SMALL('_轮次'!$B$21:$M$21,COUNTIF('_轮次'!$B$21:$M$21,"<="&'_轮次'!$A$1)+1),MAX('_轮次'!$B$21:$M$21))) | I21: =IF(ISNUMBER(H21),INDEX('_轮次'!$AX$21:$BI$21,MATCH(H21,'_轮次'!$B$21:$M$21,0)),"—") | J21: AoE | K21: =IF(ISNUMBER(H21),IF(N(INDEX('_轮次'!$Z$21:$AK$21,MATCH(H21,'_轮次'!$B$21:$M$21,0)))=0,"—",INDEX('_轮次'!$Z$21:$AK$21,MATCH(H21,'_轮次'!$B$21:$M$21,0))),"—") | L21: =IF(ISNUMBER(H21),IF(N(INDEX('_轮次'!$AL$21:$AW$21,MATCH(H21,'_轮次'!$B$21:$M$21,0)))=0,"—",INDEX('_轮次'!$AL$21:$AW$21,MATCH(H21,'_轮次'!$B$21:$M$21,0))),"—") | M21: =IF(ISNUMBER(H21),IF(H21>'_轮次'!$A$1,"未截止","已截止"),"TBD") | N21: =IF(ISNUMBER(H21),IF(H21>'_轮次'!$A$1,INT(H21-'_轮次'!$A$1),"—"),"—") | O21: FEBRUARY 23-25, 2027 | P21: Renton, WA, USA | Q21: 线下 | R21: 必须到场 | S21: 无线上报告选项 | T21: 不限 | U21: — | V21: 利好｜通道 WIP/Posters、Mentoring（均设联合主席） | W21: 已核实 | X21: — | Y21: https://www.usenix.org/conference/fast27 | Z21: USENIX 体系，录用后需提交 artifact；核查:春秋两轮，取秋季轮；无独立摘要截稿；全部轮次 Spring deadline:2026-03-18 / Fall deadline:2026-09-16
A22: 21 | B22: HPCA | C22: IEEE International Symposium on High-Performance Computer Architecture | D22: 体系结构三大顶会之一，处理器/缓存/加速器微架构，重创新与仿真评估 | E22: 体系结构/并行/存储 | F22: A | G22: 46228.833 | H22: 46235.833 | I22: 单轮 | J22: AoE | K22: 46307.833 | L22: 2026-11-06 | M22: =IF(ISNUMBER(H22),IF(H22>'_轮次'!$A$1,"未截止","已截止"),"TBD") | N22: =IF(ISNUMBER(H22),IF(H22>'_轮次'!$A$1,INT(H22-'_轮次'!$A$1),"—"),"—") | O22: March 20-24, 2027 | P22: Salt Lake City, Utah | Q22: 线下 | R22: 必须到场 | S22: 待确认 | T22: 不限 | U22: — | V22: 硬性｜每篇须指定资深作者，或须任Light PC审稿≤6篇 | W22: 已核实 | X22: — | Y22: https://conf.researchr.org/home/hpca-2027 | Z22: 与 ISCA、MICRO 合称体系结构三大会；核查:官网track页404，读SIGARCH官方CFP
A23: 22 | B23: ISCA | C23: International Symposium on Computer Architecture | D23: 最老牌体系结构顶会，CPU/内存/加速器架构，重开创性想法与量化评估 | E23: 体系结构/并行/存储 | F23: A | G23: 46336.833 | H23: 46343.833 | I23: Main Track; rebuttal/revision period: February 16-March 8, 2027 | J23: AoE | K23: 46455.833 | L23: 2027-03-26 | M23: =IF(ISNUMBER(H23),IF(H23>'_轮次'!$A$1,"未截止","已截止"),"TBD") | N23: =IF(ISNUMBER(H23),IF(H23>'_轮次'!$A$1,INT(H23-'_轮次'!$A$1),"—"),"—") | O23: June 5-9, 2027 | P23: Atlanta, Georgia, USA | Q23: 线下 | R23: 必须到场 | S23: 待确认 | T23: 8 | U23: 每届 | V23: 硬性｜须指定资深作者任reserve reviewer；投超6篇须任PC | W23: 已核实 | X23: — | Y23: https://iscaconf.org/isca2027/ | Z23: 有 rebuttal 与作者答复环节；核查:摘要2026-11-09截止；CFP未写现场报告要求
A24: 23 | B24: PPoPP | C24: ACM SIGPLAN Symposium on Principles & Practice of Parallel Programming | D24: 并行编程顶会，并行算法/运行时/编译优化与性能可移植性 | E24: 体系结构/并行/存储 | F24: A | G24: — | H24: 46238.833 | I24: 单轮 | J24: AoE | K24: — | L24: 2026-10-26 | M24: =IF(ISNUMBER(H24),IF(H24>'_轮次'!$A$1,"未截止","已截止"),"TBD") | N24: =IF(ISNUMBER(H24),IF(H24>'_轮次'!$A$1,INT(H24-'_轮次'!$A$1),"—"),"—") | O24: Mar 20-24, 2027 | P24: Salt Lake City, Utah, USA | Q24: 线下 | R24: 必须到场 | S24: 待确认 | T24: 不限 | U24: — | V24: 无专属条款 | W24: 已核实 | X24: — | Y24: https://ppopp27.sigplan.org/ | Z24: 与 PPoPP 同期常有 CGO/HPCA 等联办；核查:通知日2026-10-26临近；官网首页未列日期
A25: 24 | B25: CHI | C25: ACM Conference on Human Factors in Computing Systems | D25: 人机交互第一大会，交互技术/用户研究/可访问性全覆盖，重人本价值 | E25: 人机交互与普适计算 | F25: A | G25: — | H25: 46276.833 | I25: 单轮 | J25: AoE | K25: 46360.833 | L25: 2026-12-17 | M25: =IF(ISNUMBER(H25),IF(H25>'_轮次'!$A$1,"未截止","已截止"),"TBD") | N25: =IF(ISNUMBER(H25),IF(H25>'_轮次'!$A$1,INT(H25-'_轮次'!$A$1),"—"),"—") | O25: May 10 - 14, 2027 | P25: David L. Lawrence Convention Center, Pittsburgh, USA | Q25: 线下 | R25: 允许远程 | S25: 可交预录视频代替现场 | T25: 不限 | U25: — | V25: 硬性｜每篇须提名4人次审稿（RRP），须满足最低审稿资格 | W25: 已核实 | X25: — | Y25: https://chi2027.acm.org/ | Z25: 投稿系统为 PCS，非常见四类系统；核查:至少一位作者须2027-03-04前注册
A26: 25 | B26: UbiComp/ISWC | C26: ACM International Joint Conference on Pervasive and Ubiquitous Computing | D26: 普适计算旗舰，可穿戴/传感/情境感知与移动健康，重真实场景部署 | E26: 人机交互与普适计算 | F26: A | G26: — | H26: 待公布 | I26: — | J26: AoE | K26: — | L26: 待公布 | M26: =IF(ISNUMBER(H26),IF(H26>'_轮次'!$A$1,"未截止","已截止"),"TBD") | N26: =IF(ISNUMBER(H26),IF(H26>'_轮次'!$A$1,INT(H26-'_轮次'!$A$1),"—"),"—") | O26: October 3-7, 2027 | P26: Seoul, Republic of Korea | Q26: 线下 | R26: 待确认 | S26: 待确认 | T26: 不限 | U26: — | V26: CFP未发布 | W26: 2027CFP未发布 | X26: 截稿日、是否到场、新人条款 | Y26: https://sigchi.org/events/ubicomp-2027/ | Z26: 论文经 PACM IMWUT 期刊通道录用；核查:官网仅公布会期2027-10-03至10-07，无CFP
A27: 26 | B27: WWW | C27: International World Wide Web Conferences | D27: 万维网旗舰会，信息检索/推荐/图挖掘/Web 系统，重数据规模与在线效果 | E27: 交叉/综合/新兴 | F27: A | G27: 46314.833 | H27: 46321.833 | I27: 单轮 | J27: AoE | K27: — | L27: 2027-01-04 | M27: =IF(ISNUMBER(H27),IF(H27>'_轮次'!$A$1,"未截止","已截止"),"TBD") | N27: =IF(ISNUMBER(H27),IF(H27>'_轮次'!$A$1,INT(H27-'_轮次'!$A$1),"—"),"—") | O27: May 10 - 14, 2027 | P27: Dublin, Ireland | Q27: 线下 | R27: 必须到场 | S27: 口头可酌情线上，海报须现场 | T27: 7 | U27: 每届 | V27: 硬性｜作者须加入审稿委员会并按时审稿，否则可被拒 | W27: 已核实 | X27: — | Y27: https://www2027.thewebconf.org/ | Z27: 分 research/industry 多个 track；核查:摘要2026-10-18；每类投稿每人限7篇
A28: 27 | B28: INFOCOM | C28: IEEE International Conference on Computer Communications | D28: 计算机网络两大顶会之一，协议/无线/数据中心网络，重建模分析与仿真 | E28: 计算机网络 | F28: A | G28: 46228.833 | H28: 46235.833 | I28: 单轮 | J28: AoE | K28: — | L28: 2026-12-08 | M28: =IF(ISNUMBER(H28),IF(H28>'_轮次'!$A$1,"未截止","已截止"),"TBD") | N28: =IF(ISNUMBER(H28),IF(H28>'_轮次'!$A$1,INT(H28-'_轮次'!$A$1),"—"),"—") | O28: May 24 - 27, 2027 | P28: Honolulu, HI, USA | Q28: 线下 | R28: 必须到场 | S28: 待确认 | T28: 不限 | U28: — | V28: 未找到 | W28: 已核实 | X28: 新人条款 | Y28: https://infocom2027.ieee-infocom.org/ | Z28: 使用 EDAS 投稿，分主会与 workshop；核查:摘要2026-07-24；早期拒稿通知2026-10-09
A29: 28 | B29: MobiCom | C29: ACM Annual International Conference On Mobile Computing And Networking | D29: 移动计算与无线网络顶会，移动系统/无线感知/蜂窝网络，重原型与实测 | E29: 计算机网络 | F29: A | G29: 46261.833 | H29: 46268.833 | I29: Summer Deadlines | J29: AoE | K29: 46333.833 | L29: 2026-11-19 | M29: =IF(ISNUMBER(H29),IF(H29>'_轮次'!$A$1,"未截止","已截止"),"TBD") | N29: =IF(ISNUMBER(H29),IF(H29>'_轮次'!$A$1,INT(H29-'_轮次'!$A$1),"—"),"—") | O29: Oct 18-22, 2027 | P29: TBD | Q29: 线下 | R29: 必须到场 | S29: 待确认 | T29: 不限 | U29: — | V29: 利好｜通道 ACM Student Research Competition（poster） | W29: 已核实 | X29: — | Y29: https://www.sigmobile.org/mobicom/2027/ | Z29: 举办地 TBD，一年一轮投稿；核查:夏季批次；摘要2026-08-26，冬季批次未定
A30: 29 | B30: NSDI | C30: USENIX Symposium on Networked Systems Design and Implementation | D30: 网络系统设计与实现顶会，数据中心/云网络/可编程网络，重真实部署 | E30: 计算机网络 | F30: A | G30: =IF(ISNUMBER(H30),IF(N(INDEX('_轮次'!$N$30:$Y$30,MATCH(H30,'_轮次'!$B$30:$M$30,0)))=0,"—",INDEX('_轮次'!$N$30:$Y$30,MATCH(H30,'_轮次'!$B$30:$M$30,0))),"—") | H30: =IF(COUNT('_轮次'!$B$30:$M$30)=0,"待公布",IF(COUNTIF('_轮次'!$B$30:$M$30,">"&'_轮次'!$A$1)>0,SMALL('_轮次'!$B$30:$M$30,COUNTIF('_轮次'!$B$30:$M$30,"<="&'_轮次'!$A$1)+1),MAX('_轮次'!$B$30:$M$30))) | I30: =IF(ISNUMBER(H30),INDEX('_轮次'!$AX$30:$BI$30,MATCH(H30,'_轮次'!$B$30:$M$30,0)),"—") | J30: UTC-4 | K30: =IF(ISNUMBER(H30),IF(N(INDEX('_轮次'!$Z$30:$AK$30,MATCH(H30,'_轮次'!$B$30:$M$30,0)))=0,"—",INDEX('_轮次'!$Z$30:$AK$30,MATCH(H30,'_轮次'!$B$30:$M$30,0))),"—") | L30: =IF(ISNUMBER(H30),IF(N(INDEX('_轮次'!$AL$30:$AW$30,MATCH(H30,'_轮次'!$B$30:$M$30,0)))=0,"—",INDEX('_轮次'!$AL$30:$AW$30,MATCH(H30,'_轮次'!$B$30:$M$30,0))),"—") | M30: =IF(ISNUMBER(H30),IF(H30>'_轮次'!$A$1,"未截止","已截止"),"TBD") | N30: =IF(ISNUMBER(H30),IF(H30>'_轮次'!$A$1,INT(H30-'_轮次'!$A$1),"—"),"—") | O30: May 11-13, 2027 | P30: Providence, RI, USA | Q30: 线下 | R30: 必须到场 | S30: 未提供线上参会 | T30: 8 | U30: 每届 | V30: 利好｜每篇须一名作者全价注册（非学生价） | W30: 已核实 | X30: — | Y30: https://www.usenix.org/conference/nsdi27 | Z30: 春秋两轮投稿；核查:两轮制，秋季轮全文9/17；须全价注册现场报告；全部轮次 轮:2026-04-24 / 轮:2026-09-18
A31: 30 | B31: SIGCOMM | C31: ACM International Conference on Applications, Technologies, Architectures, and Protocols for Computer Communication | D31: 数据通信第一会，网络架构/协议/可编程数据平面，重测量与现网部署 | E31: 计算机网络 | F31: A | G31: — | H31: 46421.833 | I31: 单轮 | J31: AoE | K31: — | L31: 待公布 | M31: =IF(ISNUMBER(H31),IF(H31>'_轮次'!$A$1,"未截止","已截止"),"TBD") | N31: =IF(ISNUMBER(H31),IF(H31>'_轮次'!$A$1,INT(H31-'_轮次'!$A$1),"—"),"—") | O31: August 8 - 12, 2027 | P31: Bangkok, Thailand | Q31: 线下 | R31: 必须到场 | S31: 设远程 pod，报告仍须到场 | T31: 8 | U31: 每届 | V31: 硬性｜每篇须报一名互惠审稿作者，一般须具博士学位 | W31: 已核实 | X31: — | Y31: https://conferences.sigcomm.org/sigcomm/2027/ | Z31: 分两个投稿轮次，重 artifact 评估；核查:单轮；未公布录用通知日；无 rebuttal
A32: 31 | B32: CCS | C32: ACM Conference on Computer and Communications Security | D32: 安全四大顶会之一，系统安全/密码应用/隐私与机器学习安全，覆盖最广 | E32: 网络与信息安全 | F32: A | G32: — | H32: 待公布 | I32: — | J32: AoE | K32: — | L32: 待公布 | M32: =IF(ISNUMBER(H32),IF(H32>'_轮次'!$A$1,"未截止","已截止"),"TBD") | N32: =IF(ISNUMBER(H32),IF(H32>'_轮次'!$A$1,INT(H32-'_轮次'!$A$1),"—"),"—") | O32: October 11-15, 2027 | P32: Atlanta, USA | Q32: 线下 | R32: 必须到场 | S32: 待确认 | T32: 不限 | U32: — | V32: CFP未发布 | W32: 2027CFP未发布 | X32: 截稿日、新人条款 | Y32: https://www.sigsac.org/ccs/CCS2027/ | Z32: 两轮评审制，投稿量大；核查:官网仅有会期地点，无 CFP 内容
A33: 32 | B33: EUROCRYPT | C33: European Cryptology Conference | D33: 密码学三大顶会之一，偏理论：公钥密码/多方计算/零知识证明 | E33: 网络与信息安全 | F33: A | G33: — | H33: 46283.833 | I33: 单轮 | J33: AoE | K33: 46362.833 | L33: 2027-01-18 | M33: =IF(ISNUMBER(H33),IF(H33>'_轮次'!$A$1,"未截止","已截止"),"TBD") | N33: =IF(ISNUMBER(H33),IF(H33>'_轮次'!$A$1,INT(H33-'_轮次'!$A$1),"—"),"—") | O33: April 11-15, 2027 | P33: Eindhoven, Netherlands | Q33: 线下 | R33: 必须到场 | S33: 不设线上通道 | T33: 不限 | U33: — | V33: 无专属条款 | W33: 已核实 | X33: — | Y33: https://eurocrypt.iacr.org/2027/ | Z33: IACR 旗下，用 IACR 投稿服务器；核查:须由作者之一现场报告；论文录制
A34: 33 | B34: NDSS | C34: Network and Distributed System Security (NDSS) Symposium | D34: 安全四大顶会之一，网络与分布式系统安全，重攻击实现与大规模实测 | E34: 网络与信息安全 | F34: A | G34: =IF(ISNUMBER(H34),IF(N(INDEX('_轮次'!$N$34:$Y$34,MATCH(H34,'_轮次'!$B$34:$M$34,0)))=0,"—",INDEX('_轮次'!$N$34:$Y$34,MATCH(H34,'_轮次'!$B$34:$M$34,0))),"—") | H34: =IF(COUNT('_轮次'!$B$34:$M$34)=0,"待公布",IF(COUNTIF('_轮次'!$B$34:$M$34,">"&'_轮次'!$A$1)>0,SMALL('_轮次'!$B$34:$M$34,COUNTIF('_轮次'!$B$34:$M$34,"<="&'_轮次'!$A$1)+1),MAX('_轮次'!$B$34:$M$34))) | I34: =IF(ISNUMBER(H34),INDEX('_轮次'!$AX$34:$BI$34,MATCH(H34,'_轮次'!$B$34:$M$34,0)),"—") | J34: UTC-12 | K34: =IF(ISNUMBER(H34),IF(N(INDEX('_轮次'!$Z$34:$AK$34,MATCH(H34,'_轮次'!$B$34:$M$34,0)))=0,"—",INDEX('_轮次'!$Z$34:$AK$34,MATCH(H34,'_轮次'!$B$34:$M$34,0))),"—") | L34: =IF(ISNUMBER(H34),IF(N(INDEX('_轮次'!$AL$34:$AW$34,MATCH(H34,'_轮次'!$B$34:$M$34,0)))=0,"—",INDEX('_轮次'!$AL$34:$AW$34,MATCH(H34,'_轮次'!$B$34:$M$34,0))),"—") | M34: =IF(ISNUMBER(H34),IF(H34>'_轮次'!$A$1,"未截止","已截止"),"TBD") | N34: =IF(ISNUMBER(H34),IF(H34>'_轮次'!$A$1,INT(H34-'_轮次'!$A$1),"—"),"—") | O34: March 22 - March 26, 2027 | P34: Seoul, Republic of Korea | Q34: 线下 | R34: 必须到场 | S34: 待确认 | T34: 6 | U34: 每轮 | V34: 硬性｜配额 6 篇/周期（每位作者各自计，适用于所有作者） | W34: 已核实 | X34: — | Y34: https://www.ndss-symposium.org/ndss2027/ | Z34: 两轮投稿，夏季/秋季各一轮；核查:夏/秋两轮均截止；仅称须按参会政策报告；全部轮次 Summer:2026-05-07 / Fall:2026-08-20
A35: 34 | B35: S&P | C35: IEEE Symposium on Security and Privacy | D35: IEEE 安全旗舰，系统安全/隐私保护/密码应用，审稿严、录用率低 | E35: 网络与信息安全 | F35: A | G35: =IF(ISNUMBER(H35),IF(N(INDEX('_轮次'!$N$35:$Y$35,MATCH(H35,'_轮次'!$B$35:$M$35,0)))=0,"—",INDEX('_轮次'!$N$35:$Y$35,MATCH(H35,'_轮次'!$B$35:$M$35,0))),"—") | H35: =IF(COUNT('_轮次'!$B$35:$M$35)=0,"待公布",IF(COUNTIF('_轮次'!$B$35:$M$35,">"&'_轮次'!$A$1)>0,SMALL('_轮次'!$B$35:$M$35,COUNTIF('_轮次'!$B$35:$M$35,"<="&'_轮次'!$A$1)+1),MAX('_轮次'!$B$35:$M$35))) | I35: =IF(ISNUMBER(H35),INDEX('_轮次'!$AX$35:$BI$35,MATCH(H35,'_轮次'!$B$35:$M$35,0)),"—") | J35: UTC-12 | K35: =IF(ISNUMBER(H35),IF(N(INDEX('_轮次'!$Z$35:$AK$35,MATCH(H35,'_轮次'!$B$35:$M$35,0)))=0,"—",INDEX('_轮次'!$Z$35:$AK$35,MATCH(H35,'_轮次'!$B$35:$M$35,0))),"—") | L35: =IF(ISNUMBER(H35),IF(N(INDEX('_轮次'!$AL$35:$AW$35,MATCH(H35,'_轮次'!$B$35:$M$35,0)))=0,"—",INDEX('_轮次'!$AL$35:$AW$35,MATCH(H35,'_轮次'!$B$35:$M$35,0))),"—") | M35: =IF(ISNUMBER(H35),IF(H35>'_轮次'!$A$1,"未截止","已截止"),"TBD") | N35: =IF(ISNUMBER(H35),IF(H35>'_轮次'!$A$1,INT(H35-'_轮次'!$A$1),"—"),"—") | O35: May 17-19, 2027 | P35: MONTREAL, CANADA | Q35: 线下 | R35: 必须到场 | S35: 待确认 | T35: 6 | U35: 每轮 | V35: 硬性｜配额 每位作者每轮最多 6 篇（适用于所有作者） | W35: 已核实 | X35: — | Y35: https://sp2027.ieee-security.org/index.html | Z35: 两轮评审，周期长，常需 rebuttal；核查:官网无 CFP 正文，cfp.html 返回 404；重查:2027 CFP 已上线，第二轮 2026-11-17 截稿；每人每轮≤6 篇；全部轮次 First Paper submission deadline:2026-06-12 / Second Paper submission deadline:2026-11-18
A36: 35 | B36: USENIX Security | C36: USENIX Security Symposium | D36: 安全四大顶会之一，以系统安全与漏洞挖掘为主，重真实威胁实证 | E36: 网络与信息安全 | F36: A | G36: =IF(ISNUMBER(H36),IF(N(INDEX('_轮次'!$N$36:$Y$36,MATCH(H36,'_轮次'!$B$36:$M$36,0)))=0,"—",INDEX('_轮次'!$N$36:$Y$36,MATCH(H36,'_轮次'!$B$36:$M$36,0))),"—") | H36: =IF(COUNT('_轮次'!$B$36:$M$36)=0,"待公布",IF(COUNTIF('_轮次'!$B$36:$M$36,">"&'_轮次'!$A$1)>0,SMALL('_轮次'!$B$36:$M$36,COUNTIF('_轮次'!$B$36:$M$36,"<="&'_轮次'!$A$1)+1),MAX('_轮次'!$B$36:$M$36))) | I36: =IF(ISNUMBER(H36),INDEX('_轮次'!$AX$36:$BI$36,MATCH(H36,'_轮次'!$B$36:$M$36,0)),"—") | J36: UTC-12 | K36: =IF(ISNUMBER(H36),IF(N(INDEX('_轮次'!$Z$36:$AK$36,MATCH(H36,'_轮次'!$B$36:$M$36,0)))=0,"—",INDEX('_轮次'!$Z$36:$AK$36,MATCH(H36,'_轮次'!$B$36:$M$36,0))),"—") | L36: =IF(ISNUMBER(H36),IF(N(INDEX('_轮次'!$AL$36:$AW$36,MATCH(H36,'_轮次'!$B$36:$M$36,0)))=0,"—",INDEX('_轮次'!$AL$36:$AW$36,MATCH(H36,'_轮次'!$B$36:$M$36,0))),"—") | M36: =IF(ISNUMBER(H36),IF(H36>'_轮次'!$A$1,"未截止","已截止"),"TBD") | N36: =IF(ISNUMBER(H36),IF(H36>'_轮次'!$A$1,INT(H36-'_轮次'!$A$1),"—"),"—") | O36: August 11-13, 2027 | P36: Denver, CO, USA | Q36: 线下 | R36: 必须到场 | S36: 未提供线上参会 | T36: 7 | U36: 每轮 | V36: 硬性｜配额 7 篇/周期（每位作者各自计，适用于所有作者） | W36: 已核实 | X36: — | Y36: https://www.usenix.org/conference/usenixsecurity27 | Z36: 每年两轮截稿，秋季与春季各一次；核查:两轮制，取第2轮；须全价注册现场报告；全部轮次 Cycle 1 Deadline:2026-08-26 / Cycle 2 Deadline:2027-01-27
A37: 36 | B37: FM | C37: International Symposium on Formal Methods | D37: 形式化方法旗舰会议，聚焦建模验证、定理证明与工业级应用 | E37: 软件工程/系统软件 | F37: A | G37: — | H37: 待公布 | I37: — | J37: AoE | K37: — | L37: 待公布 | M37: =IF(ISNUMBER(H37),IF(H37>'_轮次'!$A$1,"未截止","已截止"),"TBD") | N37: =IF(ISNUMBER(H37),IF(H37>'_轮次'!$A$1,INT(H37-'_轮次'!$A$1),"—"),"—") | O37: October 18-22, 2027 | P37: Athens, Greece | Q37: 线下 | R37: 必须到场 | S37: 不设线上通道 | T37: 不限 | U37: — | V37: CFP未发布 | W37: 2027CFP未发布 | X37: 截稿日、新人条款 | Y37: https://www.fmeurope.org/feature/upcoming_conferences/ | Z37: 核查:FME 仅列 FM 2027 会期 18-22 Oct 2027 Athens，无截稿日
A38: 37 | B38: FSE | C38: ACM International Conference on the Foundations of Software Engineering | D38: 软件工程两大顶会之一，重方法创新与真实工程场景实证 | E38: 软件工程/系统软件 | F38: A | G38: — | H38: 46298.833 | I38: 单轮 | J38: AoE | K38: 46375.833 | L38: 2027-01-22 | M38: =IF(ISNUMBER(H38),IF(H38>'_轮次'!$A$1,"未截止","已截止"),"TBD") | N38: =IF(ISNUMBER(H38),IF(H38>'_轮次'!$A$1,INT(H38-'_轮次'!$A$1),"—"),"—") | O38: July 12-16, 2027 | P38: Shenzhen, China | Q38: 线下 | R38: 必须到场 | S38: 不设线上通道 | T38: 不限 | U38: — | V38: 未找到 | W38: 已核实 | X38: 新人条款 | Y38: https://conf.researchr.org/home/fse-2027 | Z38: 2027 届在深圳举办，国内投稿便利；核查:初审2027-01-22，大修改终审2027-03-31
A39: 38 | B39: ICSE | C39: International Conference on Software Engineering | D39: 软件工程第一大会，覆盖需求到测试全流程，看重实证与影响力 | E39: 软件工程/系统软件 | F39: A | G39: 46197.833 | H39: 46204.833 | I39: Single Submission Cycle Deadline | J39: AoE | K39: 46291.833 | L39: 2026-10-20 | M39: =IF(ISNUMBER(H39),IF(H39>'_轮次'!$A$1,"未截止","已截止"),"TBD") | N39: =IF(ISNUMBER(H39),IF(H39>'_轮次'!$A$1,INT(H39-'_轮次'!$A$1),"—"),"—") | O39: April 25-May 01, 2027 | P39: Dublin, Ireland | Q39: 线下 | R39: 必须到场 | S39: 不设线上通道 | T39: 不限 | U39: — | V39: 未找到 | W39: 已核实 | X39: 新人条款 | Y39: https://conf.researchr.org/home/icse-2027 | Z39: 核查:摘要2026-06-23；大修改论文终审2026-12-18
A40: 39 | B40: ISSTA | C40: ACM SIGSOFT International Symposium on Software Testing and Analysis | D40: 软件测试与分析顶会，偏动态分析、模糊测试与缺陷定位 | E40: 软件工程/系统软件 | F40: A | G40: 46396.833 | H40: 46399.833 | I40: 单轮 | J40: AoE | K40: 46472.833 | L40: 2027-04-20 | M40: =IF(ISNUMBER(H40),IF(H40>'_轮次'!$A$1,"未截止","已截止"),"TBD") | N40: =IF(ISNUMBER(H40),IF(H40>'_轮次'!$A$1,INT(H40-'_轮次'!$A$1),"—"),"—") | O40: September 7-10, 2027 | P40: Singapore | Q40: 线下 | R40: 必须到场 | S40: 不设线上通道 | T40: 不限 | U40: — | V40: 未找到 | W40: 已核实 | X40: 新人条款 | Y40: https://conf.researchr.org/home/issta-2027 | Z40: 常与 ECOOP 等会议联合举办；核查:强制摘要2027-01-08；终审2027-06-17
A41: 40 | B41: OOPSLA | C41: Conference on Object-Oriented Programming Systems, Languages, and Applications | D41: 编程语言与面向对象旗舰，重语言设计、类型系统与实现 | E41: 软件工程/系统软件 | F41: A | G41: =IF(ISNUMBER(H41),IF(N(INDEX('_轮次'!$N$41:$Y$41,MATCH(H41,'_轮次'!$B$41:$M$41,0)))=0,"—",INDEX('_轮次'!$N$41:$Y$41,MATCH(H41,'_轮次'!$B$41:$M$41,0))),"—") | H41: =IF(COUNT('_轮次'!$B$41:$M$41)=0,"待公布",IF(COUNTIF('_轮次'!$B$41:$M$41,">"&'_轮次'!$A$1)>0,SMALL('_轮次'!$B$41:$M$41,COUNTIF('_轮次'!$B$41:$M$41,"<="&'_轮次'!$A$1)+1),MAX('_轮次'!$B$41:$M$41))) | I41: =IF(ISNUMBER(H41),INDEX('_轮次'!$AX$41:$BI$41,MATCH(H41,'_轮次'!$B$41:$M$41,0)),"—") | J41: AoE | K41: =IF(ISNUMBER(H41),IF(N(INDEX('_轮次'!$Z$41:$AK$41,MATCH(H41,'_轮次'!$B$41:$M$41,0)))=0,"—",INDEX('_轮次'!$Z$41:$AK$41,MATCH(H41,'_轮次'!$B$41:$M$41,0))),"—") | L41: =IF(ISNUMBER(H41),IF(N(INDEX('_轮次'!$AL$41:$AW$41,MATCH(H41,'_轮次'!$B$41:$M$41,0)))=0,"—",INDEX('_轮次'!$AL$41:$AW$41,MATCH(H41,'_轮次'!$B$41:$M$41,0))),"—") | M41: =IF(ISNUMBER(H41),IF(H41>'_轮次'!$A$1,"未截止","已截止"),"TBD") | N41: =IF(ISNUMBER(H41),IF(H41>'_轮次'!$A$1,INT(H41-'_轮次'!$A$1),"—"),"—") | O41: October 10-15, 2027 | P41: Prague, Czechia | Q41: 线下 | R41: 必须到场 | S41: 不允许远程报告 | T41: 5 | U41: 每届 | V41: 硬性｜每篇须1名资深作者注册储备审稿人，否则可desk reject | W41: 已核实 | X41: — | Y41: https://2027.splashcon.org/track/splashoopsla2027 | Z41: SPLASH 旗下，PACMPL 期刊式出版；核查:两轮制，R2截稿2027-04-07；每人每轮≤5篇；全部轮次 Submission Deadline Round 1:2026-10-15 / Submission Deadline Round 2:2027-04-08
A42: 41 | B42: OSDI | C42: USENIX Symposium on Operating Systems Design and Implementation | D42: 系统领域顶会，重操作系统与分布式系统的设计实现与实测 | E42: 软件工程/系统软件 | F42: A | G42: 46358.291 | H42: 46365.291 | I42: 单轮 | J42: UTC | K42: — | L42: 2027-03-16 | M42: =IF(ISNUMBER(H42),IF(H42>'_轮次'!$A$1,"未截止","已截止"),"TBD") | N42: =IF(ISNUMBER(H42),IF(H42>'_轮次'!$A$1,INT(H42-'_轮次'!$A$1),"—"),"—") | O42: July 7-9, 2027 | P42: Baltimore, MD, USA | Q42: 线下 | R42: 必须到场 | S42: 无远程，须全额注册 | T42: 8 | U42: 每届 | V42: 硬性｜配额 8 篇（每位作者各自计，适用于所有作者） | W42: 已核实 | X42: — | Y42: https://www.usenix.org/conference/osdi27 | Z42: 与 SOSP 并列系统两大顶会；核查:摘要注册2026-12-01
A43: 42 | B43: PLDI | C43: ACM SIGPLAN Conference on Programming Language Design & Implementation | D43: 程序语言设计与实现顶会，偏编译器、程序分析与性能优化 | E43: 软件工程/系统软件 | F43: A | G43: — | H43: 46339.833 | I43: 单轮 | J43: AoE | K43: 46437.833 | L43: 2027-03-04 | M43: =IF(ISNUMBER(H43),IF(H43>'_轮次'!$A$1,"未截止","已截止"),"TBD") | N43: =IF(ISNUMBER(H43),IF(H43>'_轮次'!$A$1,INT(H43-'_轮次'!$A$1),"—"),"—") | O43: June 5-11, 2027 | P43: Atlanta, Georgia, USA | Q43: 线下 | R43: 必须到场 | S43: 不允许远程报告 | T43: 不限 | U43: — | V43: 硬性｜每篇须 1 名资深作者注册 reserve reviewer（无资深作者可豁免） | W43: 已核实 | X43: — | Y43: https://pldi27.sigplan.org/ | Z43: PACMPL 期刊式出版，一轮大改；核查:终审2027-04-01；重查:CFP 原文：Remote presentations will not be possible
A44: 43 | B44: POPL | C44: ACM SIGPLAN-SIGACT Symposium on Principles of Programming Languages | D44: 程序语言理论最高会，偏类型系统、程序语义与形式化基础 | E44: 软件工程/系统软件 | F44: A | G44: — | H44: 46213.833 | I44: Submission Deadline | J44: AoE | K44: 46276.833 | L44: 46336.833 | M44: =IF(ISNUMBER(H44),IF(H44>'_轮次'!$A$1,"未截止","已截止"),"TBD") | N44: =IF(ISNUMBER(H44),IF(H44>'_轮次'!$A$1,INT(H44-'_轮次'!$A$1),"—"),"—") | O44: January 10-16, 2027 | P44: Mexico City | Q44: 线下 | R44: 允许远程 | S44: 无法到场者提供远程报告选项 | T44: 不限 | U44: — | V44: 硬性｜每篇至少1名资深作者须在TPMS注册储备审稿人 | W44: 已核实 | X44: — | Y44: https://popl27.sigplan.org/ | Z44: PACMPL 期刊式出版，理论门槛高；核查:已明确作者受邀但非必须现场；无摘要截稿
A45: 44 | B45: AAMAS | C45: International Conference on Autonomous Agents and Multiagent Systems | D45: 智能体与多智能体系统主会，覆盖博弈、协作与强化学习 | E45: 人工智能 | F45: B | G45: 46297.833 | H45: 46304.833 | I45: 单轮 | J45: AoE | K45: 46351.833 | L45: 2026-12-21 | M45: =IF(ISNUMBER(H45),IF(H45>'_轮次'!$A$1,"未截止","已截止"),"TBD") | N45: =IF(ISNUMBER(H45),IF(H45>'_轮次'!$A$1,INT(H45-'_轮次'!$A$1),"—"),"—") | O45: May 3-7, 2027 | P45: Hanoi, Vietnam | Q45: 线下 | R45: 待确认 | S45: 待确认 | T45: 不限 | U45: — | V45: 未找到 | W45: 已核实 | X45: 是否到场、新人条款 | Y45: https://warwick.ac.uk/fac/sci/dcs/aamas2027/ | Z45: 另有 JAAMAS 期刊投稿通道；核查:官网列2027主会日期，未写现场报告与远程政策
A46: 45 | B46: COLING | C46: International Conference on Computational Linguistics | D46: 计算语言学老牌会议，偏语言理解、多语处理与语料资源 | E46: 人工智能 | F46: B | G46: =IF(ISNUMBER(H46),IF(N(INDEX('_轮次'!$N$46:$Y$46,MATCH(H46,'_轮次'!$B$46:$M$46,0)))=0,"—",INDEX('_轮次'!$N$46:$Y$46,MATCH(H46,'_轮次'!$B$46:$M$46,0))),"—") | H46: =IF(COUNT('_轮次'!$B$46:$M$46)=0,"待公布",IF(COUNTIF('_轮次'!$B$46:$M$46,">"&'_轮次'!$A$1)>0,SMALL('_轮次'!$B$46:$M$46,COUNTIF('_轮次'!$B$46:$M$46,"<="&'_轮次'!$A$1)+1),MAX('_轮次'!$B$46:$M$46))) | I46: =IF(ISNUMBER(H46),INDEX('_轮次'!$AX$46:$BI$46,MATCH(H46,'_轮次'!$B$46:$M$46,0)),"—") | J46: UTC-12 | K46: =IF(ISNUMBER(H46),IF(N(INDEX('_轮次'!$Z$46:$AK$46,MATCH(H46,'_轮次'!$B$46:$M$46,0)))=0,"—",INDEX('_轮次'!$Z$46:$AK$46,MATCH(H46,'_轮次'!$B$46:$M$46,0))),"—") | L46: =IF(ISNUMBER(H46),IF(N(INDEX('_轮次'!$AL$46:$AW$46,MATCH(H46,'_轮次'!$B$46:$M$46,0)))=0,"—",INDEX('_轮次'!$AL$46:$AW$46,MATCH(H46,'_轮次'!$B$46:$M$46,0))),"—") | M46: =IF(ISNUMBER(H46),IF(H46>'_轮次'!$A$1,"未截止","已截止"),"TBD") | N46: =IF(ISNUMBER(H46),IF(H46>'_轮次'!$A$1,INT(H46-'_轮次'!$A$1),"—"),"—") | O46: May 9-14, 2027 | P46: Macau SAR, China | Q46: 线下 | R46: 允许远程 | S46: 5月6-7日线上虚拟会场 | T46: 不限 | U46: — | V46: 未找到 | W46: 已核实 | X46: 新人条款 | Y46: https://2027.coling-iccl.org/ | Z46: 核查:走ARR 10月轮，12-23需commitment；全部轮次 ARR Submission:2026-10-13 / COLING commitment after ARR meta-reviews; reviewed papers only:2026-12-24
A47: 46 | B47: COLT | C47: Annual Conference on Learning Theory | D47: 学习理论专会，偏泛化界、在线学习与统计学习基础理论 | E47: 人工智能 | F47: B | G47: — | H47: 待公布 | I47: — | J47: AoE | K47: — | L47: 待公布 | M47: =IF(ISNUMBER(H47),IF(H47>'_轮次'!$A$1,"未截止","已截止"),"TBD") | N47: =IF(ISNUMBER(H47),IF(H47>'_轮次'!$A$1,INT(H47-'_轮次'!$A$1),"—"),"—") | O47: June 28 - July 2, 2027 | P47: Tokyo, Japan | Q47: 线下 | R47: 必须到场 | S47: 不设线上通道 | T47: 不限 | U47: — | V47: CFP未发布 | W47: 2027CFP未发布 | X47: 截稿日、新人条款 | Y47: https://learningtheory.org/colt2027/ | Z47: 偏理论，数学功底要求高；核查:仅公布会期6/28-7/2，各截止日均TBD
A48: 47 | B48: ECAI | C48: European Conference on Artificial Intelligence | D48: 欧洲人工智能主会，各方向均收，欧洲学界参与度高 | E48: 人工智能 | F48: B | G48: — | H48: 46492.833 | I48: 单轮 | J48: AoE | K48: 46557.833 | L48: 2027-07-15 | M48: =IF(ISNUMBER(H48),IF(H48>'_轮次'!$A$1,"未截止","已截止"),"TBD") | N48: =IF(ISNUMBER(H48),IF(H48>'_轮次'!$A$1,INT(H48-'_轮次'!$A$1),"—"),"—") | O48: October 2-7, 2027 | P48: Athens, Greece | Q48: 线下 | R48: 待确认 | S48: 待确认 | T48: 不限 | U48: — | V48: 利好｜通道 Doctoral Consortium, STAIRS | W48: 已核实 | X48: 是否到场 | Y48: https://ecai2027.org/ | Z48: 核查:强调in person举办，但未写作者到场硬性要求
A49: 48 | B49: ICAPS | C49: International Conference on Automated Planning and Scheduling | D49: 自动规划与调度专会，覆盖规划算法、调度优化与机器人应用 | E49: 人工智能 | F49: B | G49: 46364.833 | H49: 46371.833 | I49: 单轮 | J49: UTC-12 | K49: 46423.833 | L49: 46445.833 | M49: =IF(ISNUMBER(H49),IF(H49>'_轮次'!$A$1,"未截止","已截止"),"TBD") | N49: =IF(ISNUMBER(H49),IF(H49>'_轮次'!$A$1,INT(H49-'_轮次'!$A$1),"—"),"—") | O49: June 27 - July 2, 2027 | P49: Columbia, SC, USA | Q49: 线下 | R49: 待确认 | S49: 待确认 | T49: 不限 | U49: — | V49: CFP未发布 | W49: 2027CFP未发布 | X49: 是否到场、新人条款 | Y49: https://icaps27.icaps-conference.org/ | Z49: 核查:官网仅有会期地点，无征稿信息
A50: 49 | B50: ICRA | C50: IEEE International Conference on Robotics and Automation | D50: 机器人与自动化规模最大会议，覆盖感知、控制与具身应用 | E50: 人工智能 | F50: B | G50: — | H50: 46282.666 | I50: Extended submission deadline | J50: UTC-8 | K50: — | L50: 46419.833 | M50: =IF(ISNUMBER(H50),IF(H50>'_轮次'!$A$1,"未截止","已截止"),"TBD") | N50: =IF(ISNUMBER(H50),IF(H50>'_轮次'!$A$1,INT(H50-'_轮次'!$A$1),"—"),"—") | O50: May 24-28, 2027 | P50: Seoul, Republic of Korea | Q50: 线下 | R50: 必须到场 | S50: 设卫星会场 | T50: 不限 | U50: — | V50: 未找到 | W50: 已核实 | X50: 新人条款 | Y50: https://2027.ieee-icra.org/ | Z50: 可转投 RA-L，篇幅更短周期更快；核查:已发CFP公告，随文视频9/18-22；正刊截稿未见
A51: 50 | B51: IJCAI | C51: International Joint Conference on Artificial Intelligence | D51: AI 综合顶会，机器学习、推理、多智能体等方向全覆盖 | E51: 人工智能 | F51: B | G51: 46392.833 | H51: 46399.833 | I51: Separate satellite event: August 15-17, 2027, Hengqin, China | J51: AoE | K51: — | L51: 2027-04-21 | M51: =IF(ISNUMBER(H51),IF(H51>'_轮次'!$A$1,"未截止","已截止"),"TBD") | N51: =IF(ISNUMBER(H51),IF(H51>'_轮次'!$A$1,INT(H51-'_轮次'!$A$1),"—"),"—") | O51: August 7-13, 2027 | P51: Kyoto, Japan | Q51: 线下 | R51: 必须到场 | S51: 不设线上通道 | T51: 不限 | U51: — | V51: 未找到 | W51: 已核实 | X51: 新人条款 | Y51: https://2027.ijcai.org/ | Z51: 摘要需提前注册，与 ECAI 为姊妹会；核查:摘要截止2027-01-04；日程页未提参会/篇数政策
A52: 51 | B52: KR | C52: International Conference on Principles of Knowledge Representation and Reasoning | D52: 知识表示与推理专会，偏本体建模、逻辑与非单调推理 | E52: 人工智能 | F52: B | G52: 46501.833 | H52: 46506.833 | I52: Main track; author response period: June 15-18, 2027 | J52: AoE | K52: 46557.833 | L52: 46569.833 | M52: =IF(ISNUMBER(H52),IF(H52>'_轮次'!$A$1,"未截止","已截止"),"TBD") | N52: =IF(ISNUMBER(H52),IF(H52>'_轮次'!$A$1,INT(H52-'_轮次'!$A$1),"—"),"—") | O52: September 21-24, 2027 | P52: Buenos Aires, Argentina | Q52: 线下 | R52: 待确认 | S52: 待确认 | T52: 不限 | U52: — | V52: 未找到 | W52: 未找到 | X52: 是否到场、新人条款 | Y52: https://kr.org/KR2027/ | Z52: 核查:官网仅会议信息无CFP；第三方称截稿2027-04-28
A53: 52 | B53: NAACL | C53: The Annual Conference of the North American Chapter of the Association for Computational Linguistics | D53: 北美计算语言学分会年会，NLP 全方向，经 ARR 滚动评审，重语言分析与多语种 | E53: 人工智能 | F53: B | G53: =IF(ISNUMBER(H53),IF(N(INDEX('_轮次'!$N$53:$Y$53,MATCH(H53,'_轮次'!$B$53:$M$53,0)))=0,"—",INDEX('_轮次'!$N$53:$Y$53,MATCH(H53,'_轮次'!$B$53:$M$53,0))),"—") | H53: =IF(COUNT('_轮次'!$B$53:$M$53)=0,"待公布",IF(COUNTIF('_轮次'!$B$53:$M$53,">"&'_轮次'!$A$1)>0,SMALL('_轮次'!$B$53:$M$53,COUNTIF('_轮次'!$B$53:$M$53,"<="&'_轮次'!$A$1)+1),MAX('_轮次'!$B$53:$M$53))) | I53: =IF(ISNUMBER(H53),INDEX('_轮次'!$AX$53:$BI$53,MATCH(H53,'_轮次'!$B$53:$M$53,0)),"—") | J53: UTC-12 | K53: =IF(ISNUMBER(H53),IF(N(INDEX('_轮次'!$Z$53:$AK$53,MATCH(H53,'_轮次'!$B$53:$M$53,0)))=0,"—",INDEX('_轮次'!$Z$53:$AK$53,MATCH(H53,'_轮次'!$B$53:$M$53,0))),"—") | L53: =IF(ISNUMBER(H53),IF(N(INDEX('_轮次'!$AL$53:$AW$53,MATCH(H53,'_轮次'!$B$53:$M$53,0)))=0,"—",INDEX('_轮次'!$AL$53:$AW$53,MATCH(H53,'_轮次'!$B$53:$M$53,0))),"—") | M53: =IF(ISNUMBER(H53),IF(H53>'_轮次'!$A$1,"未截止","已截止"),"TBD") | N53: =IF(ISNUMBER(H53),IF(H53>'_轮次'!$A$1,INT(H53-'_轮次'!$A$1),"—"),"—") | O53: June 1-5, 2027 | P53: San Francisco, California, USA | Q53: 线下 | R53: 待确认 | S53: 待确认 | T53: 不限 | U53: — | V53: 硬性｜每篇投稿须指定合格 service contributor 并登记 | W53: 已核实 | X53: 是否到场 | Y53: https://2027.naacl.org/ | Z53: 投稿走 ACL Rolling Review，非直接投会议；核查:走ARR，commitment截止2026-12-23；全部轮次 ARR Submission:2026-10-13 / NAACL commitment after ARR meta-reviews; reviewed papers only:2026-12-24
A54: 53 | B54: DCC | C54: Data Compression Conference | D54: 数据压缩专会，无损与有损编码、图像视频压缩、压缩感知，规模小而专 | E54: 图形学与多媒体 | F54: B | G54: — | H54: 46305.624 | I54: 单轮 | J54: PT | K54: — | L54: 46349.833 | M54: =IF(ISNUMBER(H54),IF(H54>'_轮次'!$A$1,"未截止","已截止"),"TBD") | N54: =IF(ISNUMBER(H54),IF(H54>'_轮次'!$A$1,INT(H54-'_轮次'!$A$1),"—"),"—") | O54: March 23-26, 2027 | P54: Snowbird, Utah, United States | Q54: 线下 | R54: 待确认 | S54: 待确认 | T54: 不限 | U54: — | V54: 无专属条款 | W54: 已核实 | X54: 是否到场 | Y54: https://datacompressionconference.org/ | Z54: 单轨小会，常与数据压缩领域工业界合办；核查:由10-02延期至10-09（美太平洋时间）；通知日未公布
A55: 54 | B55: EuroVis | C55: Eurographics Conference on Visualization | D55: 欧洲可视化年会，信息可视化与科学可视化并重，重设计方法与用户实验 | E55: 图形学与多媒体 | F55: B | G55: — | H55: 待公布 | I55: — | J55: AoE | K55: — | L55: 待公布 | M55: =IF(ISNUMBER(H55),IF(H55>'_轮次'!$A$1,"未截止","已截止"),"TBD") | N55: =IF(ISNUMBER(H55),IF(H55>'_轮次'!$A$1,INT(H55-'_轮次'!$A$1),"—"),"—") | O55: May 31-June 4, 2027 | P55: Stuttgart, Germany | Q55: 线下 | R55: 待确认 | S55: 待确认 | T55: 不限 | U55: — | V55: 未找到 | W55: 未找到 | X55: 截稿日、是否到场、新人条款 | Y55: https://eurovis27.github.io/web/ | Z55: 全文经 CGF 期刊轨出版；核查:仅公布workshop/STAR日期，full paper截稿未出
A56: 55 | B56: Eurographics | C56: Eurographics | D56: 欧洲图形学学会年会，渲染、几何、动画、建模全覆盖，图形学欧洲主会 | E56: 图形学与多媒体 | F56: B | G56: 46291.833 | H56: 46297.833 | I56: 单轮 | J56: UTC | K56: 46357.333 | L56: 46428.333 | M56: =IF(ISNUMBER(H56),IF(H56>'_轮次'!$A$1,"未截止","已截止"),"TBD") | N56: =IF(ISNUMBER(H56),IF(H56>'_轮次'!$A$1,INT(H56-'_轮次'!$A$1),"—"),"—") | O56: May 10-14, 2027 | P56: Lucca, Italy | Q56: 线下 | R56: 待确认 | S56: 待确认 | T56: 不限 | U56: — | V56: 未找到 | W56: 未找到 | X56: 是否到场、新人条款 | Y56: https://eg2027.isti.cnr.it/ | Z56: full paper 经 CGF 期刊轨发表；核查:仅见STAR截稿2026-10-19 AoE；full paper页404
A57: 56 | B57: ICASSP | C57: IEEE International Conference on Acoustics, Speech, and Signal Processing | D57: 语音与信号处理旗舰会，声学、语音、音频、阵列信号全覆盖，规模超大 | E57: 图形学与多媒体 | F57: B | G57: — | H57: 46289.833 | I57: 单轮 | J57: UTC-12 | K57: — | L57: 2027-01-13 | M57: =IF(ISNUMBER(H57),IF(H57>'_轮次'!$A$1,"未截止","已截止"),"TBD") | N57: =IF(ISNUMBER(H57),IF(H57>'_轮次'!$A$1,INT(H57-'_轮次'!$A$1),"—"),"—") | O57: May 16-21, 2027 | P57: Toronto, Canada | Q57: 线下 | R57: 必须到场 | S57: 不设线上报告通道 | T57: 不限 | U57: — | V57: 无专属条款 | W57: 已核实 | X57: — | Y57: https://2027.ieeeicassp.org/ | Z57: 接收后需现场报告，缺席可能撤稿；核查:终稿2027-01-27，作者注册2027-02-10
A58: 57 | B58: ICME | C58: The IEEE International Conference on Multimedia & Expo | D58: 多媒体旗舰会之一，多媒体分析、检索、编码与系统，工业界展示环节多 | E58: 图形学与多媒体 | F58: B | G58: — | H58: 46387.833 | I58: 单轮 | J58: AoE | K58: 46451.833 | L58: 2027-03-24 | M58: =IF(ISNUMBER(H58),IF(H58>'_轮次'!$A$1,"未截止","已截止"),"TBD") | N58: =IF(ISNUMBER(H58),IF(H58>'_轮次'!$A$1,INT(H58-'_轮次'!$A$1),"—"),"—") | O58: July 13-17, 2027 | P58: Xiamen, China | Q58: 线下 | R58: 必须到场 | S58: 待确认 | T58: 不限 | U58: — | V58: 无专属条款 | W58: 已核实 | X58: — | Y58: https://2027.ieeeicme.org/ | Z58: 核查:CFP未写到场要求与投稿篇数上限
A59: 58 | B59: ICMR | C59: ACM SIGMM International Conference on Multimedia Retrieval | D59: 多媒体检索专会，跨模态检索、索引与评测，规模中等偏应用 | E59: 图形学与多媒体 | F59: B | G59: — | H59: 46419.833 | I59: 单轮 | J59: UTC-12 | K59: — | L59: 46479.833 | M59: =IF(ISNUMBER(H59),IF(H59>'_轮次'!$A$1,"未截止","已截止"),"TBD") | N59: =IF(ISNUMBER(H59),IF(H59>'_轮次'!$A$1,INT(H59-'_轮次'!$A$1),"—"),"—") | O59: June 7-10, 2027 | P59: Singapore | Q59: 线下 | R59: 待确认 | S59: 待确认 | T59: 不限 | U59: — | V59: CFP未发布 | W59: 2027CFP未发布 | X59: 是否到场、新人条款 | Y59: https://www.icmr2027.org/ | Z59: 核查:官网仅公布会期，CFP页返回404
A60: 59 | B60: InterSpeech | C60: Conference of the International Speech Communication Association | D60: 语音领域第一大会，语音识别、合成、说话人与情感，年会规模大 | E60: 图形学与多媒体 | F60: B | G60: — | H60: 46428.333 | I60: 单轮 | J60: UTC+0 | K60: — | L60: 2027-06-02 | M60: =IF(ISNUMBER(H60),IF(H60>'_轮次'!$A$1,"未截止","已截止"),"TBD") | N60: =IF(ISNUMBER(H60),IF(H60>'_轮次'!$A$1,INT(H60-'_轮次'!$A$1),"—"),"—") | O60: August 29 - September 2, 2027 | P60: São Paulo, Brazil | Q60: 线下 | R60: 必须到场 | S60: 待确认 | T60: 不限 | U60: — | V60: 硬性｜配额 2 篇（每人一作上限） | W60: 已核实 | X60: — | Y60: https://interspeech2027.org/ | Z60: ISCA 主办，每年换城市；核查:CFP页未上线，日期取自官网首页
A61: 60 | B61: SGP | C61: Eurographics Symposium on Geometry Processing | D61: 几何处理专会，网格处理、形状分析与几何深度学习，小圈子高质量 | E61: 图形学与多媒体 | F61: B | G61: — | H61: 待公布 | I61: — | J61: AoE | K61: — | L61: 待公布 | M61: =IF(ISNUMBER(H61),IF(H61>'_轮次'!$A$1,"未截止","已截止"),"TBD") | N61: =IF(ISNUMBER(H61),IF(H61>'_轮次'!$A$1,INT(H61-'_轮次'!$A$1),"—"),"—") | O61: June 21-25, 2027 | P61: Singapore | Q61: 线下 | R61: 待确认 | S61: 待确认 | T61: 不限 | U61: — | V61: CFP未发布 | W61: 2027CFP未发布 | X61: 截稿日、是否到场、新人条款 | Y61: https://igs2027singapore.github.io/ | Z61: 与 CGF 期刊轨联动；核查:IGS2027称SGP另设官网，尚未上线
A62: 61 | B62: SPM | C62: Symposium on Solid and Physical Modeling | D62: 实体与物理建模专会，CAD、几何建模与仿真，偏工程与应用数学结合 | E62: 图形学与多媒体 | F62: B | G62: — | H62: 待公布 | I62: — | J62: AoE | K62: — | L62: 待公布 | M62: =IF(ISNUMBER(H62),IF(H62>'_轮次'!$A$1,"未截止","已截止"),"TBD") | N62: =IF(ISNUMBER(H62),IF(H62>'_轮次'!$A$1,INT(H62-'_轮次'!$A$1),"—"),"—") | O62: June 21-25, 2027 | P62: Singapore | Q62: 线下 | R62: 待确认 | S62: 待确认 | T62: 不限 | U62: — | V62: CFP未发布 | W62: 2027CFP未发布 | X62: 截稿日、是否到场、新人条款 | Y62: https://igs2027singapore.github.io/ | Z62: 常与 SMI 等几何会议同期；核查:IGS2027称SPM另设官网，尚未上线
A63: 62 | B63: CADE | C63: The Conference on Automated Deduction | D63: 自动推理老牌会议，定理证明、形式化方法与 SMT，与 ITP 社区高度重合 | E63: 计算机科学理论 | F63: B | G63: 46434.833 | H63: 46441.833 | I63: 单轮 | J63: AoE | K63: 46508.833 | L63: 2027-05-17 | M63: =IF(ISNUMBER(H63),IF(H63>'_轮次'!$A$1,"未截止","已截止"),"TBD") | N63: =IF(ISNUMBER(H63),IF(H63>'_轮次'!$A$1,INT(H63-'_轮次'!$A$1),"—"),"—") | O63: August 22-25, 2027 | P63: Nijmegen, Netherlands | Q63: 线下 | R63: 待确认 | S63: 待确认 | T63: 不限 | U63: — | V63: 利好｜通道 最佳学生论文奖 | W63: 已核实 | X63: 是否到场 | Y63: https://fscd-cade.science.ru.nl/ | Z63: Springer LNCS 出版；核查:首页时间线2/14、2/21，CFP页为2/15、2/22
A64: 63 | B64: CCC | C64: Computational Complexity Conference | D64: 计算复杂性理论专会，电路下界、证明复杂性与伪随机，纯理论小规模 | E64: 计算机科学理论 | F64: B | G64: — | H64: 待公布 | I64: — | J64: AoE | K64: — | L64: 待公布 | M64: =IF(ISNUMBER(H64),IF(H64>'_轮次'!$A$1,"未截止","已截止"),"TBD") | N64: =IF(ISNUMBER(H64),IF(H64>'_轮次'!$A$1,INT(H64-'_轮次'!$A$1),"—"),"—") | O64: July 19-22, 2027 | P64: Seattle, Washington, USA | Q64: 线下 | R64: 待确认 | S64: 待确认 | T64: 不限 | U64: — | V64: CFP未发布 | W64: 2027CFP未发布 | X64: 截稿日、是否到场、新人条款 | Y64: https://computationalcomplexity.org/ | Z64: 单轨，无 workshop；核查:仅公布会期地点，2027届CFP未发布
A65: 64 | B65: HSCC | C65: International Conference on Hybrid Systems: Computation and Control | D65: 混合系统与控制交叉会，形式化验证、信息物理系统，与 CPS 社区重合 | E65: 计算机科学理论 | F65: B | G65: 46325.833 | H65: 46332.833 | I65: 单轮 | J65: AoE | K65: 46403.833 | L65: 2027-01-28 | M65: =IF(ISNUMBER(H65),IF(H65>'_轮次'!$A$1,"未截止","已截止"),"TBD") | N65: =IF(ISNUMBER(H65),IF(H65>'_轮次'!$A$1,INT(H65-'_轮次'!$A$1),"—"),"—") | O65: May 17-20, 2027 | P65: Boulder, Colorado, USA | Q65: 线下 | R65: 待确认 | S65: 待确认 | T65: 不限 | U65: — | V65: 未找到 | W65: 已核实 | X65: 是否到场、新人条款 | Y65: https://hscc.acm.org/2027/ | Z65: 常与 ICCPS 等合办 CPS-IoT Week；核查:2027与ICCPS合并为HSCC+ICCPS'27，未提参会形式；重查:Authors 页未写到场与新人条款；artifact evaluation 自愿参加
A66: 65 | B66: ICALP | C66: EATCS International Colloquium on Automata, Languages, and Programming | D66: 理论计算机科学欧洲旗舰，算法、复杂度、自动机与逻辑，LIPIcs 开放出版 | E66: 计算机科学理论 | F66: B | G66: — | H66: 46281.833 | I66: Track B first round; Track A and Track B second round TBA | J66: AoE | K66: 46336.833 | L66: 46365.833 | M66: =IF(ISNUMBER(H66),IF(H66>'_轮次'!$A$1,"未截止","已截止"),"TBD") | N66: =IF(ISNUMBER(H66),IF(H66>'_轮次'!$A$1,INT(H66-'_轮次'!$A$1),"—"),"—") | O66: July 5-9, 2027 | P66: Kraków, Poland | Q66: 线下 | R66: 待确认 | S66: 待确认 | T66: 不限 | U66: — | V66: CFP未发布 | W66: 2027CFP未发布 | X66: 是否到场、新人条款 | Y66: https://icalp.uj.edu.pl/ | Z66: 分 Track A/B，LIPIcs 免费开放获取；核查:官网仅公布会期2027-07-05至09及举办地
A67: 66 | B67: SOCG | C67: International Symposium on Computational Geometry | D67: 计算几何专会，几何算法、拓扑与组合几何，常与 ICALP 等联合举办 | E67: 计算机科学理论 | F67: B | G67: — | H67: 待公布 | I67: — | J67: AoE | K67: — | L67: 待公布 | M67: =IF(ISNUMBER(H67),IF(H67>'_轮次'!$A$1,"未截止","已截止"),"TBD") | N67: =IF(ISNUMBER(H67),IF(H67>'_轮次'!$A$1,INT(H67-'_轮次'!$A$1),"—"),"—") | O67: June 21-25, 2027 | P67: Bengaluru, India | Q67: 线下 | R67: 待确认 | S67: 待确认 | T67: 不限 | U67: — | V67: CFP未发布 | W67: 2027CFP未发布 | X67: 截稿日、是否到场、新人条款 | Y67: https://cgweek27.computational-geometry.org/ | Z67: LIPIcs 出版；核查:CG Week 2027会期6/21-25，CFP页404；须CG Society会员
A68: 67 | B68: CIDR | C68: International Conference on Innovative Data Systems Research | D68: 创新数据系统研究，系统与架构新想法优先，单轮评审、偏工业界 | E68: 数据库/数据挖掘 | F68: B | G68: — | H68: 46239.624 | I68: 单轮 | J68: UTC-7 | K68: — | L68: 46302.624 | M68: =IF(ISNUMBER(H68),IF(H68>'_轮次'!$A$1,"未截止","已截止"),"TBD") | N68: =IF(ISNUMBER(H68),IF(H68>'_轮次'!$A$1,INT(H68-'_轮次'!$A$1),"—"),"—") | O68: January 24-27, 2027 | P68: Amsterdam, The Netherlands | Q68: 线下 | R68: 待确认 | S68: 待确认 | T68: 1 | U68: 每届 | V68: 硬性｜配额 1 篇（每位作者上限） | W68: 已核实 | X68: 是否到场 | Y68: https://www.cidrdb.org/cidr2027/ | Z68: 无正式 proceedings，单轮评审、重讨论；核查:官网写明每作者限投1篇，但未列任何截止日期
A69: 68 | B69: DASFAA | C69: Database Systems for Advanced Applications | D69: 亚太数据库旗舰会，数据管理、挖掘与查询优化，Springer LNCS 出版 | E69: 数据库/数据挖掘 | F69: B | G69: — | H69: 46352.833 | I69: Research papers | J69: AoE | K69: — | L69: 2027-01-25 | M69: =IF(ISNUMBER(H69),IF(H69>'_轮次'!$A$1,"未截止","已截止"),"TBD") | N69: =IF(ISNUMBER(H69),IF(H69>'_轮次'!$A$1,INT(H69-'_轮次'!$A$1),"—"),"—") | O69: May 27-30, 2027 | P69: Shenyang, China | Q69: 线下 | R69: 待确认 | S69: 待确认 | T69: 不限 | U69: — | V69: 利好｜通道 Ph.D. Forum, Teen Research Track | W69: 已核实 | X69: 是否到场 | Y69: https://dasfaa2027.github.io/ | Z69: 核查:研究/工业track，AoE23:59；Demo稿12-10截
A70: 69 | B70: ECML-PKDD | C70: European Conference on Machine Learning and 25th Principles and Practice of Knowledge Discovery in Databases | D70: 欧洲机器学习与数据挖掘主会，方法与应用并重，设工业与应用 track | E70: 数据库/数据挖掘 | F70: B | G70: — | H70: 待公布 | I70: — | J70: AoE | K70: — | L70: 待公布 | M70: =IF(ISNUMBER(H70),IF(H70>'_轮次'!$A$1,"未截止","已截止"),"TBD") | N70: =IF(ISNUMBER(H70),IF(H70>'_轮次'!$A$1,INT(H70-'_轮次'!$A$1),"—"),"—") | O70: September 20-24, 2027 | P70: Eindhoven, The Netherlands | Q70: 线下 | R70: 待确认 | S70: 待确认 | T70: 不限 | U70: — | V70: CFP未发布 | W70: 2027CFP未发布 | X70: 截稿日、是否到场、新人条款 | Y70: https://ecmlpkdd.org/2027/ | Z70: Springer LNCS 格式；核查:官网仅标题页，会期2027-08-30至09-03
A71: 70 | B71: EDBT | C71: International Conference on Extending Database Technology | D71: 数据库系统与查询处理老牌会议，偏系统实现与工程验证，与 ICDT 联办 | E71: 数据库/数据挖掘 | F71: B | G71: =IF(ISNUMBER(H71),IF(N(INDEX('_轮次'!$N$71:$Y$71,MATCH(H71,'_轮次'!$B$71:$M$71,0)))=0,"—",INDEX('_轮次'!$N$71:$Y$71,MATCH(H71,'_轮次'!$B$71:$M$71,0))),"—") | H71: =IF(COUNT('_轮次'!$B$71:$M$71)=0,"待公布",IF(COUNTIF('_轮次'!$B$71:$M$71,">"&'_轮次'!$A$1)>0,SMALL('_轮次'!$B$71:$M$71,COUNTIF('_轮次'!$B$71:$M$71,"<="&'_轮次'!$A$1)+1),MAX('_轮次'!$B$71:$M$71))) | I71: =IF(ISNUMBER(H71),INDEX('_轮次'!$AX$71:$BI$71,MATCH(H71,'_轮次'!$B$71:$M$71,0)),"—") | J71: AoE | K71: =IF(ISNUMBER(H71),IF(N(INDEX('_轮次'!$Z$71:$AK$71,MATCH(H71,'_轮次'!$B$71:$M$71,0)))=0,"—",INDEX('_轮次'!$Z$71:$AK$71,MATCH(H71,'_轮次'!$B$71:$M$71,0))),"—") | L71: =IF(ISNUMBER(H71),IF(N(INDEX('_轮次'!$AL$71:$AW$71,MATCH(H71,'_轮次'!$B$71:$M$71,0)))=0,"—",INDEX('_轮次'!$AL$71:$AW$71,MATCH(H71,'_轮次'!$B$71:$M$71,0))),"—") | M71: =IF(ISNUMBER(H71),IF(H71>'_轮次'!$A$1,"未截止","已截止"),"TBD") | N71: =IF(ISNUMBER(H71),IF(H71>'_轮次'!$A$1,INT(H71-'_轮次'!$A$1),"—"),"—") | O71: April 6-9, 2027 | P71: Lille, France | Q71: 线下 | R71: 待确认 | S71: 待确认 | T71: 不限 | U71: — | V71: CFP未发布 | W71: 2027CFP未发布 | X71: 是否到场、新人条款 | Y71: https://edbticdt2027.github.io/ | Z71: 与 ICDT 同期同地举办；核查:仅占位首页，会期2027-04-06至09，无CFP；全部轮次 Official February cutoff is 17:00 PST (UTC-8), represented as the equivalent 13:00 AoE.:2026-02-05 / 轮:2026-06-11 / 轮:2026-10-08
A72: 71 | B72: ICDM | C72: IEEE International Conference on Data Mining | D72: 数据挖掘核心会议，图挖掘、时序、异常检测与大数据应用并重 | E72: 数据库/数据挖掘 | F72: B | G72: — | H72: 46545.833 | I72: Full papers; dates are tentative and subject to change | J72: AoE | K72: — | L72: 2027-08-16 | M72: =IF(ISNUMBER(H72),IF(H72>'_轮次'!$A$1,"未截止","已截止"),"TBD") | N72: =IF(ISNUMBER(H72),IF(H72>'_轮次'!$A$1,INT(H72-'_轮次'!$A$1),"—"),"—") | O72: November 15-18, 2027 | P72: Brisbane, Australia | Q72: 线下 | R72: 待确认 | S72: 待确认 | T72: 不限 | U72: — | V72: 未找到 | W72: 已核实 | X72: 是否到场、新人条款 | Y72: https://icdm2027-website.onrender.com/ | Z72: IEEE 主办，另有短论文与 demo track；核查:日期页已公布，CFP正文标注coming soon
A73: 72 | B73: ICDT | C73: International Conference on Database Theory | D73: 数据库理论专会，查询复杂度、逻辑与数据模型基础研究 | E73: 数据库/数据挖掘 | F73: B | G73: =IF(ISNUMBER(H73),IF(N(INDEX('_轮次'!$N$73:$Y$73,MATCH(H73,'_轮次'!$B$73:$M$73,0)))=0,"—",INDEX('_轮次'!$N$73:$Y$73,MATCH(H73,'_轮次'!$B$73:$M$73,0))),"—") | H73: =IF(COUNT('_轮次'!$B$73:$M$73)=0,"待公布",IF(COUNTIF('_轮次'!$B$73:$M$73,">"&'_轮次'!$A$1)>0,SMALL('_轮次'!$B$73:$M$73,COUNTIF('_轮次'!$B$73:$M$73,"<="&'_轮次'!$A$1)+1),MAX('_轮次'!$B$73:$M$73))) | I73: =IF(ISNUMBER(H73),INDEX('_轮次'!$AX$73:$BI$73,MATCH(H73,'_轮次'!$B$73:$M$73,0)),"—") | J73: AoE | K73: =IF(ISNUMBER(H73),IF(N(INDEX('_轮次'!$Z$73:$AK$73,MATCH(H73,'_轮次'!$B$73:$M$73,0)))=0,"—",INDEX('_轮次'!$Z$73:$AK$73,MATCH(H73,'_轮次'!$B$73:$M$73,0))),"—") | L73: =IF(ISNUMBER(H73),IF(N(INDEX('_轮次'!$AL$73:$AW$73,MATCH(H73,'_轮次'!$B$73:$M$73,0)))=0,"—",INDEX('_轮次'!$AL$73:$AW$73,MATCH(H73,'_轮次'!$B$73:$M$73,0))),"—") | M73: =IF(ISNUMBER(H73),IF(H73>'_轮次'!$A$1,"未截止","已截止"),"TBD") | N73: =IF(ISNUMBER(H73),IF(H73>'_轮次'!$A$1,INT(H73-'_轮次'!$A$1),"—"),"—") | O73: April 6-9, 2027 | P73: Lille, France | Q73: 线下 | R73: 待确认 | S73: 待确认 | T73: 不限 | U73: — | V73: CFP未发布 | W73: 2027CFP未发布 | X73: 是否到场、新人条款 | Y73: https://edbticdt2027.github.io/ | Z73: LIPIcs 开放获取出版；核查:官网仅落地页，无CFP入口；全部轮次 轮:2026-03-11 / 轮:2026-09-11
A74: 73 | B74: PODS | C74: ACM Symposium on Principles of Database Systems | D74: 数据库理论最权威会议，查询语言语义、复杂度与数据模型理论 | E74: 数据库/数据挖掘 | F74: B | G74: =IF(ISNUMBER(H74),IF(N(INDEX('_轮次'!$N$74:$Y$74,MATCH(H74,'_轮次'!$B$74:$M$74,0)))=0,"—",INDEX('_轮次'!$N$74:$Y$74,MATCH(H74,'_轮次'!$B$74:$M$74,0))),"—") | H74: =IF(COUNT('_轮次'!$B$74:$M$74)=0,"待公布",IF(COUNTIF('_轮次'!$B$74:$M$74,">"&'_轮次'!$A$1)>0,SMALL('_轮次'!$B$74:$M$74,COUNTIF('_轮次'!$B$74:$M$74,"<="&'_轮次'!$A$1)+1),MAX('_轮次'!$B$74:$M$74))) | I74: =IF(ISNUMBER(H74),INDEX('_轮次'!$AX$74:$BI$74,MATCH(H74,'_轮次'!$B$74:$M$74,0)),"—") | J74: AoE | K74: =IF(ISNUMBER(H74),IF(N(INDEX('_轮次'!$Z$74:$AK$74,MATCH(H74,'_轮次'!$B$74:$M$74,0)))=0,"—",INDEX('_轮次'!$Z$74:$AK$74,MATCH(H74,'_轮次'!$B$74:$M$74,0))),"—") | L74: =IF(ISNUMBER(H74),IF(N(INDEX('_轮次'!$AL$74:$AW$74,MATCH(H74,'_轮次'!$B$74:$M$74,0)))=0,"—",INDEX('_轮次'!$AL$74:$AW$74,MATCH(H74,'_轮次'!$B$74:$M$74,0))),"—") | M74: =IF(ISNUMBER(H74),IF(H74>'_轮次'!$A$1,"未截止","已截止"),"TBD") | N74: =IF(ISNUMBER(H74),IF(H74>'_轮次'!$A$1,INT(H74-'_轮次'!$A$1),"—"),"—") | O74: June 13-19, 2027 | P74: Huntington Beach, California, USA | Q74: 线下 | R74: 待确认 | S74: 待确认 | T74: 不限 | U74: — | V74: 未找到 | W74: 已核实 | X74: 是否到场、新人条款 | Y74: https://2027.sigmod.org/ | Z74: 与 SIGMOD 同期同地举办；核查:两轮制，此为第2轮周期；第1轮5月已过；全部轮次 First Submission Cycle:2026-05-31 / Second Submission Cycle:2026-12-11
A75: 74 | B75: RecSys | C75: ACM Conference on Recommender Systems | D75: 推荐系统唯一专属顶会，工业大规模推荐与评测方法并重 | E75: 数据库/数据挖掘 | F75: B | G75: — | H75: 待公布 | I75: — | J75: AoE | K75: — | L75: 待公布 | M75: =IF(ISNUMBER(H75),IF(H75>'_轮次'!$A$1,"未截止","已截止"),"TBD") | N75: =IF(ISNUMBER(H75),IF(H75>'_轮次'!$A$1,INT(H75-'_轮次'!$A$1),"—"),"—") | O75: August 23-27, 2027 | P75: Honolulu, O‘ahu, Hawaii, USA | Q75: 线下 | R75: 待确认 | S75: 待确认 | T75: 不限 | U75: — | V75: CFP未发布 | W75: 2027CFP未发布 | X75: 截稿日、是否到场、新人条款 | Y75: https://recsys.acm.org/recsys27/ | Z75: 含 industrial track 与 Challenge；核查:官网仅会议信息，CFP页404
A76: 75 | B76: WSDM | C76: International Conference on Web Search and Data Mining | D76: 网页搜索与数据挖掘交叉会议，检索、图学习与用户行为建模 | E76: 数据库/数据挖掘 | F76: B | G76: 46252.833 | H76: 46259.833 | I76: Full Paper | J76: UTC-12 | K76: — | L76: 2026-11-02 | M76: =IF(ISNUMBER(H76),IF(H76>'_轮次'!$A$1,"未截止","已截止"),"TBD") | N76: =IF(ISNUMBER(H76),IF(H76>'_轮次'!$A$1,INT(H76-'_轮次'!$A$1),"—"),"—") | O76: February 15 - 19, 2027 | P76: Cordis, Hong Kong SAR, China | Q76: 线下 | R76: 必须到场 | S76: 不设远程，需他人代讲 | T76: 10 | U76: 每届 | V76: 硬性｜配额 10 篇（每作者全文上限） | W76: 已核实 | X76: — | Y76: https://wsdm-conference.org/2027/ | Z76: 接收率偏低，偏重实证与工业数据；核查:摘要8月17日已过；正文截稿为2026-08-24
A77: 76 | B77: DATE | C77: Design, Automation & Test in Europe | D77: 欧洲设计自动化旗舰会，EDA、嵌入式系统与测试可靠性 | E77: 体系结构/并行/存储 | F77: B | G77: 46279.833 | H77: 46286.833 | I77: 单轮 | J77: AoE | K77: — | L77: 2026-11-23 | M77: =IF(ISNUMBER(H77),IF(H77>'_轮次'!$A$1,"未截止","已截止"),"TBD") | N77: =IF(ISNUMBER(H77),IF(H77>'_轮次'!$A$1,INT(H77-'_轮次'!$A$1),"—"),"—") | O77: March 22-24, 2027 | P77: Dresden, Germany | Q77: 线下 | R77: 待确认 | S77: 待确认 | T77: 不限 | U77: — | V77: 利好｜通道 Young People Programme：PhD Forum、Student Teams Fair、University Fair、Career Fair、Mentoring | W77: 已核实 | X77: 是否到场 | Y77: https://www.date-conference.com/date-2027-call-papers | Z77: 双栏 6 页，含 design/EDA/test；核查:9月13日注册摘要，9月20日全文截稿
A78: 77 | B78: FPGA | C78: ACM/SIGDA International Symposium on Field-Programmable Gate Arrays | D78: FPGA 领域第一会议，体系结构、EDA 工具与硬件加速应用 | E78: 体系结构/并行/存储 | F78: B | G78: 46297.833 | H78: 46304.833 | I78: 单轮 | J78: UTC-12 | K78: 46342.833 | L78: 2026-11-24 | M78: =IF(ISNUMBER(H78),IF(H78>'_轮次'!$A$1,"未截止","已截止"),"TBD") | N78: =IF(ISNUMBER(H78),IF(H78>'_轮次'!$A$1,INT(H78-'_轮次'!$A$1),"—"),"—") | O78: March 14 - March 16, 2027 | P78: Monterey, California, USA | Q78: 线下 | R78: 必须到场 | S78: 旅行受限可特殊安排 | T78: 不限 | U78: — | V78: 无专属条款 | W78: 已核实 | X78: — | Y78: https://www.isfpga.org/ | Z78: ACM/SIGDA 主办，规模小接收率低；核查:摘要10月1日；正文10月8日，均无延期
A79: 78 | B79: HiPEAC | C79: International Conference on High Performance and Embedded Architectures and Compilers | D79: 高性能与嵌入式体系结构、编译器交叉会议，欧洲社区年会 | E79: 体系结构/并行/存储 | F79: B | G79: — | H79: 46175.833 | I79: 单轮 | J79: AoE | K79: — | L79: 2026-11-15 | M79: =IF(ISNUMBER(H79),IF(H79>'_轮次'!$A$1,"未截止","已截止"),"TBD") | N79: =IF(ISNUMBER(H79),IF(H79>'_轮次'!$A$1,INT(H79-'_轮次'!$A$1),"—"),"—") | O79: January 18-20, 2027 | P79: Glasgow, Scotland, UK | Q79: 线下 | R79: 待确认 | S79: 待确认 | T79: 不限 | U79: — | V79: 无专属条款 | W79: 已核实 | X79: 是否到场 | Y79: https://www.hipeac.net/2027/glasgow/#/call-for-papers/ | Z79: 与 HiPEAC 年会同期，偏体系结构与编译；核查:journal-first 模式，投稿ACM TACO；6/1前投稿方可入选2027
A80: 79 | B80: ICDCS | C80: IEEE International Conference on Distributed Computing Systems | D80: 分布式系统老牌会议，共识容错、边缘计算与云系统 | E80: 体系结构/并行/存储 | F80: B | G80: — | H80: 待公布 | I80: — | J80: AoE | K80: — | L80: 待公布 | M80: =IF(ISNUMBER(H80),IF(H80>'_轮次'!$A$1,"未截止","已截止"),"TBD") | N80: =IF(ISNUMBER(H80),IF(H80>'_轮次'!$A$1,INT(H80-'_轮次'!$A$1),"—"),"—") | O80: July 5-8, 2027 | P80: Melbourne, Australia | Q80: 线下 | R80: 待确认 | S80: 待确认 | T80: 不限 | U80: — | V80: CFP未发布 | W80: 2027CFP未发布 | X80: 截稿日、是否到场、新人条款 | Y80: https://icdcs2027.icdcs.org/ | Z80: IEEE 主办，含 poster/demo；核查:官网仅公布会期2027-07-05至08，所有日期TBD
A81: 80 | B81: ICS | C81: ACM International Conference on Supercomputing | D81: 超级计算与高性能计算会议，并行算法、性能建模与加速器 | E81: 体系结构/并行/存储 | F81: B | G81: 46358.833 | H81: 46364.833 | I81: 单轮 | J81: AoE | K81: — | L81: 2027-03-12 | M81: =IF(ISNUMBER(H81),IF(H81>'_轮次'!$A$1,"未截止","已截止"),"TBD") | N81: =IF(ISNUMBER(H81),IF(H81>'_轮次'!$A$1,INT(H81-'_轮次'!$A$1),"—"),"—") | O81: TBD | P81: Atlanta, Georgia, USA | Q81: 线下 | R81: 待确认 | S81: 待确认 | T81: 不限 | U81: — | V81: 硬性｜无审稿义务（Junior PC 自愿自荐） | W81: 已核实 | X81: 是否到场 | Y81: https://ics-conference.org/index.html | Z81: ACM SIGARCH 主办，与 HPC 社区重合；核查:摘要2026-12-01；早期拒稿2027-02-11
A82: 81 | B82: IEEE/ACM CGO | C82: The International Symposium on Code Generation and Optimization | D82: 代码生成与编译优化专会，JIT、ML 编译器与自动调优 | E82: 体系结构/并行/存储 | F82: B | G82: =IF(ISNUMBER(H82),IF(N(INDEX('_轮次'!$N$82:$Y$82,MATCH(H82,'_轮次'!$B$82:$M$82,0)))=0,"—",INDEX('_轮次'!$N$82:$Y$82,MATCH(H82,'_轮次'!$B$82:$M$82,0))),"—") | H82: =IF(COUNT('_轮次'!$B$82:$M$82)=0,"待公布",IF(COUNTIF('_轮次'!$B$82:$M$82,">"&'_轮次'!$A$1)>0,SMALL('_轮次'!$B$82:$M$82,COUNTIF('_轮次'!$B$82:$M$82,"<="&'_轮次'!$A$1)+1),MAX('_轮次'!$B$82:$M$82))) | I82: =IF(ISNUMBER(H82),INDEX('_轮次'!$AX$82:$BI$82,MATCH(H82,'_轮次'!$B$82:$M$82,0)),"—") | J82: AoE | K82: =IF(ISNUMBER(H82),IF(N(INDEX('_轮次'!$Z$82:$AK$82,MATCH(H82,'_轮次'!$B$82:$M$82,0)))=0,"—",INDEX('_轮次'!$Z$82:$AK$82,MATCH(H82,'_轮次'!$B$82:$M$82,0))),"—") | L82: =IF(ISNUMBER(H82),IF(N(INDEX('_轮次'!$AL$82:$AW$82,MATCH(H82,'_轮次'!$B$82:$M$82,0)))=0,"—",INDEX('_轮次'!$AL$82:$AW$82,MATCH(H82,'_轮次'!$B$82:$M$82,0))),"—") | M82: =IF(ISNUMBER(H82),IF(H82>'_轮次'!$A$1,"未截止","已截止"),"TBD") | N82: =IF(ISNUMBER(H82),IF(H82>'_轮次'!$A$1,INT(H82-'_轮次'!$A$1),"—"),"—") | O82: March 20-24, 2027 | P82: Salt Lake City, Utah, USA | Q82: 线下 | R82: 待确认 | S82: 待确认 | T82: 不限 | U82: — | V82: 未找到 | W82: 已核实 | X82: 是否到场、新人条款 | Y82: https://conf.researchr.org/home/cgo-2027 | Z82: 编译器方向核心会议，规模较小；核查:两轮投稿：R1截稿2026-06-11、通知2026-08-03；全部轮次 First Submission:2026-06-12 / Second Submission:2026-09-11
A83: 82 | B83: IPDPS | C83: IEEE International Parallel and Distributed Processing Symposium | D83: 并行与分布式处理主会，HPC、GPU 加速与大规模系统 | E83: 体系结构/并行/存储 | F83: B | G83: 46297.833 | H83: 46304.833 | I83: 单轮 | J83: AoE | K83: 46360.833 | L83: 2027-02-02 | M83: =IF(ISNUMBER(H83),IF(H83>'_轮次'!$A$1,"未截止","已截止"),"TBD") | N83: =IF(ISNUMBER(H83),IF(H83>'_轮次'!$A$1,INT(H83-'_轮次'!$A$1),"—"),"—") | O83: June 1-5, 2027 | P83: Seattle, USA | Q83: 线下 | R83: 必须到场 | S83: 待确认 | T83: 8 | U83: 每届 | V83: 无专属条款 | W83: 已核实 | X83: — | Y83: https://www.ipdps.org/ | Z83: IEEE 主办，含 workshop 与 PhD forum；核查:摘要2026-10-01；同作者限投8篇；正文强调现场报告
A84: 83 | B84: ISCAS | C84: IEEE International Symposium on Circuits and Systems | D84: 电路与系统旗舰会，模拟数字电路、信号处理与 VLSI 设计 | E84: 体系结构/并行/存储 | F84: B | G84: — | H84: 46322.541 | I84: 单轮 | J84: UTC-5 | K84: — | L84: 待公布 | M84: =IF(ISNUMBER(H84),IF(H84>'_轮次'!$A$1,"未截止","已截止"),"TBD") | N84: =IF(ISNUMBER(H84),IF(H84>'_轮次'!$A$1,INT(H84-'_轮次'!$A$1),"—"),"—") | O84: June 6-9, 2027 | P84: Bordeaux, France | Q84: 线下 | R84: 待确认 | S84: 待确认 | T84: 不限 | U84: — | V84: CFP未发布 | W84: 2027CFP未发布 | X84: 是否到场、新人条款 | Y84: https://2027.ieee-iscas.org/ | Z84: IEEE CAS 主办，规模极大，审稿周期短；核查:官网仅有会期2027-06-06至09，无截稿信息
A85: 84 | B85: MSST | C85: International Conference on Massive Storage Systems and Technology | D85: 大规模存储系统与技术会议，闪存、硬盘与分布式存储架构 | E85: 体系结构/并行/存储 | F85: B | G85: — | H85: 待公布 | I85: — | J85: AoE | K85: — | L85: 待公布 | M85: =IF(ISNUMBER(H85),IF(H85>'_轮次'!$A$1,"未截止","已截止"),"TBD") | N85: =IF(ISNUMBER(H85),IF(H85>'_轮次'!$A$1,INT(H85-'_轮次'!$A$1),"—"),"—") | O85: May 17-21, 2027 | P85: TBD | Q85: 线下 | R85: 待确认 | S85: 待确认 | T85: 不限 | U85: — | V85: CFP未发布 | W85: 2027CFP未发布 | X85: 截稿日、是否到场、新人条款 | Y85: https://www.msstconference.org/ | Z85: 2027 举办地点尚未公布；核查:仅公布会期2027-05-17至21，官网仍为MSST 2026内容
A86: 85 | B86: RTAS | C86: IEEE Real-Time and Embedded Technology and Applications Symposium | D86: 实时与嵌入式系统应用会议，实时调度、时序分析与信息物理系统 | E86: 体系结构/并行/存储 | F86: B | G86: — | H86: 46332.833 | I86: Submission Deadline (Firm) | J86: AoE | K86: 46403.833 | L86: 2027-01-28 | M86: =IF(ISNUMBER(H86),IF(H86>'_轮次'!$A$1,"未截止","已截止"),"TBD") | N86: =IF(ISNUMBER(H86),IF(H86>'_轮次'!$A$1,INT(H86-'_轮次'!$A$1),"—"),"—") | O86: May 17-20, 2027 | P86: Boulder, Colorado | Q86: 线下 | R86: 必须到场 | S86: 不允许预录视频报告 | T86: 不限 | U86: — | V86: 硬性｜投稿时每位作者须填 ORCID iD | W86: 已核实 | X86: — | Y86: https://2027.rtas.org/ | Z86: 与 CPS-IoT Week 同期举办；核查:截稿2026-11-05(AoE, firm)；通知日官网标注 tentative；重查:未现场报告的论文将从 IEEE Xplore 撤除
A87: 86 | B87: SIGMETRICS | C87: ACM Special Interest Group on Measurement and Evaluation | D87: 系统性能测量与建模旗舰会，重排队论调度与云资源实测 | E87: 体系结构/并行/存储 | F87: B | G87: =IF(ISNUMBER(H87),IF(N(INDEX('_轮次'!$N$87:$Y$87,MATCH(H87,'_轮次'!$B$87:$M$87,0)))=0,"—",INDEX('_轮次'!$N$87:$Y$87,MATCH(H87,'_轮次'!$B$87:$M$87,0))),"—") | H87: =IF(COUNT('_轮次'!$B$87:$M$87)=0,"待公布",IF(COUNTIF('_轮次'!$B$87:$M$87,">"&'_轮次'!$A$1)>0,SMALL('_轮次'!$B$87:$M$87,COUNTIF('_轮次'!$B$87:$M$87,"<="&'_轮次'!$A$1)+1),MAX('_轮次'!$B$87:$M$87))) | I87: =IF(ISNUMBER(H87),INDEX('_轮次'!$AX$87:$BI$87,MATCH(H87,'_轮次'!$B$87:$M$87,0)),"—") | J87: AoE | K87: =IF(ISNUMBER(H87),IF(N(INDEX('_轮次'!$Z$87:$AK$87,MATCH(H87,'_轮次'!$B$87:$M$87,0)))=0,"—",INDEX('_轮次'!$Z$87:$AK$87,MATCH(H87,'_轮次'!$B$87:$M$87,0))),"—") | L87: =IF(ISNUMBER(H87),IF(N(INDEX('_轮次'!$AL$87:$AW$87,MATCH(H87,'_轮次'!$B$87:$M$87,0)))=0,"—",INDEX('_轮次'!$AL$87:$AW$87,MATCH(H87,'_轮次'!$B$87:$M$87,0))),"—") | M87: =IF(ISNUMBER(H87),IF(H87>'_轮次'!$A$1,"未截止","已截止"),"TBD") | N87: =IF(ISNUMBER(H87),IF(H87>'_轮次'!$A$1,INT(H87-'_轮次'!$A$1),"—"),"—") | O87: June 7-11, 2027 | P87: Atlanta, Georgia, USA | Q87: 线下 | R87: 必须到场 | S87: 待确认 | T87: 不限 | U87: — | V87: 无专属条款 | W87: 已核实 | X87: — | Y87: https://www.sigmetrics.org/sigmetrics2027/ | Z87: 常与 Performance 合办；核查:三轮投稿制，夏/秋轮已过，末轮截稿2027-01-11；全部轮次 summer round:2026-07-11 / fall round:2026-10-10 / winter round:2027-01-12
A88: 87 | B88: SPAA | C88: ACM Symposium on Parallelism in Algorithms and Architectures | D88: 并行与分布式算法理论会议，关注算法复杂度、下界与并行计算模型 | E88: 体系结构/并行/存储 | F88: B | G88: =IF(ISNUMBER(H88),IF(N(INDEX('_轮次'!$N$88:$Y$88,MATCH(H88,'_轮次'!$B$88:$M$88,0)))=0,"—",INDEX('_轮次'!$N$88:$Y$88,MATCH(H88,'_轮次'!$B$88:$M$88,0))),"—") | H88: =IF(COUNT('_轮次'!$B$88:$M$88)=0,"待公布",IF(COUNTIF('_轮次'!$B$88:$M$88,">"&'_轮次'!$A$1)>0,SMALL('_轮次'!$B$88:$M$88,COUNTIF('_轮次'!$B$88:$M$88,"<="&'_轮次'!$A$1)+1),MAX('_轮次'!$B$88:$M$88))) | I88: =IF(ISNUMBER(H88),INDEX('_轮次'!$AX$88:$BI$88,MATCH(H88,'_轮次'!$B$88:$M$88,0)),"—") | J88: AoE | K88: =IF(ISNUMBER(H88),IF(N(INDEX('_轮次'!$Z$88:$AK$88,MATCH(H88,'_轮次'!$B$88:$M$88,0)))=0,"—",INDEX('_轮次'!$Z$88:$AK$88,MATCH(H88,'_轮次'!$B$88:$M$88,0))),"—") | L88: =IF(ISNUMBER(H88),IF(N(INDEX('_轮次'!$AL$88:$AW$88,MATCH(H88,'_轮次'!$B$88:$M$88,0)))=0,"—",INDEX('_轮次'!$AL$88:$AW$88,MATCH(H88,'_轮次'!$B$88:$M$88,0))),"—") | M88: =IF(ISNUMBER(H88),IF(H88>'_轮次'!$A$1,"未截止","已截止"),"TBD") | N88: =IF(ISNUMBER(H88),IF(H88>'_轮次'!$A$1,INT(H88-'_轮次'!$A$1),"—"),"—") | O88: June 5 - June 11, 2027 | P88: Atlanta, GA, USA | Q88: 线下 | R88: 待确认 | S88: 待确认 | T88: 不限 | U88: — | V88: 无专属条款 | W88: 已核实 | X88: 是否到场 | Y88: https://spaa.acm.org/ | Z88: 理论会议，纯证明型投稿为主；核查:两轮投稿，第二轮截稿2027-01-29；CFP日期未标年份；全部轮次 Cycle 1:2026-09-26 / Cycle 2:2027-01-30
A89: 88 | B89: GROUP | C89: ACM International Conference on Supporting Group Work | D89: 面向群体协作的支持协同工作会议，兼收社会计算研究 | E89: 人机交互与普适计算 | F89: B | G89: =IF(ISNUMBER(H89),IF(N(INDEX('_轮次'!$N$89:$Y$89,MATCH(H89,'_轮次'!$B$89:$M$89,0)))=0,"—",INDEX('_轮次'!$N$89:$Y$89,MATCH(H89,'_轮次'!$B$89:$M$89,0))),"—") | H89: =IF(COUNT('_轮次'!$B$89:$M$89)=0,"待公布",IF(COUNTIF('_轮次'!$B$89:$M$89,">"&'_轮次'!$A$1)>0,SMALL('_轮次'!$B$89:$M$89,COUNTIF('_轮次'!$B$89:$M$89,"<="&'_轮次'!$A$1)+1),MAX('_轮次'!$B$89:$M$89))) | I89: =IF(ISNUMBER(H89),INDEX('_轮次'!$AX$89:$BI$89,MATCH(H89,'_轮次'!$B$89:$M$89,0)),"—") | J89: AoE | K89: =IF(ISNUMBER(H89),IF(N(INDEX('_轮次'!$Z$89:$AK$89,MATCH(H89,'_轮次'!$B$89:$M$89,0)))=0,"—",INDEX('_轮次'!$Z$89:$AK$89,MATCH(H89,'_轮次'!$B$89:$M$89,0))),"—") | L89: =IF(ISNUMBER(H89),IF(N(INDEX('_轮次'!$AL$89:$AW$89,MATCH(H89,'_轮次'!$B$89:$M$89,0)))=0,"—",INDEX('_轮次'!$AL$89:$AW$89,MATCH(H89,'_轮次'!$B$89:$M$89,0))),"—") | M89: =IF(ISNUMBER(H89),IF(H89>'_轮次'!$A$1,"未截止","已截止"),"TBD") | N89: =IF(ISNUMBER(H89),IF(H89>'_轮次'!$A$1,INT(H89-'_轮次'!$A$1),"—"),"—") | O89: January 10-13, 2027 | P89: St Simons Island, Georgia, USA | Q89: 线下 | R89: 待确认 | S89: 待确认 | T89: 不限 | U89: — | V89: 未找到 | W89: 已核实 | X89: 是否到场、新人条款 | Y89: https://group.acm.org/conferences/group27/ | Z89: 论文现多刊于 PACM HCI；核查:两轮投稿均已截止；官网称线下举办但未明示作者到场要求；全部轮次 Full Paper First Wave Submissions:2025-07-16 / Full Paper Second Wave Submissions (extended):2026-04-01
A90: 89 | B90: ICWSM | C90: The International AAAI Conference on Web and Social Media | D90: 网络与社交媒体研究会议，社交网络分析、计算社会科学与信息扩散 | E90: 人机交互与普适计算 | F90: B | G90: =IF(ISNUMBER(H90),IF(N(INDEX('_轮次'!$N$90:$Y$90,MATCH(H90,'_轮次'!$B$90:$M$90,0)))=0,"—",INDEX('_轮次'!$N$90:$Y$90,MATCH(H90,'_轮次'!$B$90:$M$90,0))),"—") | H90: =IF(COUNT('_轮次'!$B$90:$M$90)=0,"待公布",IF(COUNTIF('_轮次'!$B$90:$M$90,">"&'_轮次'!$A$1)>0,SMALL('_轮次'!$B$90:$M$90,COUNTIF('_轮次'!$B$90:$M$90,"<="&'_轮次'!$A$1)+1),MAX('_轮次'!$B$90:$M$90))) | I90: =IF(ISNUMBER(H90),INDEX('_轮次'!$AX$90:$BI$90,MATCH(H90,'_轮次'!$B$90:$M$90,0)),"—") | J90: AoE | K90: =IF(ISNUMBER(H90),IF(N(INDEX('_轮次'!$Z$90:$AK$90,MATCH(H90,'_轮次'!$B$90:$M$90,0)))=0,"—",INDEX('_轮次'!$Z$90:$AK$90,MATCH(H90,'_轮次'!$B$90:$M$90,0))),"—") | L90: =IF(ISNUMBER(H90),IF(N(INDEX('_轮次'!$AL$90:$AW$90,MATCH(H90,'_轮次'!$B$90:$M$90,0)))=0,"—",INDEX('_轮次'!$AL$90:$AW$90,MATCH(H90,'_轮次'!$B$90:$M$90,0))),"—") | M90: =IF(ISNUMBER(H90),IF(H90>'_轮次'!$A$1,"未截止","已截止"),"TBD") | N90: =IF(ISNUMBER(H90),IF(H90>'_轮次'!$A$1,INT(H90-'_轮次'!$A$1),"—"),"—") | O90: TBD | P90: Edinburgh, Scotland | Q90: 线下 | R90: 待确认 | S90: 待确认 | T90: 不限 | U90: — | V90: CFP未发布 | W90: 2027CFP未发布 | X90: 是否到场、新人条款 | Y90: https://www.icwsm.org/2027/ | Z90: AAAI 主办，数据集类论文另设 track；核查:2027主页仅介绍，无投稿日期；CFP子页404；全部轮次 1st Full-paper Deadline:2026-05-16 / 2nd Full-paper Deadline:2026-09-16 / 3rd Full-paper Deadline:2027-01-16
A91: 90 | B91: IUI | C91: ACM Conference on Intelligent User Interfaces | D91: 智能用户界面会议，推荐与自适应界面、人机协同的智能交互研究 | E91: 人机交互与普适计算 | F91: B | G91: 46248.833 | H91: 46255.833 | I91: 单轮 | J91: AoE | K91: 46332.833 | L91: 2026-11-23 | M91: =IF(ISNUMBER(H91),IF(H91>'_轮次'!$A$1,"未截止","已截止"),"TBD") | N91: =IF(ISNUMBER(H91),IF(H91>'_轮次'!$A$1,INT(H91-'_轮次'!$A$1),"—"),"—") | O91: February 8-11, 2027 | P91: Helsinki, Finland | Q91: 线下 | R91: 必须到场 | S91: 待确认 | T91: 不限 | U91: — | V91: 无专属条款 | W91: 已核实 | X91: — | Y91: https://iui.hosting.acm.org/2027/ | Z91: 偏 HCI，重用户研究与人机协作实验；核查:截稿2026-08-20已过；须至少一位作者注册并现场报告
A92: 91 | B92: MobileHCI | C92: ACM International Conference on Mobile Human-Computer Interaction | D92: 移动人机交互会议，移动端交互技术、情境感知与在野可用性研究 | E92: 人机交互与普适计算 | F92: B | G92: 46429.833 | H92: 46436.833 | I92: 单轮 | J92: AoE | K92: — | L92: 2027-04-15 | M92: =IF(ISNUMBER(H92),IF(H92>'_轮次'!$A$1,"未截止","已截止"),"TBD") | N92: =IF(ISNUMBER(H92),IF(H92>'_轮次'!$A$1,INT(H92-'_轮次'!$A$1),"—"),"—") | O92: September 20-23, 2027 | P92: Limassol, Cyprus | Q92: 线下 | R92: 待确认 | S92: 待确认 | T92: 不限 | U92: — | V92: 硬性｜投稿即视为同意参与审稿 | W92: 已核实 | X92: 是否到场 | Y92: https://mobilehci.acm.org/2027/ | Z92: 与 MobileHCI 系列同源的 SIGCHI 会议；核查:摘要2027-02-10；仅要求至少一位作者全额注册，最终通知06-17
A93: 92 | B93: PerCom | C93: IEEE International Conference on Pervasive Computing and Communications | D93: 普适计算与通信会议，感知、边缘计算、可穿戴与移动系统研究 | E93: 人机交互与普适计算 | F93: B | G93: 46277.833 | H93: 46284.833 | I93: Extended deadlines | J93: AoE | K93: 46354.833 | L93: 2026-12-18 | M93: =IF(ISNUMBER(H93),IF(H93>'_轮次'!$A$1,"未截止","已截止"),"TBD") | N93: =IF(ISNUMBER(H93),IF(H93>'_轮次'!$A$1,INT(H93-'_轮次'!$A$1),"—"),"—") | O93: March 8-12, 2027 | P93: Goa, India | Q93: 线下 | R93: 必须到场 | S93: 仅签证/健康等特殊情形例外 | T93: 不限 | U93: — | V93: 无专属条款 | W93: 已核实 | X93: — | Y93: https://percom.org/ | Z93: IEEE 主办，含 workshop 与 demo；核查:截稿由9/11延至9/18 AoE；禁远程与预录视频
A94: 93 | B94: ISMB | C94: International Conference on Intelligent Systems for Molecular Biology | D94: 计算生物学与生物信息学旗舰会，序列分析、结构与系统生物学方法 | E94: 交叉/综合/新兴 | F94: B | G94: — | H94: 46402.833 | I94: Proceedings; conditional acceptance: March 2, 2027; revised papers due: March 18, 2027, 23:59 AoE; no extensions to submission or revision deadlines | J94: AoE | K94: — | L94: 46477.833 | M94: =IF(ISNUMBER(H94),IF(H94>'_轮次'!$A$1,"未截止","已截止"),"TBD") | N94: =IF(ISNUMBER(H94),IF(H94>'_轮次'!$A$1,INT(H94-'_轮次'!$A$1),"—"),"—") | O94: July 18-22, 2027 | P94: Copenhagen, Denmark | Q94: 线下 | R94: 必须到场 | S94: 提供线上参会 | T94: 不限 | U94: — | V94: CFP未发布 | W94: 2027CFP未发布 | X94: 新人条款 | Y94: https://www.iscb.org/ismbeccb2027/ | Z94: Proceedings 刊于 Bioinformatics；核查:Key Dates页栏目为空；官网称线下+线上双轨
A95: 94 | B95: MICCAI | C95: International Conference on Medical Image Computing and Computer Assisted Intervention | D95: 医学影像计算与辅助介入顶会，分割配准与临床落地 | E95: 交叉/综合/新兴 | F95: B | G95: — | H95: 待公布 | I95: — | J95: UTC-8 | K95: — | L95: 待公布 | M95: =IF(ISNUMBER(H95),IF(H95>'_轮次'!$A$1,"未截止","已截止"),"TBD") | N95: =IF(ISNUMBER(H95),IF(H95>'_轮次'!$A$1,INT(H95-'_轮次'!$A$1),"—"),"—") | O95: September 26 - October 1, 2027 | P95: Auckland, New Zealand | Q95: 线下 | R95: 必须到场 | S95: 待确认 | T95: 不限 | U95: — | V95: CFP未发布 | W95: 2027CFP未发布 | X95: 截稿日、新人条款 | Y95: https://conferences.miccai.org/2027/en/ | Z95: Springer LNCS 出版，另设 challenges；核查:仅公布会期9/27-10/1，CFP页404未上线
A96: 95 | B96: RECOMB | C96: International Conference on Research inComputational Molecular Biology | D96: 计算分子生物学会议，基因组算法、序列比对与组合生物学方法 | E96: 交叉/综合/新兴 | F96: B | G96: 46324.833 | H96: 46331.833 | I96: 单轮 | J96: AoE | K96: — | L96: 46379.833 | M96: =IF(ISNUMBER(H96),IF(H96>'_轮次'!$A$1,"未截止","已截止"),"TBD") | N96: =IF(ISNUMBER(H96),IF(H96>'_轮次'!$A$1,INT(H96-'_轮次'!$A$1),"—"),"—") | O96: May 17-20, 2027 | P96: Toronto, Canada | Q96: 线下 | R96: 待确认 | S96: 待确认 | T96: 不限 | U96: — | V96: CFP未发布 | W96: 2027CFP未发布 | X96: 是否到场、新人条款 | Y96: https://recomb.org/recomb2027/ | Z96: 论文常刊于 JCB 或 LNBI，会议另有摘要 track；核查:仅见会期2027-05-17至20，截稿未公布
A97: 96 | B97: CoNEXT | C97: International Conference on Emerging Networking Experiments and Technologies | D97: 新兴网络实验与技术会议，网络架构、可编程数据平面与测量实证 | E97: 计算机网络 | F97: B | G97: =IF(ISNUMBER(H97),IF(N(INDEX('_轮次'!$N$97:$Y$97,MATCH(H97,'_轮次'!$B$97:$M$97,0)))=0,"—",INDEX('_轮次'!$N$97:$Y$97,MATCH(H97,'_轮次'!$B$97:$M$97,0))),"—") | H97: =IF(COUNT('_轮次'!$B$97:$M$97)=0,"待公布",IF(COUNTIF('_轮次'!$B$97:$M$97,">"&'_轮次'!$A$1)>0,SMALL('_轮次'!$B$97:$M$97,COUNTIF('_轮次'!$B$97:$M$97,"<="&'_轮次'!$A$1)+1),MAX('_轮次'!$B$97:$M$97))) | I97: =IF(ISNUMBER(H97),INDEX('_轮次'!$AX$97:$BI$97,MATCH(H97,'_轮次'!$B$97:$M$97,0)),"—") | J97: AoE | K97: =IF(ISNUMBER(H97),IF(N(INDEX('_轮次'!$Z$97:$AK$97,MATCH(H97,'_轮次'!$B$97:$M$97,0)))=0,"—",INDEX('_轮次'!$Z$97:$AK$97,MATCH(H97,'_轮次'!$B$97:$M$97,0))),"—") | L97: =IF(ISNUMBER(H97),IF(N(INDEX('_轮次'!$AL$97:$AW$97,MATCH(H97,'_轮次'!$B$97:$M$97,0)))=0,"—",INDEX('_轮次'!$AL$97:$AW$97,MATCH(H97,'_轮次'!$B$97:$M$97,0))),"—") | M97: =IF(ISNUMBER(H97),IF(H97>'_轮次'!$A$1,"未截止","已截止"),"TBD") | N97: =IF(ISNUMBER(H97),IF(H97>'_轮次'!$A$1,INT(H97-'_轮次'!$A$1),"—"),"—") | O97: December 6-9, 2027 (To be confirmed) | P97: Rio de Janeiro, Brazil | Q97: 线下 | R97: 必须到场 | S97: 待确认 | T97: 不限 | U97: — | V97: 无专属条款 | W97: 已核实 | X97: — | Y97: https://conferences.sigcomm.org/co-next/2027/#!/home | Z97: 核查:两轮截稿(12/4、2027-06-04)；未提现场要求；全部轮次 December Cycle:2026-12-05 / June Cycle:2027-06-05
A98: 97 | B98: IMC | C98: ACM Internet Measurement Conference | D98: 互联网测量会议，测量方法、流量分析、基础设施与隐私实证研究 | E98: 计算机网络 | F98: B | G98: =IF(ISNUMBER(H98),IF(N(INDEX('_轮次'!$N$98:$Y$98,MATCH(H98,'_轮次'!$B$98:$M$98,0)))=0,"—",INDEX('_轮次'!$N$98:$Y$98,MATCH(H98,'_轮次'!$B$98:$M$98,0))),"—") | H98: =IF(COUNT('_轮次'!$B$98:$M$98)=0,"待公布",IF(COUNTIF('_轮次'!$B$98:$M$98,">"&'_轮次'!$A$1)>0,SMALL('_轮次'!$B$98:$M$98,COUNTIF('_轮次'!$B$98:$M$98,"<="&'_轮次'!$A$1)+1),MAX('_轮次'!$B$98:$M$98))) | I98: =IF(ISNUMBER(H98),INDEX('_轮次'!$AX$98:$BI$98,MATCH(H98,'_轮次'!$B$98:$M$98,0)),"—") | J98: AoE | K98: =IF(ISNUMBER(H98),IF(N(INDEX('_轮次'!$Z$98:$AK$98,MATCH(H98,'_轮次'!$B$98:$M$98,0)))=0,"—",INDEX('_轮次'!$Z$98:$AK$98,MATCH(H98,'_轮次'!$B$98:$M$98,0))),"—") | L98: =IF(ISNUMBER(H98),IF(N(INDEX('_轮次'!$AL$98:$AW$98,MATCH(H98,'_轮次'!$B$98:$M$98,0)))=0,"—",INDEX('_轮次'!$AL$98:$AW$98,MATCH(H98,'_轮次'!$B$98:$M$98,0))),"—") | M98: =IF(ISNUMBER(H98),IF(H98>'_轮次'!$A$1,"未截止","已截止"),"TBD") | N98: =IF(ISNUMBER(H98),IF(H98>'_轮次'!$A$1,INT(H98-'_轮次'!$A$1),"—"),"—") | O98: Oct 25-29, 2027 | P98: Atlanta, GA, USA | Q98: 线下 | R98: 必须到场 | S98: 待确认 | T98: 不限 | U98: — | V98: 利好｜通道 最佳学生论文奖（限学生一作） | W98: 已核实 | X98: — | Y98: https://conferences.sigcomm.org/imc/2027/ | Z98: 偏实测数据，鼓励公开数据集与代码；核查:两轮截稿(11/17、2027-04-07)；未提现场要求；全部轮次 Cycle 1; rebuttal period January 26-February 2, 2027:2026-11-18 / Cycle 2:2027-04-08
A99: 98 | B99: MobiSys | C99: ACM International Conference on Mobile Systems, Applications, and Services | D99: 移动系统会议，移动端操作系统与应用，强调真实部署 | E99: 计算机网络 | F99: B | G99: 46354.833 | H99: 46361.833 | I99: 单轮 | J99: AoE | K99: 46431.833 | L99: 2027-03-06 | M99: =IF(ISNUMBER(H99),IF(H99>'_轮次'!$A$1,"未截止","已截止"),"TBD") | N99: =IF(ISNUMBER(H99),IF(H99>'_轮次'!$A$1,INT(H99-'_轮次'!$A$1),"—"),"—") | O99: June 21-25, 2027 | P99: Ho Chi Minh City, Vietnam | Q99: 线下 | R99: 必须到场 | S99: 待确认 | T99: 不限 | U99: — | V99: 利好｜须1位作者以非学生费率注册 | W99: 已核实 | X99: — | Y99: https://www.sigmobile.org/mobisys/2027/ | Z99: 重视原型系统与在野实测；核查:须至少一位作者按非学生费率注册并现场报告
A100: 99 | B100: NOSSDAV | C100: International Workshop on Network and Operating System Support for Digital Audio and Video | D100: 音视频网络与系统支持研讨会，流媒体与低延迟传输 | E100: 计算机网络 | F100: B | G100: — | H100: 46399.833 | I100: 单轮 | J100: AoE | K100: — | L100: 2027-02-01 | M100: =IF(ISNUMBER(H100),IF(H100>'_轮次'!$A$1,"未截止","已截止"),"TBD") | N100: =IF(ISNUMBER(H100),IF(H100>'_轮次'!$A$1,INT(H100-'_轮次'!$A$1),"—"),"—") | O100: TBD | P100: Ghent, Belgium | Q100: 线下 | R100: 待确认 | S100: 待确认 | T100: 不限 | U100: — | V100: 无专属条款 | W100: 已核实 | X100: 是否到场 | Y100: https://nossdav.org/ | Z100: workshop 规模小，接收短文；核查:单轨工作坊；截稿日原文未标年份
...

Sheet 扩展规则
A1: 序号 | B1: 简称 | C1: CCF | D1: 页数限制 | E1: 盲审 | F1: 投稿系统 | G1: CORE | H1: THCPL | I1: 作者投稿上限（原文） | J1: 官网核查 | K1: 核查依据 | L1: 备注
A2: 1 | B2: AAAI | C2: A | D2: 7 页正文 + refs | E2: 双盲 | F2: OpenReview | G2: A* | H2: A | I2: 不限 | J2: 已核实 | K2: https://aaai.org/conference/aaai/aaai-27/ | L2: 近年投稿量极大，录取率约 20% 上下；核查:摘要07-21，全文07-28；日程页未写宣讲与远程政策
A3: 2 | B3: ACL | C3: A | D3: 8 页长文 / 4 页短文 + refs | E3: 双盲 | F3: OpenReview | G3: A* | H3: A | I3: 不限 | J3: 已核实 | K3: https://2027.aclweb.org/calls/main/ | L3: 经 ACL Rolling Review 提交，再承诺至会议；核查:须至少一位作者注册并宣讲；录用通知日TBD
A4: 3 | B4: CVPR | C4: A | D4: 8 页 + refs | E4: 双盲 | F4: OpenReview | G4: A* | H4: A | I4: 不限 | J4: 已核实 | K4: https://cvpr.thecvf.com/Conferences/2027/CallForPapers | L4: 每年 11 月截稿，6 月开会；核查:论文注册11-10；CFP未明写现场宣讲要求
A5: 4 | B5: ICCV | C5: A | D5: 8 页 + refs | E5: 双盲 | F5: OpenReview | G5: A* | H5: A | I5: 不限 | J5: 2027CFP未发布 | K5: https://iccv.thecvf.com/Conferences/2027 | L5: 奇数年举办，2027 届正常召开；核查:官网仅公布时间地点(10/3-7)，CFP未出
A6: 5 | B6: ICLR | C6: A | D6: 9 页正文 + refs/附录 | E6: 双盲 | F6: OpenReview | G6: A* | H6: A | I6: 20 篇 | J6: 已核实 | K6: https://iclr.cc/Conferences/2027/AuthorGuidelines | L6: 评审意见与讨论全程公开；核查:署名≥3篇须审6篇；出席形式未明示
A7: 6 | B7: ACM SIGGRAPH | C7: A | D7: 待确认 | E7: 待确认 | F7: 官网自建 | G7: A* | H7: A | I7: 不限 | J7: 2027CFP未发布 | K7: https://s2027.siggraph.org/ | L7: 分技术论文与 Art Papers 等多轨道；核查:第三方站点称Stage1为2027-01-21，官网未见
A8: 7 | B8: IEEE VR | C8: A | D8: 8 页 + refs | E8: 双盲 | F8: OpenReview | G8: A* | H8: A | I8: 不限 | J8: 已核实 | K8: https://ieeevr.org/2027/contribute/papers | L8: 期刊轨与会议轨并行，TVCG 出版；核查:截稿已过(2026-08-31)；资深作者须任审稿人
A9: 8 | B9: CAV | C9: A | D9: 待确认 | E9: 单盲 | F9: 待确认 | G9: A* | H9: A | I9: 5 篇 | J9: 已核实 | K9: https://conferences.i-cav.org/2027/cfp/ | L9: LNCS 出版，另设 artifact 评审；核查:全文2027-01-20；每作者限投5篇（含三类）
A10: 9 | B10: LICS | C10: A | D10: 待确认 | E10: 单盲 | F10: 待确认 | G10: A* | H10: A | I10: 不限 | J10: 2027CFP未发布 | K10: https://lics.siglog.org/lics27/ | L10: 常与 ICALP 等逻辑类会议联办；核查:官网仅占位页，注明信息稍后公布
A11: 10 | B11: SODA | C11: A | D11: 待确认 | E11: 单盲 | F11: EasyChair | G11: A* | H11: A | I11: 不限 | J11: 已核实 | K11: https://www.siam.org/conferences-events/siam-conferences/soda27/submissions/ | L11: 与 ALENEX/ANALCO 同期同地举办；核查:录用通知仅写2026年10月，无具体日
A12: 11 | B12: STOC | C12: A | D12: 待确认 | E12: 单盲 | F12: 待确认 | G12: A* | H12: A | I12: 5 篇 | J12: 已核实 | K12: https://acm-stoc.org/stoc2027/stoc2027-cfp.html | L12: 与 FOCS 并列为理论两大顶会；核查:强制公开发布投稿并提交20-30分钟视频
A13: 12 | B13: ICDE | C13: A | D13: 6 页 + refs | E13: 待确认 | F13: 待确认 | G13: A* | H13: A | I13: 不限 | J13: 已核实 | K13: https://icde2027.github.io/important-dates.html | L13: IEEE 主办，分研究轨与工业轨；核查:研究主会两轮，第一轮2026-06-11已截；全部轮次 first round:2026-06-12 / second round:2026-11-12
... A201: 200 | B201: SATML | C201: N | D201: 待确认 | E201: 双盲 | F201: OpenReview | G201: N | H201: N | I201: 不限 | J201: 已核实 | K201: https://satml.org/call-for-papers | L201: IEEE 主办，安全与ML交叉，含竞赛 track；核查:摘要注册2026-09-22必填

Sheet 新人作者要求
A1: 序号 | B1: 简称 | C1: CCF | D1: 方向 | E1: 条款状态 | F1: 对首投的影响 | G1: 首投可投篇数 | H1: 审稿义务 / 互惠审稿 | I1: 首投配额 | J1: 资深作者要求 | K1: 投稿账号门槛 | L1: 学生 / 新人通道 | M1: 费用与资助 | N1: 依据 URL | O1: 置信度 | P1: 备注
A2: 1 | B2: AAAI | C2: A | D2: 人工智能 | E2: 未找到 | F2: 未找到 | G2: 不限 | H2: 未找到 | I2: 未找到 | J2: 待确认 | K2: 未找到 | L2: 未找到 | M2: 未找到 | N2: https://aaai.org/conference/aaai/aaai-27/ | O2: 低 | P2: 站点仅发布日程；作者政策页重定向至往届 AAAI-25
A3: 2 | B3: ACL | C3: A | D3: 人工智能 | E3: 未找到 | F3: 未找到 | G3: 不限 | H3: 未找到 | I3: 未找到 | J3: 待确认 | K3: 未找到 | L3: 未找到 | M3: 未找到 | N3: https://2027.aclweb.org/calls/main/ | O3: 低 | P3: 站点仅上线主会 CFP；审稿与 SRW 政策走 ARR，未发布
A4: 3 | B4: CVPR | C4: A | D4: 人工智能 | E4: 有专属条款 | F4: 有硬性要求 | G4: 不限 | H4: 全体作者须应召担任审稿人，豁免须事前申请 | I4: 无 | J4: 不强制 | K4: 需 OpenReview 档案；无机构邮箱审核约 2 周 | L4: 无 | M4: 未提及 | N4: https://cvpr.thecvf.com/Conferences/2027/CallForPapers | O4: 高 | P4: Mandatory Reviewer Service，依 PAMI 技术委员会指引
A5: 4 | B5: ICCV | C5: A | D5: 人工智能 | E5: CFP未发布 | F5: CFP未发布 | G5: CFP未发布 | H5: CFP未发布 | I5: CFP未发布 | J5: CFP未发布 | K5: CFP未发布 | L5: CFP未发布 | M5: CFP未发布 | N5: — | O5: 高
A6: 5 | B6: ICLR | C6: A | D6: 人工智能 | E6: 有专属条款 | F6: 有硬性要求 | G6: 1 篇（无合格互惠审稿人时）；全体上限 20 篇/届 | H6: 须指定作者注册审稿≥3 篇，否则直接拒稿 | I6: 1 篇（无合格互惠审稿人时） | J6: 不强制 | K6: 须 OpenReview 档案；无机构邮箱审核约 2 周 | L6: 无 | M6: 未提及 | N6: https://iclr.cc/Conferences/2027/AuthorGuidelines | O6: 高 | P6: 单人最多 20 篇；3 篇以上作者须审 ≥6 篇
A7: 6 | B7: ACM SIGGRAPH | C7: A | D7: 图形学与多媒体 | E7: CFP未发布 | F7: CFP未发布 | G7: CFP未发布 | H7: CFP未发布 | I7: CFP未发布 | J7: CFP未发布 | K7: CFP未发布 | L7: CFP未发布 | M7: CFP未发布 | N7: — | O7: 高
A8: 7 | B8: IEEE VR | C8: A | D8: 图形学与多媒体 | E8: 有专属条款 | F8: 有硬性要求 | G8: 不限 | H8: 资深作者须注册审稿，评审数≥投稿数，失责可拒稿 | I8: 无 | J8: 不强制 | K8: 走 PCS 投稿；资深作者须在 PCS 注册审稿 | L8: 无 | M8: 未提及 | N8: https://ieeevr.org/2027/contribute/papers | O8: 高 | P8: 资深=有 PhD 或同等资历；无资深作者亦须指派人
A9: 8 | B9: CAV | C9: A | D9: 计算机科学理论 | E9: 无专属条款 | F9: 无 | G9: 5 篇/届 | H9: 无审稿义务 | I9: 无 | J9: 不强制 | K9: 无门槛 | L9: 无 | M9: 未提及 | N9: https://conferences.i-cav.org/2027/cfp/ | O9: 中 | P9: 仅全体作者统一 5 篇上限，无新人专属条款
A10: 9 | B10: LICS | C10: A | D10: 计算机科学理论 | E10: CFP未发布 | F10: CFP未发布 | G10: CFP未发布 | H10: CFP未发布 | I10: CFP未发布 | J10: CFP未发布 | K10: CFP未发布 | L10: CFP未发布 | M10: CFP未发布 | N10: — | O10: 高
A11: 10 | B11: SODA | C11: A | D11: 计算机科学理论 | E11: 有专属条款 | F11: 只有利好通道 | G11: 不限 | H11: 无审稿义务 | I11: 无 | J11: 不强制 | K11: 无门槛 | L11: 最佳学生论文奖（全学生作者可评） | M11: SIAM 通用差旅资助，10/26 截止 | N11: https://www.siam.org/conferences-events/siam-conferences/soda27/submissions/ | O11: 中 | P11: 无页数限制；学生相关活动见 Special Events 页
A12: 11 | B12: STOC | C12: A | D12: 计算机科学理论 | E12: 有专属条款 | F12: 有硬性要求 | G12: 5 篇/届 | H12: 无审稿义务 | I12: 5 篇（每位作者各自计，适用于所有作者） | J12: 不强制 | K12: 录用后须 ORCID ID | L12: 最佳学生论文奖（Danny Lewin） | M12: SIGACT 学生及发展中国家差旅资助 | N12: https://acm-stoc.org/stoc2027/stoc2027-cfp.html | O12: 高 | P12: 非匿名评审；作者须为人类
A13: 12 | B13: ICDE | C13: A | D13: 数据库/数据挖掘 | E13: 有专属条款 | F13: 有硬性要求 | G13: 5 篇（每轮，研究轨道） | H13: 无审稿义务 | I13: 5 篇（每轮，研究轨道） | J13: 不强制 | K13: 全体作者须 ORCID 及 CMT 档案，缺则拒稿 | L13: Ph.D. Symposium | M13: 未提及 | N13: https://icde2027.github.io/submission-guidelines.html | O13: 高 | P13: 两轮投稿，每轮只给接受/拒绝，无修订
A14: 13 | B14: SIGIR | C14: A | D14: 数据库/数据挖掘 | E14: 有专属条款 | F14: 只有利好通道 | G14: 不限 | H14: 未找到 | I14: 未找到 | J14: 待确认 | K14: 未找到 | L14: Doctoral Consortium | M14: 学生及研究者 travel grants（50 周年） | N14: https://sigir2027.org/ | O14: 中 | P14: 论文 CFP 与审稿政策尚未上线，仅首页零散信息
A15: 14 | B15: SIGKDD | C15: A | D15: 数据库/数据挖掘 | E15: 有专属条款 | F15: 有硬性要求 | G15: 7 篇/届 | H15: 须提名 1 名合格审稿人（KDD 等≥3 篇） | I15: 7 篇（研究轨道，每周期） | J15: 不强制 | K15: 全体作者须完整 OpenReview 档案，缺则拒稿 | L15: 无 | M15: 未提及；注册须标准（非学生）价 | N15: https://kdd2027.kdd.org/research-track-call-for-papers/ | O15: 高 | P15: 档案须含机构、DBLP、ORCID、导师与论文
A16: 15 | B16: SIGMOD | C16: A | D16: 数据库/数据挖掘 | E16: 未找到 | F16: 未找到 | G16: 10 篇/届 | H16: 未找到 | I16: 未找到 | J16: 待确认 | K16: 未找到 | L16: 未找到 | M16: 未找到 | N16: https://2027.sigmod.org/calls_papers_important_dates.shtml | O16: 低 | P16: 仅有日程页；calls_papers 征稿政策页返回 404
A17: 16 | B17: VLDB | C17: A | D17: 数据库/数据挖掘 | E17: 有专属条款 | F17: 有硬性要求 | G17: 12 篇/年（每月≤2） | H17: 须提名 1 名合格审稿人（VLDB 等≥2 篇） | I17: 每月 2 篇，全年 12 篇 | J17: 不强制 | K17: 全体作者须 CMT 注册并申报冲突，否则拒稿 | L17: 无 | M17: 未提及 | N17: https://vldb.org/pvldb/volumes/20/submission | O17: 高 | P17: 提名审稿人失责，全体作者年上限各减 1 篇
A18: 17 | B18: ASPLOS | C18: A | D18: 体系结构/并行/存储 | E18: 无专属条款 | F18: 无 | G18: 4 篇/届 | H18: 无审稿义务 | I18: 无 | J18: 不强制 | K18: 无门槛 | L18: 无 | M18: 未提及 | N18: https://www.asplos-conference.org/asplos2027/cfp/ | O18: 高 | P18: CFP全文无A-F条款；仅全局限每人每周期4篇
A19: 18 | B19: DAC | C19: A | D19: 体系结构/并行/存储 | E19: 无专属条款 | F19: 无 | G19: 不限 | H19: 无审稿义务 | I19: 无 | J19: 不强制 | K19: 无门槛 | L19: 无 | M19: 未提及 | N19: https://dac.com/2027/authors/call-for-contributions | O19: 中 | P19: Tracks页与研究稿页均无新人/学生及审稿义务条款
A20: 19 | B20: EuroSys | C20: A | D20: 体系结构/并行/存储 | E20: 无专属条款 | F20: 无 | G20: 3 篇/届 | H20: 无审稿义务 | I20: 无 | J20: 不强制 | K20: 无门槛 | L20: 无 | M20: 未提及 | N20: https://2027.eurosys.org/cfp.html | O20: 高 | P20: CFP无A-F条款；仅全局限每人每周期3篇
A21: 20 | B21: FAST | C21: A | D21: 体系结构/并行/存储 | E21: 有专属条款 | F21: 只有利好通道 | G21: 不限 | H21: 无审稿义务 | I21: 无 | J21: 不强制 | K21: 无门槛 | L21: WIP/Posters、Mentoring（均设联合主席） | M21: 每篇须一名作者全价注册（非学生价） | N21: https://www.usenix.org/conference/fast27/call-for-papers | O21: 中 | P21: 无学生注册优惠；经济困难可邮件申请
A22: 21 | B22: HPCA | C22: A | D22: 体系结构/并行/存储 | E22: 有专属条款 | F22: 有硬性要求 | G22: 不限 | H22: 每篇须指定资深作者，或须任Light PC审稿≤6篇 | I22: 无 | J22: 必须挂资深作者 | K22: 无门槛 | L22: 无 | M22: 未提及 | N22: https://sigarch.org/call-contributions/hpca-2027 | O22: 高 | P22: 无资深作者将无人可被派审稿，属硬门槛
... A25: 24 | B25: CHI | C25: A | D25: 人机交互与普适计算 | E25: 有专属条款 | F25: 有硬性要求 | G25: 不限 | H25: 每篇须提名4人次审稿（RRP），须满足最低审稿资格 | I25: 无 | J25: 不强制 | K25: 须ORCID，PCS档案填DBLP，邮箱有效 | L25: 无 | M25: 未提及 | N25: https://chi2027.acm.org/authors/papers/ | O25: 高 | P25: 未达审稿资格者须靠资深合作者凑4份；作者名单冻结
A26: 25 | B26: UbiComp/ISWC | C26: A | D26: 人机交互与普适计算 | E26: CFP未发布 | F26: CFP未发布 | G26: CFP未发布 | H26: CFP未发布 | I26: CFP未发布 | J26: CFP未发布 | K26: CFP未发布 | L26: CFP未发布 | M26: CFP未发布 | N26: — | O26: 高
A27: 26 | B27: WWW | C27: A | D27: 交叉/综合/新兴 | E27: 有专属条款 | F27: 有硬性要求 | G27: 7 篇/届 | H27: 作者须加入审稿委员会并按时审稿，否则可被拒 | I27: 无 | J27: 不强制 | K27: 所有作者须完善OpenReview档案与COI | L27: 无 | M27: 论文须非学生标准现场注册，每篇一次 | N27: https://www2027.thewebconf.org/research-track-papers/ | O27: 高 | P27: 全局限每类投稿7篇；学生价不能覆盖论文
A28: 27 | B28: INFOCOM | C28: A | D28: 计算机网络 | E28: 未找到 | F28: 未找到 | G28: 不限 | H28: 未找到 | I28: 无 | J28: 待确认 | K28: 未找到 | L28: 未找到 | M28: 未提及 | N28: https://infocom2027.ieee-infocom.org/authors | O28: 低 | P28: Authors页仅列日期，CFP称细则另发，未见审稿/配额条款
A29: 28 | B29: MobiCom | C29: A | D29: 计算机网络 | E29: 有专属条款 | F29: 只有利好通道 | G29: 不限 | H29: 未找到 | I29: 无 | J29: 待确认 | K29: 未找到 | L29: ACM Student Research Competition（poster） | M29: 未提及 | N29: https://www.sigmobile.org/mobicom/2027/ | O29: 中 | P29: 仅主页可读，/cfp/与/call-for-papers/均404
A30: 29 | B30: NSDI | C30: A | D30: 计算机网络 | E30: 有专属条款 | F30: 只有利好通道 | G30: 8 篇/届 | H30: 无审稿义务 | I30: 无 | J30: 不强制 | K30: 无门槛 | L30: 无 | M30: 每篇须一名作者全价注册（非学生价） | N30: https://www.usenix.org/conference/nsdi27/call-for-papers | O30: 高 | P30: 学生无法用学生价覆盖论文；全局限8篇
A31: 30 | B31: SIGCOMM | C31: A | D31: 计算机网络 | E31: 有专属条款 | F31: 有硬性要求 | G31: 8 篇/届 | H31: 每篇须报一名互惠审稿作者，一般须具博士学位 | I31: 无 | J31: 不强制 | K31: 投稿须填ORCID | L31: 无 | M31: 未提及 | N31: https://conferences.sigcomm.org/sigcomm/2027/cfp/ | O31: 高 | P31: 无博士级互惠审稿人的独立作者最受限；全局限8篇
A32: 31 | B32: CCS | C32: A | D32: 网络与信息安全 | E32: CFP未发布 | F32: CFP未发布 | G32: CFP未发布 | H32: CFP未发布 | I32: CFP未发布 | J32: CFP未发布 | K32: CFP未发布 | L32: CFP未发布 | M32: CFP未发布 | N32: — | O32: 高
A33: 32 | B33: EUROCRYPT | C33: A | D33: 网络与信息安全 | E33: 无专属条款 | F33: 无 | G33: 不限 | H33: 无审稿义务 | I33: 无 | J33: 不强制 | K33: 无门槛 | L33: 无 | M33: 未提及 | N33: https://eurocrypt.iacr.org/2027/papersubmission.php | O33: 中 | P33: 通读投稿页：仅匿名、格式、COI要求，无A–F条款
A34: 33 | B34: NDSS | C34: A | D34: 网络与信息安全 | E34: 有专属条款 | F34: 有硬性要求 | G34: 6 篇/轮 | H34: 无审稿义务 | I34: 6 篇/周期（每位作者各自计，适用于所有作者） | J34: 不强制 | K34: 无门槛 | L34: 无 | M34: 未提及 | N34: https://www.ndss-symposium.org/ndss2027/submissions/call-for-papers/ | O34: 高 | P34: 单周期6篇、全年12篇，超额可desk reject
A35: 34 | B35: S&P | C35: A | D35: 网络与信息安全 | E35: 有专属条款 | F35: 有硬性要求 | G35: 6 篇/轮 | H35: 无审稿义务 | I35: 每位作者每轮最多 6 篇（适用于所有作者） | J35: 不强制 | K35: 摘要注册时须填全部作者 ORCID，邮箱须与 HotCRP 一致 | L35: 无 | M35: 设学生差旅资助（组委会设专职主席） | N35: https://sp2027.ieee-security.org/cfpapers.html | O35: 高 | P35: CFP 原文：Any author may submit no more than 6 papers per cycle
A36: 35 | B36: USENIX Security | C36: A | D36: 网络与信息安全 | E36: 有专属条款 | F36: 有硬性要求 | G36: 7 篇/轮 | H36: 无审稿义务 | I36: 7 篇/周期（每位作者各自计，适用于所有作者） | J36: 不强制 | K36: 全员须配 ORCID 并确认投稿条款 | L36: 无 | M36: 报告者须全价注册，困难可申请减免 | N36: https://www.usenix.org/conference/usenixsecurity27/call-for-papers | O36: 高 | P36: 超7篇保留投稿号最小的7篇；学生价不满足报告义务
A37: 36 | B37: FM | C37: A | D37: 软件工程/系统软件 | E37: CFP未发布 | F37: CFP未发布 | G37: CFP未发布 | H37: CFP未发布 | I37: CFP未发布 | J37: CFP未发布 | K37: CFP未发布 | L37: CFP未发布 | M37: CFP未发布 | N37: — | O37: 高
A38: 37 | B38: FSE | C38: A | D38: 软件工程/系统软件 | E38: 未找到 | F38: 未找到 | G38: 不限 | H38: 未找到 | I38: 未找到 | J38: 待确认 | K38: 未找到 | L38: 未找到 | M38: 未找到 | N38: https://conf.researchr.org/home/fse-2027 | O38: 低 | P38: evidence疑指向密码学FSE；本会Research Papers页需登录
A39: 38 | B39: ICSE | C39: A | D39: 软件工程/系统软件 | E39: 未找到 | F39: 未找到 | G39: 不限 | H39: 未找到 | I39: 未找到 | J39: 待确认 | K39: 未找到 | L39: 未找到 | M39: 未找到 | N39: https://conf.researchr.org/home/icse-2027 | O39: 低 | P39: Research Papers CFP返回404；首页仅见双盲与数据共享说明
A40: 39 | B40: ISSTA | C40: A | D40: 软件工程/系统软件 | E40: 未找到 | F40: 未找到 | G40: 不限 | H40: 未找到 | I40: 未找到 | J40: 待确认 | K40: 未找到 | L40: 未找到 | M40: 未找到 | N40: https://conf.researchr.org/track/issta-2027/issta-2027-research-papers | O40: 低 | P40: Research Papers 正文内容仍为 TBD，日期已公布
A41: 40 | B41: OOPSLA | C41: A | D41: 软件工程/系统软件 | E41: 有专属条款 | F41: 有硬性要求 | G41: 5 篇/轮（无资深作者者至多2篇）；全体上限 5 篇/届 | H41: 每篇须1名资深作者注册储备审稿人，否则可desk reject | I41: 5 篇/轮（无资深作者者至多2篇） | J41: 不强制 | K41: 储备审稿人须用HotCRP同邮箱在TPMS注册 | L41: 无 | M41: 未提及 | N41: https://2027.splashcon.org/track/splashoopsla2027 | O41: 高 | P41: 无资深作者、或资深者为SIGPLAN/SIGSOFT新人可豁免
A42: 41 | B42: OSDI | C42: A | D42: 软件工程/系统软件 | E42: 有专属条款 | F42: 有硬性要求 | G42: 8 篇/届 | H42: 无审稿义务 | I42: 8 篇（每位作者各自计，适用于所有作者） | J42: 不强制 | K42: 无门槛 | L42: 无 | M42: 未提及 | N42: https://www.usenix.org/conference/osdi27/call-for-papers | O42: 高 | P42: 超8篇由项目主席desk reject多余投稿
A43: 42 | B43: PLDI | C43: A | D43: 软件工程/系统软件 | E43: 有专属条款 | F43: 有硬性要求 | G43: 不限 | H43: 每篇须 1 名资深作者注册 reserve reviewer（无资深作者可豁免） | I43: 无 | J43: 不强制 | K43: 无门槛 | L43: 无 | M43: 录用后可申请 SIGPLAN PAC 差旅资助 | N43: https://pldi27.sigplan.org/track/pldi-2027-papers | O43: 高 | P43: 资深=博士毕业满 5 年或任教职；作者全为新人可豁免
A44: 43 | B44: POPL | C44: A | D44: 软件工程/系统软件 | E44: 有专属条款 | F44: 有硬性要求 | G44: 不限 | H44: 每篇至少1名资深作者须在TPMS注册储备审稿人 | I44: 无 | J44: 不强制 | K44: 储备审稿人须用HotCRP同邮箱在TPMS注册 | L44: 无 | M44: 未提及 | N44: https://popl27.sigplan.org/track/POPL-2027-popl-research-papers | O44: 高 | P44: 2027新政；无资深作者或资深者为SIGPLAN新人可豁免
A45: 44 | B45: AAMAS | C45: B | D45: 人工智能 | E45: 未找到 | F45: 未找到 | G45: 不限 | H45: 未找到 | I45: 未找到 | J45: 待确认 | K45: 未找到 | L45: 未找到 | M45: 未找到 | N45: https://warwick.ac.uk/fac/sci/dcs/aamas2027/ | O45: 低 | P45: 主页仅列各track日期；/call-for-papers 返回404
A46: 45 | B46: COLING | C46: B | D46: 人工智能 | E46: 未找到 | F46: 未找到 | G46: 不限 | H46: 未找到 | I46: 未找到 | J46: 待确认 | K46: 未找到 | L46: 未找到 | M46: 未找到 | N46: https://2027.coling-iccl.org/calls/main_conference_papers/ | O46: 中 | P46: 主会CFP通篇无A–F；须经ARR平台投稿，细则另见ARR
A47: 46 | B47: COLT | C47: B | D47: 人工智能 | E47: CFP未发布 | F47: CFP未发布 | G47: CFP未发布 | H47: CFP未发布 | I47: CFP未发布 | J47: CFP未发布 | K47: CFP未发布 | L47: CFP未发布 | M47: CFP未发布 | N47: — | O47: 高
A48: 47 | B48: ECAI | C48: B | D48: 人工智能 | E48: 有专属条款 | F48: 只有利好通道 | G48: 不限 | H48: 未找到 | I48: 未找到 | J48: 待确认 | K48: 未找到 | L48: Doctoral Consortium, STAIRS | M48: 未找到 | N48: https://ecai2027.org/ | O48: 中 | P48: CFP尚未发布；学生通道信息仅见于官网主页介绍
A49: 48 | B49: ICAPS | C49: B | D49: 人工智能 | E49: CFP未发布 | F49: CFP未发布 | G49: CFP未发布 | H49: CFP未发布 | I49: CFP未发布 | J49: CFP未发布 | K49: CFP未发布 | L49: CFP未发布 | M49: CFP未发布 | N49: — | O49: 高
A50: 49 | B50: ICRA | C50: B | D50: 人工智能 | E50: 未找到 | F50: 未找到 | G50: 不限 | H50: 未找到 | I50: 未找到 | J50: 待确认 | K50: 未找到 | L50: 未找到 | M50: 未找到 | N50: https://2027.ieee-icra.org/call-for-papers/ | O50: 低 | P50: 官网仅称将发布 Call for Papers，尚无 Authors 条款页
A51: 50 | B51: IJCAI | C51: B | D51: 人工智能 | E51: 未找到 | F51: 未找到 | G51: 不限 | H51: 未找到 | I51: 未找到 | J51: 待确认 | K51: 未找到 | L51: 未找到 | M51: 未找到 | N51: https://2027.ijcai.org/ | O51: 低 | P51: 官网仅列重要日期，Authors/CFP 页 404
A52: 51 | B52: KR | C52: B | D52: 人工智能 | E52: 未找到 | F52: 未找到 | G52: 不限 | H52: 未找到 | I52: 未找到 | J52: 待确认 | K52: 未找到 | L52: 未找到 | M52: 未提及 | N52: https://kr.org/KR2027/ | O52: 低 | P52: 站点仅会议简介，无投稿与作者页
A53: 52 | B53: NAACL | C53: B | D53: 人工智能 | E53: 有专属条款 | F53: 有硬性要求 | G53: 20 篇/周期、一作 5 篇；无贡献者入抽签 | H53: 每篇投稿须指定合格 service contributor 并登记 | I53: 20 篇/周期、一作 5 篇；无贡献者入抽签 | J53: 不强制 | K53: 全体作者须有含 ORCiD 的 OpenReview 档案 | L53: 无 | M53: 未提及 | N53: https://2027.naacl.org/calls/main_conference_papers/ | O53: 高 | P53: 互惠审稿细则见 ARR 2026 可持续审稿政策
A54: 53 | B54: DCC | C54: B | D54: 图形学与多媒体 | E54: 无专属条款 | F54: 无 | G54: 不限 | H54: 无审稿义务 | I54: 无 | J54: 不强制 | K54: 无门槛 | L54: 无 | M54: 未提及 | N54: https://datacompressionconference.org/call-for-papers/information-for-authors/ | O54: 中 | P54: CFP 与作者须知页仅规范格式与双盲，无 A–F
A55: 54 | B55: EuroVis | C55: B | D55: 图形学与多媒体 | E55: 未找到 | F55: 未找到 | G55: 不限 | H55: 未找到 | I55: 未找到 | J55: 待确认 | K55: 未找到 | L55: 未找到 | M55: 未提及 | N55: https://eurovis27.github.io/web/submissions/all-deadlines/ | O55: 低 | P55: 仅见各 track 截稿日，full papers 正文为空
A56: 55 | B56: Eurographics | C56: B | D56: 图形学与多媒体 | E56: 未找到 | F56: 未找到 | G56: 不限 | H56: 未找到 | I56: 未找到 | J56: 待确认 | K56: 未找到 | L56: 未找到 | M56: 未提及 | N56: https://eg2027.isti.cnr.it/ | O56: 低 | P56: 首页仅有 STAR 延期通知，无作者条款
A57: 56 | B57: ICASSP | C57: B | D57: 图形学与多媒体 | E57: 无专属条款 | F57: 无 | G57: 不限 | H57: 无审稿义务 | I57: 无 | J57: 不强制 | K57: 无门槛 | L57: 无 | M57: 未提及 | N57: https://2027.ieeeicassp.org/call-for-papers/ | O57: 中 | P57: CFP 页仅列日期、范围与 OJSP 通道
A58: 57 | B58: ICME | C58: B | D58: 图形学与多媒体 | E58: 无专属条款 | F58: 无 | G58: 不限 | H58: 无审稿义务 | I58: 无 | J58: 不强制 | K58: 无门槛 | L58: 无 | M58: 未提及 | N58: https://2027.ieeeicme.org/authors/call-for-papers | O58: 中 | P58: CFP 页仅列主题与日期，无新人/学生条款
A59: 58 | B59: ICMR | C59: B | D59: 图形学与多媒体 | E59: CFP未发布 | F59: CFP未发布 | G59: CFP未发布 | H59: CFP未发布 | I59: CFP未发布 | J59: CFP未发布 | K59: CFP未发布 | L59: CFP未发布 | M59: CFP未发布 | N59: — | O59: 高
A60: 59 | B60: InterSpeech | C60: B | D60: 图形学与多媒体 | E60: 有专属条款 | F60: 有硬性要求 | G60: 2 篇（每人一作上限） | H60: 无审稿义务 | I60: 2 篇（每人一作上限） | J60: 不强制 | K60: 无门槛 | L60: 无 | M60: 未提及 | N60: https://interspeech2027.org/calls/call_for_papers/ | O60: 高 | P60: 一作上限对全体作者通用；另设 Long Paper 轨道
A61: 60 | B61: SGP | C61: B | D61: 图形学与多媒体 | E61: CFP未发布 | F61: CFP未发布 | G61: CFP未发布 | H61: CFP未发布 | I61: CFP未发布 | J61: CFP未发布 | K61: CFP未发布 | L61: CFP未发布 | M61: CFP未发布 | N61: — | O61: 高
A62: 61 | B62: SPM | C62: B | D62: 图形学与多媒体 | E62: CFP未发布 | F62: CFP未发布 | G62: CFP未发布 | H62: CFP未发布 | I62: CFP未发布 | J62: CFP未发布 | K62: CFP未发布 | L62: CFP未发布 | M62: CFP未发布 | N62: — | O62: 高
A63: 62 | B63: CADE | C63: B | D63: 计算机科学理论 | E63: 有专属条款 | F63: 只有利好通道 | G63: 不限 | H63: 无审稿义务 | I63: 无 | J63: 不强制 | K63: 无门槛 | L63: 最佳学生论文奖 | M63: 未提及 | N63: https://fscd-cade.science.ru.nl/calls/papers-cade | O63: 高 | P63: 学生奖要求至少一位作者为学生身份
A64: 63 | B64: CCC | C64: B | D64: 计算机科学理论 | E64: CFP未发布 | F64: CFP未发布 | G64: 不限 | H64: 未找到 | I64: 未找到 | J64: 待确认 | K64: 未找到 | L64: 未找到 | M64: 未找到 | N64: — | O64: 低 | P64: 2027 CFP 未发布，A-F 类条款无从判定
A65: 64 | B65: HSCC | C65: B | D65: 计算机科学理论 | E65: 未找到 | F65: 未找到 | G65: 不限 | H65: 未找到 | I65: 未找到 | J65: 待确认 | K65: 未找到 | L65: 未找到 | M65: 未找到 | N65: https://hscc.acm.org/2027/ | O65: 低 | P65: 已并入 HSCC+ICCPS'27 合并站，无 Authors 条款页
A66: 65 | B66: ICALP | C66: B | D66: 计算机科学理论 | E66: CFP未发布 | F66: CFP未发布 | G66: 不限 | H66: 未找到 | I66: 未找到 | J66: 待确认 | K66: 未找到 | L66: 未找到 | M66: 未找到 | N66: — | O66: 低 | P66: 2027 CFP 未发布，A-F 类条款无从判定
A67: 66 | B67: SOCG | C67: B | D67: 计算机科学理论 | E67: CFP未发布 | F67: CFP未发布 | G67: 不限 | H67: 未找到 | I67: 未找到 | J67: 待确认 | K67: 未找到 | L67: 未找到 | M67: 未找到 | N67: — | O67: 低 | P67: 2027 CFP 未发布，A-F 类条款无从判定
A68: 67 | B68: CIDR | C68: B | D68: 数据库/数据挖掘 | E68: 有专属条款 | F68: 有硬性要求 | G68: 1 篇/届 | H68: 无审稿义务 | I68: 1 篇（每位作者上限） | J68: 不强制 | K68: 无门槛 | L68: 无 | M68: 未提及 | N68: https://www.cidrdb.org/cidr2027/ | O68: 高 | P68: 官网明示作者最多提交 1 篇
A69: 68 | B69: DASFAA | C69: B | D69: 数据库/数据挖掘 | E69: 有专属条款 | F69: 只有利好通道 | G69: 不限 | H69: 无审稿义务 | I69: 无 | J69: 不强制 | K69: 无门槛 | L69: Ph.D. Forum, Teen Research Track | M69: 未提及 | N69: https://dasfaa2027.github.io/ | O69: 中 | P69: 首页日期表列 Ph.D. Forum 与学生向赛道
A70: 69 | B70: ECML-PKDD | C70: B | D70: 数据库/数据挖掘 | E70: CFP未发布 | F70: CFP未发布 | G70: 不限 | H70: 未找到 | I70: 未找到 | J70: 待确认 | K70: 未找到 | L70: 未找到 | M70: 未找到 | N70: — | O70: 低 | P70: 2027 CFP 未发布，A-F 类条款无从判定
A71: 70 | B71: EDBT | C71: B | D71: 数据库/数据挖掘 | E71: CFP未发布 | F71: CFP未发布 | G71: 不限 | H71: 未找到 | I71: 未找到 | J71: 待确认 | K71: 未找到 | L71: 未找到 | M71: 未找到 | N71: — | O71: 低 | P71: 2027 CFP 未发布，A-F 类条款无从判定
A72: 71 | B72: ICDM | C72: B | D72: 数据库/数据挖掘 | E72: 未找到 | F72: 未找到 | G72: 不限 | H72: 未找到 | I72: 未找到 | J72: 待确认 | K72: 未找到 | L72: 未找到 | M72: 未找到 | N72: https://icdm2027-website.onrender.com/ | O72: 低 | P72: 首页仅简介与日期，CFP 细则页未抓取
A73: 72 | B73: ICDT | C73: B | D73: 数据库/数据挖掘 | E73: CFP未发布 | F73: CFP未发布 | G73: 不限 | H73: 未找到 | I73: 未找到 | J73: 待确认 | K73: 未找到 | L73: 未找到 | M73: 未找到 | N73: — | O73: 低 | P73: 2027 CFP 未发布，A-F 类条款无从判定
A74: 73 | B74: PODS | C74: B | D74: 数据库/数据挖掘 | E74: 未找到 | F74: 未找到 | G74: 不限 | H74: 未找到 | I74: 未找到 | J74: 待确认 | K74: 未找到 | L74: 未找到 | M74: 未找到 | N74: https://2027.sigmod.org/calls_papers_important_dates.shtml | O74: 低 | P74: 仅读到重要日期页，未见作者条款页
... A146: 145 | B146: GI | C146: C | D146: 人机交互与普适计算 | E146: CFP未发布 | F146: CFP未发布 | G146: 不限 | H146: — | I146: — | J146: — | K146: — | L146: — | M146: — | N146: — | O146: 高 | P146: 2027 CFP 未发布，无 Authors/Submission 页可查
A147: 146 | B147: IDC | C147: C | D147: 人机交互与普适计算 | E147: 有专属条款 | F147: 只有利好通道 | G147: 不限 | H147: 无审稿义务 | I147: 无 | J147: 不强制 | K147: 无门槛 | L147: Doctoral Consortium, Research and Design Challenge | M147: 未提及 | N147: https://idc.acm.org/2027/ | O147: 高
A148: 147 | B148: INTERACT | C148: C | D148: 人机交互与普适计算 | E148: 有专属条款 | F148: 只有利好通道 | G148: 不限 | H148: 无审稿义务 | I148: 无 | J148: 不强制 | K148: 无门槛 | L148: Doctoral Consortium | M148: 未提及 | N148: https://interact2027.org/ | O148: 高 | P148: DC与短文等同期截止
A149: 148 | B149: WHC | C149: C | D149: 人机交互与普适计算 | E149: 有专属条款 | F149: 只有利好通道 | G149: 不限 | H149: 无审稿义务 | I149: 无 | J149: 不强制 | K149: 无门槛 | L149: Student Innovation Challenge | M149: 未提及 | N149: https://2027.worldhaptics.org/ | O149: 高 | P149: 另有 Work-in-Progress、Demo 通道
A150: 149 | B150: ICIC | C150: C | D150: 交叉/综合/新兴 | E150: 未找到 | F150: 未找到 | G150: 不限 | H150: 未找到 | I150: 未找到 | J150: 待确认 | K150: 未找到 | L150: 未找到 | M150: 未提及 | N150: — | O150: 低 | P150: 官网 2027 不可达，无 CFP 原文
A151: 150 | B151: ICC | C151: C | D151: 计算机网络 | E151: 无专属条款 | F151: 无 | G151: 不限 | H151: 无审稿义务 | I151: 无 | J151: 不强制 | K151: EDAS 账号提交，无额外门槛 | L151: 无 | M151: 未提及 | N151: https://icc2027.ieee-icc.org/authors/call-symposium-papers | O151: 中 | P151: 仅设 Spotlight/Best Paper，无学生条款
A152: 151 | B152: ICCCN | C152: C | D152: 计算机网络 | E152: 无专属条款 | F152: 无 | G152: 不限 | H152: 无审稿义务 | I152: 无 | J152: 不强制 | K152: EasyChair 账号，无额外门槛 | L152: 无 | M152: 未提及 | N152: http://www.icccn.org/icccn27/call-for-papers/index.html | O152: 高 | P152: 设 Best Paper；边缘稿可转 short paper
A153: 152 | B153: WCNC | C153: C | D153: 计算机网络 | E153: 无专属条款 | F153: 无 | G153: 不限 | H153: 无审稿义务 | I153: 无 | J153: 不强制 | K153: 无门槛 | L153: 无 | M153: 未提及 | N153: https://wcnc2027.ieee-wcnc.org/authors/call-papers | O153: 中 | P153: 已读 Authors 与 CFP 页，未见 A–F 条款
A154: 153 | B154: WoWMoM | C154: C | D154: 计算机网络 | E154: 无专属条款 | F154: 无 | G154: 不限 | H154: 无审稿义务 | I154: 无 | J154: 不强制 | K154: 无门槛 | L154: 无 | M154: 未提及 | N154: https://wowmom2027.dii.unipi.it/call-for-papers.html | O154: 中 | P154: 有 WIP 通道，非学生专属
A155: 154 | B155: ACISP | C155: C | D155: 网络与信息安全 | E155: 无专属条款 | F155: 无 | G155: 不限 | H155: 无审稿义务 | I155: 无 | J155: 不强制 | K155: EasyChair 账号，无额外门槛 | L155: 无 | M155: 未提及 | N155: https://acisp.org/cfp.html | O155: 高 | P155: 两轮投稿；设 SoK 通道；无学生条款
A156: 155 | B156: ACNS | C156: C | D156: 网络与信息安全 | E156: 有专属条款 | F156: 有硬性要求 | G156: 不限 | H156: 无审稿义务 | I156: 无 | J156: 不强制 | K156: HotCRP 账号，无额外门槛 | L156: 最佳学生论文奖（Springer 1500 EUR） | M156: 无学生费率，录用须全价注册 | N156: https://acns2027.isg.rhul.ac.uk/calls/papers | O156: 高 | P156: 须有全职学生作者并到会方可评学生奖
A157: 156 | B157: AsiaCCS | C157: C | D157: 网络与信息安全 | E157: 有专属条款 | F157: 有硬性要求 | G157: 不限 | H157: 无审稿义务 | I157: 无 | J157: 不强制 | K157: 所有作者须投稿前提供 ORCID | L157: 无 | M157: ACM Open APC 补贴 500/750 美元 | N157: https://asiaccs2027.cityu.edu.mo/call-for-papers/index.html | O157: 高 | P157: Track Chair 投本 track 限 2 篇
A158: 157 | B158: BlockSys | C158: C | D158: 网络与信息安全 | E158: 有专属条款 | F158: 有硬性要求 | G158: 不限 | H158: 无审稿义务 | I158: 无 | J158: 不强制 | K158: EasyChair 账号，无额外门槛 | L158: 最佳学生论文奖 | M158: 未提及 | N158: https://blocksys.info/2027/call-for-papers/ | O158: 高 | P158: 另设 Best Paper、Best Contributions
A159: 158 | B159: CODASPY | C159: C | D159: 网络与信息安全 | E159: 有专属条款 | F159: 只有利好通道 | G159: 不限 | H159: 无审稿义务 | I159: 无 | J159: 不强制 | K159: 须注册 ORCID（ACM 出版流程） | L159: 无 | M159: ACM Open APC 补贴 500/750 美元 | N159: https://www.codaspy.org/2027/cfp.html | O159: 中 | P159: ORCID 为 ACM 通用要求，非新人专属
... A169: 168 | B169: SOUPS | C169: C | D169: 网络与信息安全 | E169: CFP未发布 | F169: CFP未发布 | G169: 不限 | H169: 未找到 | I169: 未找到 | J169: 待确认 | K169: 未找到 | L169: 未找到 | M169: 未找到 | N169: — | O169: 低 | P169: 2027 CFP 未发布，无法核查新人条款
A170: 169 | B170: SecureComm | C170: C | D170: 网络与信息安全 | E170: 无专属条款 | F170: 无 | G170: 不限 | H170: 无审稿义务 | I170: 无 | J170: 不强制 | K170: EasyChair 自助注册，无门槛 | L170: 无 | M170: 未提及 | N170: https://securecomm.eai-conferences.org/2027/call-for-paper/ | O170: 中
A171: 170 | B171: COMPSAC | C171: C | D171: 软件工程/系统软件 | E171: 有专属条款 | F171: 只有利好通道 | G171: 不限 | H171: 无审稿义务 | I171: 无 | J171: 待确认 | K171: 无门槛 | L171: 学生论文竞赛 STC, 学生研究论坛 SRS, 早期职业 Mentorium 工作坊 | M171: 未提及 | N171: https://ieeecompsac.computer.org/2027/ | O171: 中 | P171: SRS 录用论文进主会论文集
A172: 171 | B172: EASE | C172: C | D172: 软件工程/系统软件 | E172: 有专属条款 | F172: 只有利好通道 | G172: 不限 | H172: 无审稿义务 | I172: 无 | J172: 不强制 | K172: 无门槛 | L172: Doctoral Symposium | M172: 未提及 | N172: https://conf.researchr.org/home/ease-2027 | O172: 高 | P172: DS 投稿 2027-02-04 截稿
A173: 172 | B173: ICST | C173: C | D173: 软件工程/系统软件 | E173: 有专属条款 | F173: 有硬性要求 | G173: 不限 | H173: 无审稿义务 | I173: 无 | J173: 不强制 | K173: HotCRP 投稿，无额外门槛 | L173: Doctoral Symposium | M173: 未提及 | N173: https://conf.researchr.org/home/icst-2027 | O173: 高 | P173: 研究论文轨不接受短文
A174: 173 | B174: MSR | C174: C | D174: 软件工程/系统软件 | E174: 有专属条款 | F174: 只有利好通道 | G174: 不限 | H174: 无审稿义务 | I174: 无 | J174: 不强制 | K174: HotCRP 投稿；录用须 ORCID | L174: Junior PC（初级审稿人导师制） | M174: 未提及 | N174: https://2027.msrconf.org/track/msr-2027-technical-papers | O174: 高 | P174: Junior PC 面向博士生/博后/新教师
A175: 174 | B175: PEPM | C175: C | D175: 软件工程/系统软件 | E175: 无专属条款 | F175: 无 | G175: 不限 | H175: 无审稿义务 | I175: 无 | J175: 不强制 | K175: 无门槛 | L175: 无 | M175: 未提及 | N175: https://popl27.sigplan.org/home/pepm-2027 | O175: 中 | P175: 单盲审；仅要求至少 1 人参会
A176: 175 | B176: REFSQ | C176: C | D176: 软件工程/系统软件 | E176: 有专属条款 | F176: 只有利好通道 | G176: 不限 | H176: 无审稿义务 | I176: 无 | J176: 不强制 | K176: 无门槛 | L176: Doctoral Symposium | M176: 未提及 | N176: https://2027.refsq.org/ | O176: 高 | P176: DS 截稿 2027-02-04
A177: 176 | B177: CPAL | C177: N | D177: 人工智能 | E177: 有专属条款 | F177: 只有利好通道 | G177: 不限 | H177: 无审稿义务 | I177: 无 | J177: 不强制 | K177: 无门槛 | L177: Rising Stars Award（早期职业，含导师指导） | M177: 未提及 | N177: https://cpal.cc/rising_stars_guidelines/ | O177: 高 | P177: Rising Stars 每人限 1 份申请，须现场参会
A178: 177 | B178: CVC | C178: N | D178: 人工智能 | E178: CFP未发布 | F178: CFP未发布 | G178: 不限 | H178: 未找到 | I178: 未找到 | J178: 待确认 | K178: 未找到 | L178: 未找到 | M178: 未找到 | N178: — | O178: 低 | P178: 2027 CFP 未发布，无法核查新人条款
A179: 178 | B179: EACL | C179: N | D179: 人工智能 | E179: 有专属条款 | F179: 有硬性要求 | G179: 不限 | H179: 全员须注册审稿或任 AC/SAC，逾期可致下轮禁投 | I179: 无 | J179: 不强制 | K179: OpenReview 投稿；作者须 8/5 前填注册表 | L179: 无 | M179: 未提及 | N179: https://2027.eacl.org/calls/papers/ | O179: 高 | P179: 该页未见 SRW/学生通道
A180: 179 | B180: ESANN | C180: N | D180: 人工智能 | E180: 无专属条款 | F180: 无 | G180: 不限 | H180: 无审稿义务 | I180: 无 | J180: 不强制 | K180: 无门槛 | L180: 无 | M180: 未提及 | N180: https://www.esann.org/author_guidelines | O180: 中 | P180: 作者页仅规定6页、单盲、注册义务
A181: 180 | B181: EuroGP | C181: N | D181: 人工智能 | E181: 有专属条款 | F181: 只有利好通道 | G181: 不限 | H181: 无审稿义务 | I181: 无 | J181: 不强制 | K181: 无门槛 | L181: Outstanding Student 提名 | M181: 须提交在读证明；入选者下届免费注册 | N181: https://www.evostar.org/2027/evostar-outstanding-students/ | O181: 高 | P181: 学生论文须上传全体作者签字声明
A182: 181 | B182: EvoApplications | C182: N | D182: 人工智能 | E182: 有专属条款 | F182: 只有利好通道 | G182: 不限 | H182: 无审稿义务 | I182: 无 | J182: 不强制 | K182: 无门槛 | L182: Outstanding Student 提名 | M182: 须提交在读证明；入选者下届免费注册 | N182: https://www.evostar.org/2027/evostar-outstanding-students/ | O182: 高 | P182: 学生论文须上传全体作者签字声明
...

Sheet 待补清单
A1: 序号 | B1: 简称 | C1: CCF | D1: 状态 | E1: 剩余天数 (生成时) | F1: 缺什么 | G1: 缺口类型 | H1: 下一步 | I1: 官网核查 | J1: 官网
A2: 129 | B2: CVM | C2: C | D2: 未截止 | E2: 2 | F2: 是否到场、新人条款 | G2: 官网未写明 | H2: 查 Registration / Attending / FAQ / Reviewing 子页 | I2: 已核实 | J2: http://iccvm.org/2027/
A3: 83 | B3: ISCAS | C3: B | D3: 未截止 | E3: 2 | F3: 是否到场、新人条款 | G3: 等官方发布 | H3: 2027 CFP 未出，发布后重查；不要沿用上届 | I3: 2027CFP未发布 | J3: https://2027.ieee-iscas.org/
A4: 194 | B4: MLSys | C4: N | D4: 未截止 | E4: 5 | F4: 是否到场 | G4: 官网未写明 | H4: 查 Registration / Attending / FAQ / Reviewing 子页 | I4: 已核实 | J4: https://mlsys.org/
A5: 166 | B5: SACMAT | C5: C | D5: 未截止 | E5: 6 | F5: 新人条款 | G5: 等官方发布 | H5: 2027 CFP 未出，发布后重查；不要沿用上届 | I5: 2027CFP未发布 | J5: https://www.sacmat.org/2027/
A6: 143 | B6: CSCWD | C6: C | D6: 未截止 | E6: 7 | F6: 是否到场、新人条款 | G6: 官网未查到 | H6: 换入口重查（官网 / dblp / 主办方页面） | I6: 官网不可达 | J6: http://2027.cscwd.org
A7: 95 | B7: RECOMB | C7: B | D7: 未截止 | E7: 11 | F7: 是否到场、新人条款 | G7: 等官方发布 | H7: 2027 CFP 未出，发布后重查；不要沿用上届 | I7: 2027CFP未发布 | J7: https://recomb.org/recomb2027/
A8: 64 | B8: HSCC | C8: B | D8: 未截止 | E8: 12 | F8: 是否到场、新人条款 | G8: 官网未写明 | H8: 查 Registration / Attending / FAQ / Reviewing 子页 | I8: 已核实 | J8: https://hscc.acm.org/2027/
A9: 198 | B9: NOMS | C9: N | D9: 未截止 | E9: 16 | F9: 是否到场 | G9: 官网未写明 | H9: 查 Registration / Attending / FAQ / Reviewing 子页 | I9: 已核实 | J9: https://noms2027.ieee-noms.org/
A10: 133 | B10: PacificVis | C10: C | D10: 未截止 | E10: 16 | F10: 新人条款 | G10: 官网未查到 | H10: 换入口重查（官网 / dblp / 主办方页面） | I10: 未找到 | J10: https://pacificvis2027.github.io/
A11: 107 | B11: CAiSE | C11: B | D11: 未截止 | E11: 22 | F11: 是否到场、新人条款 | G11: 官网未写明 | H11: 查 Registration / Attending / FAQ / Reviewing 子页 | I11: 已核实 | J11: https://deal.us.es/caise27/
A12: 108 | B12: ECOOP | C12: B | D12: 未截止 | E12: 26 | F12: 是否到场 | G12: 官网未写明 | H12: 查 Registration / Attending / FAQ / Reviewing 子页 | I12: 已核实 | J12: https://2027.ecoop.org/
A13: 197 | B13: MMSys | C13: N | D13: 未截止 | E13: 26 | F13: 是否到场、新人条款 | G13: 官网未写明 | H13: 查 Registration / Attending / FAQ / Reviewing 子页 | I13: 已核实 | J13: https://2027.acmmmsys.org
... A62: 71 | B62: ICDM | C62: B | D62: 未截止 | E62: 225 | F62: 是否到场、新人条款 | G62: 官网未写明 | H62: 查 Registration / Attending / FAQ / Reviewing 子页 | I62: 已核实 | J62: https://icdm2027-website.onrender.com/
A63: 135 | B63: FSCD | C63: C | D63: TBD | E63: — | F63: 截稿日、是否到场 | G63: 官网未写明 | H63: 查 Registration / Attending / FAQ / Reviewing 子页 | I63: 已核实 | J63: https://fscd-cade.science.ru.nl/
A64: 54 | B64: EuroVis | C64: B | D64: TBD | E64: — | F64: 截稿日、是否到场、新人条款 | G64: 官网未查到 | H64: 换入口重查（官网 / dblp / 主办方页面） | I64: 未找到 | J64: https://eurovis27.github.io/web/
A65: 4 | B65: ICCV | C65: A | D65: TBD | E65: — | F65: 截稿日、新人条款 | G65: 等官方发布 | H65: 2027 CFP 未出，发布后重查；不要沿用上届 | I65: 2027CFP未发布 | J65: https://iccv.thecvf.com/Conferences/2027
A66: 6 | B66: ACM SIGGRAPH | C66: A | D66: TBD | E66: — | F66: 截稿日、新人条款 | G66: 等官方发布 | H66: 2027 CFP 未出，发布后重查；不要沿用上届 | I66: 2027CFP未发布 | J66: https://s2027.siggraph.org/
A67: 9 | B67: LICS | C67: A | D67: TBD | E67: — | F67: 截稿日、是否到场、新人条款 | G67: 等官方发布 | H67: 2027 CFP 未出，发布后重查；不要沿用上届 | I67: 2027CFP未发布 | J67: https://lics.siglog.org/lics27/
A68: 25 | B68: UbiComp/ISWC | C68: A | D68: TBD | E68: — | F68: 截稿日、是否到场、新人条款 | G68: 等官方发布 | H68: 2027 CFP 未出，发布后重查；不要沿用上届 | I68: 2027CFP未发布 | J68: https://sigchi.org/events/ubicomp-2027/
A69: 31 | B69: CCS | C69: A | D69: TBD | E69: — | F69: 截稿日、新人条款 | G69: 等官方发布 | H69: 2027 CFP 未出，发布后重查；不要沿用上届 | I69: 2027CFP未发布 | J69: https://www.sigsac.org/ccs/CCS2027/
A70: 36 | B70: FM | C70: A | D70: TBD | E70: — | F70: 截稿日、新人条款 | G70: 等官方发布 | H70: 2027 CFP 未出，发布后重查；不要沿用上届 | I70: 2027CFP未发布 | J70: https://www.fmeurope.org/feature/upcoming_conferences/
A71: 46 | B71: COLT | C71: B | D71: TBD | E71: — | F71: 截稿日、新人条款 | G71: 等官方发布 | H71: 2027 CFP 未出，发布后重查；不要沿用上届 | I71: 2027CFP未发布 | J71: https://learningtheory.org/colt2027/
A72: 60 | B72: SGP | C72: B | D72: TBD | E72: — | F72: 截稿日、是否到场、新人条款 | G72: 等官方发布 | H72: 2027 CFP 未出，发布后重查；不要沿用上届 | I72: 2027CFP未发布 | J72: https://igs2027singapore.github.io/
A73: 61 | B73: SPM | C73: B | D73: TBD | E73: — | F73: 截稿日、是否到场、新人条款 | G73: 等官方发布 | H73: 2027 CFP 未出，发布后重查；不要沿用上届 | I73: 2027CFP未发布 | J73: https://igs2027singapore.github.io/
A74: 63 | B74: CCC | C74: B | D74: TBD | E74: — | F74: 截稿日、是否到场、新人条款 | G74: 等官方发布 | H74: 2027 CFP 未出，发布后重查；不要沿用上届 | I74: 2027CFP未发布 | J74: https://computationalcomplexity.org/
... A113: 177 | B113: CVC | C113: N | D113: 已截止 | E113: — | F113: 是否到场、新人条款 | G113: 等官方发布 | H113: 2027 CFP 未出，发布后重查；不要沿用上届 | I113: 2027CFP未发布 | J113: https://saiconference.com/CVC

Sheet ARR 轮次
A1: ACL Rolling Review（ARR）滚动审稿轮次
A2: ARR 自 2025 年 5 月起改为 10 周一轮、每年约 5 轮，投稿日不再固定为每月某日。 数据源：https://aclrollingreview.org/dates（核对于 2026-10-25）
A4: Cycle | B4: 投稿截止 | C4: 审稿人注册 | D4: 审稿意见截止 | E4: 作者回复期 | F4: Meta-review 释出 | G4: Cycle 结束
A5: March 2026 | B5: 46097 | C5: 46099 | D5: 46132 | E5: 04-28 → 05-04 | F5: 46163 | G5: 46166
A6: May 2026 | B6: 46167 | C6: 46169 | D6: 46205 | E6: 07-08 → 07-14 | F6: 46233 | G6: 46236
A7: August 2026 | B7: 46237 | C7: 46239 | D7: 46272 | E7: 09-14 → 09-24 | F7: 46303 | G7: 46306
A8: October 2026 | B8: 46307 | C8: 46309 | D8: 46342 | E8: 11-24 → 11-30 | F8: 46373 | G8: 46376
A10: =IF(COUNTIF($B$5:$B$8,">="&TODAY())=0,"⚠ 表内各 ARR cycle 的投稿日均已过，请核对 https://aclrollingreview.org/dates 后更新 arr_cycles.json 并重新生成","最近一轮 ARR 投稿截止："&TEXT(SMALL($B$5:$B$8,COUNTIF($B$5:$B$8,"<"&TODAY())+1),"yyyy-mm-dd")&"（高亮行）")
A11: 官网提到 ACL 2027 对应 cycle 的投稿截止在 2027 年 1 月，但完整日期尚未列出；建议每月核对 aclrollingreview.org/dates。
A13: ARR 路径与可 commit 会议（2027 届）
A14: 会议 | B14: CCF | C14: 会期 / 地点 | D14: 路径 | E14: 最近一轮截稿(北京) | F14: 说明
A15: ACL | B15: A | C15: August 17-22, 2027 | Kyoto, Japan | D15: ARR Submission | E15: 2027-01-05 19:59 | F15: 先投 ARR 拿 meta-review，再 commit 到本会，非直接投稿
A16: COLING | B16: B | C16: May 9-14, 2027 | Macau SAR, China | D16: COLING commitment after ARR meta-reviews; reviewed papers only | E16: 2026-12-24 19:59 | F16: 先投 ARR 拿 meta-review，再 commit 到本会，非直接投稿
A17: NAACL | B17: B | C17: June 1-5, 2027 | San Francisco, California, USA | D17: NAACL commitment after ARR meta-reviews; reviewed papers only | E17: 2026-12-24 19:59 | F17: 先投 ARR 拿 meta-review，再 commit 到本会，非直接投稿
A18: EACL | B18: N | C18: March 9-14, 2027 | Athens, Greece | D18: EACL commitment after ARR meta-reviews; reviewed papers only | E18: 2026-10-12 19:59 | F18: 先投 ARR 拿 meta-review，再 commit 到本会，非直接投稿

Sheet 读我
A1: CCF 推荐会议 2027 届投稿规划表
A2: 生成时间 2026-10-25 05:12（北京） |覆盖 2027 届会议 200 个（A 43 · B 74 · C 58 · N 25） | 官网已核实 149 未发布 42 未查到 9 | 新人条款：有 79（其中硬性 43） 无 39 CFP未发布 42 未找到 40
A3: 电脑时区 (UTC±h) | B3: 8
A4: 换算后北京时间 | B4: =TEXT('_轮次'!$A$1,"yyyy-mm-dd hh:mm")&" ← 与北京时间不符就改 B3"
A6: 时间口径 | B6: 所有截稿、rebuttal、录用通知时间**已统一折算为北京时间（UTC+8）**，不是会议当地时间。本表 148 个会议用 AoE、29 个用 UTC-12，折北京时间需 +20 小时，共 174 个会议的截稿日期因此顺延一天。要对照官网原文时请看「原始时区」列。
A7: 剩余天数 | B7: 「正文截稿 / 状态 / 剩余天数」是公式，打开文件时按电脑当前时间实时计算。Excel 只能读到电脑本地时间，所以先用上方 B3「电脑时区」换算成北京时间再比较——B3 默认 8（北京）；电脑不在北京时区就改成该电脑的 UTC 偏移，如美东填 -4（夏令时）/ -5，B4 会显示换算结果供核对。多轮会议会自动跳到最近一个未过期轮次，摘要截稿、轮次、Rebuttal、录用通知随之切换。「待补清单」里的剩余天数是生成时的快照，仅用于排序。
A8: 方向标签 | B8: 10 个方向对应 CCF 目录的十大领域：人工智能、体系结构/并行/存储、计算机网络、网络与信息安全、软件工程/系统软件、数据库/数据挖掘、计算机科学理论、图形学与多媒体、人机交互与普适计算、交叉/综合/新兴。
A9: 同名会议 | B9: 合并按会议唯一 ID 进行，不按简称。同简称会议中评级高的保留原简称，其余加后缀，如 ACM FSE（软工 A）与 FSE(IACR)（密码学 B）。
A10: 官网核查列 | B10: 【已核实】读到官方 2027 CFP，参会与投稿规则字段来自官方原文。 【2027CFP未发布】官网还没有 2027 的征稿说明——这是当前多数会议的真实状态，不代表信息错误，代表现在查不到。 【官网不可达】会议官网打不开或链接失效。【未找到】官网上没找到对应页面。 【未核查】本轮未覆盖到，字段来自知识补全。
A11: 置信度 | B11: 【高】官网已核实或 ccfddl 官方数据。【中】合理推断，投稿前需复核。【低】沿用上一届口径或推测。 截稿时间另有一层风险：部分 2027 数据是按上届规律外推的（如 SIGMOD 2027 四轮日期与 2026 完全同月同日），官方 CFP 一出就会变。
A12: 轮次取法 | B12: 存在未过期轮次时取最早一个未过期的，否则取最后一轮并标「已截止」。多轮会议（SIGMOD、VLDB 等）的完整轮次已写进「备注」列。
A13: ARR 类 | B13: ACL / NAACL / EACL / COLING 走 ACL Rolling Review 滚动审稿，不直接投稿。主表截稿是该会的 commit / submission 节点，真实投稿看 ARR cycle，见「ARR 轮次」表。ARR 日期存于 arr_cycles.json，全部过期时该表顶部会出现提示。
A14: 作者投稿上限 | B14: 主表拆成「投稿上限(篇)」数字列 + 「上限口径」列（每届 / 每轮 / 每年 / 配额制），可直接用数字筛选。按「同一作者在该届的投稿篇数硬性上限」理解，绝大多数会议不设上限，故填「不限」；填「待确认」表示可能有规定但未核实。官方原文写法见「扩展规则」表。表内没有任何编造的数字。
A15: 新人作者条款 | B15: 「新人作者」指三类人，条款各不相同：首次向该会投稿的作者、学生作者、无资深合作者的独立作者。 「新人作者要求」sheet 把条款拆成 6 类逐项核查：审稿义务/互惠审稿（A）、首投配额（B）、是否强制挂资深作者（C）、投稿账号门槛（D，如 OpenReview 新账号须机构邮箱）、学生与新人通道（E，如 SRW / Doctoral Consortium / Junior PC）、费用与资助（F）。 关键：「无专属条款」是查过且确实没有的结论，不是默认值；CFP 未发布的会一律标「CFP未发布」，不冒充「无」。 「对首投的影响」再分三档：有硬性要求（会卡住或拒稿）、只有利好通道（学生 track / 资助）、仅奖项。 D 类账号门槛只认「投稿时」的要求，录用后走出版流程的 ORCID、版权表单不计入，避免虚高。 最容易卡住首投的几条：ICLR 须指定作者审稿≥3 篇否则 desk reject、无合格互惠审稿人限投 1 篇；OOPSLA / POPL 2027 新政要求每篇至少 1 名资深作者注册 reserve reviewer；AISTATS 无四大 ML 会录用记录者限 3 篇、全体作者不合格则仅 1 篇；MobiSys / SenSys 每篇须 1 位按非学生费率注册；CVPR 无机构邮箱的 OpenReview 新账号需等约两周。
A16: 信息缺口 | B16: 共 112 个会议仍有字段待补，见「待补清单」：官网未写明 61、官网未查到 9、等官方发布 42。「等官方发布」的不要用上届口径填，等 CFP 出来再查；其余两类可按「下一步」列重查，结果写入 recheck/ 目录后重新生成即可合并。
A17: 建议动作 | B17: 1) 先按「未截止」+ 剩余天数 ≤90 筛，再按 CCF 评级与方向锁定 15–20 个目标。 2) 「官网核查」为「已核实」的行可直接用；其余投稿前必须点官网复核。 3) 每年 12 月至次年 3 月是 CFP 集中发布期，本表需定期刷新。

Sheet _轮次
A1: =NOW()+(8-'读我'!$B$3)/24 | B1: dl1 | C1: dl2 | D1: dl3 | E1: dl4 | F1: dl5 | G1: dl6 | H1: dl7 | I1: dl8 | J1: dl9 | K1: dl10 | L1: dl11 | M1: dl12 | N1: abs1 | O1: abs2 | P1: abs3 | Q1: abs4 | R1: abs5 | S1: abs6 | T1: abs7 | U1: abs8 | V1: abs9 | W1: abs10 | X1: abs11 | Y1: abs12 | Z1: reb1 | AA1: reb2 | AB1: reb3 | AC1: reb4 | AD1: reb5 | AE1: reb6 | AF1: reb7 | AG1: reb8 | AH1: reb9 | AI1: reb10 | AJ1: reb11 | AK1: reb12 | AL1: dec1 | AM1: dec2 | AN1: dec3 | AO1: dec4 | AP1: dec5 | AQ1: dec6 | AR1: dec7 | AS1: dec8 | AT1: dec9 | AU1: dec10 | AV1: dec11 | AW1: dec12 | AX1: l1 | AY1: l2 | AZ1: l3 | BA1: l4 | BB1: l5 | BC1: l6 | BD1: l7 | BE1: l8 | BF1: l9 | BG1: l10 | BH1: l11 | BI1: l12
A2: aaai27 | B2: 46232.833 | N2: 46225.833 | Z2: 46321.833 | AL2: 46357.833 | AX2: 单轮
A3: acl27 | B3: 46392.833 | AX3: ARR Submission
A4: cvpr27 | B4: 46343.833 | N4: 46337.833 | Z4: 46420.833 | AL4: 46444.833 | AX4: 单轮
A5: iccv27 | AX5: 单轮
A6: iclr27 | B6: 46291.833 | N6: 46284.833 | Z6: 46345.833 | AL6: 46373.833 | AX6: 单轮
A7: siggraph27 | AX7: 单轮
A8: vr27 | B8: 46266.833 | N8: 46259.833 | AL8: 46395.833 | AX8: 单轮
A9: cav27 | B9: 46408.833 | Z9: 46486.833 | AL9: 46501.833 | AX9: 单轮
A10: lics27 | AX10: 单轮
A11: soda27 | B11: 46213.833 | Z11: 46270.833 | AX11: 单轮
A12: stoc27 | B12: 46329.833 | AL12: 46420.833 | AX12: 单轮
A13: icde27 | B13: 46185.333 | C13: 46338.375 | Z13: 46250.333 | AA13: 46403.375 | AX13: first round | AY13: second round
A14: sigir27 | B14: 46409.833 | N14: 46402.833 | AX14: 单轮
A15: sigkdd27 | B15: 46230.833 | N15: 46223.833 | Z15: 46309.833 | AL15: 46341.833 | AX15: 1st round of 2 total rounds
A16: sigmod27 | B16: 46040.833 | C16: 46130.833 | D16: 46221.833 | E16: 46313.833 | N16: 46033.833 | O16: 46123.833 | P16: 46214.833 | Q16: 46306.833 | Z16: 46099.833 | AA16: 46191.833 | AB16: 46283.833 | AC16: 46374.833 | AL16: 46186.833 | AM16: 46278.833 | AN16: 46369.833 | AO16: 46459.833 | AX16: round 1 | AY16: round 2 | AZ16: round 3 | BA16: round 4
A17: vldb27 | B17: 46114.333 | C17: 46144.333 | D17: 46175.333 | E17: 46205.333 | F17: 46236.333 | G17: 46267.333 | H17: 46297.333 | I17: 46328.375 | J17: 46358.375 | K17: 46389.375 | L17: 46420.375 | M17: 46448.375 | N17: 46107.333 | O17: 46138.333 | P17: 46168.333 | Q17: 46199.333 | R17: 46229.333 | S17: 46260.333 | T17: 46291.333 | U17: 46321.333 | V17: 46352.375 | W17: 46382.375 | X17: 46413.375 | Y17: 46444.375 | AX17: 第1轮 | AY17: 第2轮 | AZ17: 第3轮 | BA17: 第4轮 | BB17: 第5轮 | BC17: 第6轮 | BD17: 第7轮 | BE17: 第8轮 | BF17: 第9轮 | BG17: 第10轮 | BH17: 第11轮 | BI17: 第12轮
A18: asplos27 | B18: 46128.833 | C18: 46275.833 | Z18: 46213.833 | AA18: 46361.833 | AX18: April Cycle Submission Deadline | AY18: September Cycle Submission Deadline
A19: dac27 | B19: 46345.375 | N19: 46338.375 | AL19: 46455.833 | AX19: 单轮
A20: eurosys2027 | B20: 46157.833 | C20: 46290.833 | N20: 46150.833 | O20: 46283.833 | Z20: 46235.833 | AA20: 46396.833 | AX20: Spring Submission Deadline | AY20: Fall Submission Deadline
A21: fast27 | B21: 46099.833 | C21: 46281.833 | Z21: 46163.833 | AA21: 46346.833 | AX21: Spring deadline | AY21: Fall deadline
A22: hpca27 | B22: 46235.833 | N22: 46228.833 | Z22: 46307.833 | AL22: 46333.833 | AX22: 单轮
A23: isca27 | B23: 46343.833 | N23: 46336.833 | Z23: 46455.833 | AL23: 46473.833 | AX23: Main Track; rebuttal/revision period: February 16-March 8, 2027
A24: ppopp27 | B24: 46238.833 | AL24: 46322.833 | AX24: 单轮
A25: chi27 | B25: 46276.833 | Z25: 46360.833 | AL25: 46374.833 | AX25: 单轮
A26: ubicomp27 | AX26: 单轮
A27: www27 | B27: 46321.833 | N27: 46314.833 | AL27: 46392.833 | AX27: 单轮
A28: infocom27 | B28: 46235.833 | N28: 46228.833 | AX28: 单轮
A29: mobicom27 | B29: 46268.833 | N29: 46261.833 | Z29: 46333.833 | AX29: Summer Deadlines
A30: nsdi27 | B30: 46136.499 | C30: 46283.499 | N30: 46129.499 | O30: 46276.499 | AX30: 第1轮 | AY30: 第2轮
A31: sigcomm27 | B31: 46421.833 | AX31: 单轮
A32: ccs27 | AX32: 单轮
A33: eurocrypt27 | B33: 46283.833 | Z33: 46362.833 | AL33: 46406.833 | AX33: 单轮
A34: ndss27 | B34: 46149.833 | C34: 46254.833 | AA34: 46340.833 | AL34: 46282.833 | AM34: 46399.833 | AX34: Summer | AY34: Fall
A35: sp27 | B35: 46185.833 | C35: 46344.833 | N35: 46178.833 | O35: 46337.833 | Z35: 46262.833 | AA35: 46435.833 | AL35: 46277.833 | AM35: 46452.833 | AX35: First Paper submission deadline | AY35: Second Paper submission deadline
A36: uss27 | B36: 46260.833 | C36: 46414.833 | N36: 46253.833 | O36: 46407.833 | Z36: 46339.833 | AA36: 46493.833 | AX36: Cycle 1 Deadline | AY36: Cycle 2 Deadline
A37: fm27 | AX37: 单轮
A38: fse27 | B38: 46298.833 | Z38: 46375.833 | AL38: 46478.833 | AX38: 单轮
A39: icse27 | B39: 46204.833 | N39: 46197.833 | Z39: 46291.833 | AL39: 46375.833 | AX39: Single Submission Cycle Deadline
A40: issta27 | B40: 46399.833 | N40: 46396.833 | Z40: 46472.833 | AL40: 46556.833 | AX40: 单轮
A41: oopsla27 | B41: 46310.833 | C41: 46485.833 | Z41: 46362.833 | AA41: 46558.833 | AL41: 46431.833 | AM41: 46613.833 | AX41: Submission Deadline Round 1 | AY41: Submission Deadline Round 2
A42: osdi2027 | B42: 46365.291 | N42: 46358.291 | AX42: 单轮
A43: pldi27 | B43: 46339.833 | Z43: 46437.833 | AL43: 46479.833 | AX43: 单轮
A44: popl27 | B44: 46213.833 | Z44: 46276.833 | AL44: 46336.833 | AX44: Submission Deadline
A45: aamas27 | B45: 46304.833 | N45: 46297.833 | Z45: 46351.833 | AL45: 46378.833 | AX45: 单轮
A46: coling27 | B46: 46308.833 | C46: 46380.833 | Z46: 46357.833 | AM46: 46429.833 | AX46: ARR Submission | AY46: COLING commitment after ARR meta-reviews; reviewed papers only
A47: colt27 | AX47: 单轮
A48: ecai27 | B48: 46492.833 | Z48: 46557.833 | AL48: 46584.833 | AX48: 单轮
A49: icaps27 | B49: 46371.833 | N49: 46364.833 | Z49: 46423.833 | AL49: 46445.833 | AX49: 单轮
A50: icra27 | B50: 46282.666 | AL50: 46419.833 | AX50: Extended submission deadline
A51: ijcai27 | B51: 46399.833 | N51: 46392.833 | AL51: 46499.833 | AX51: Separate satellite event: August 15-17, 2027, Hengqin, China
A52: krd27 | B52: 46506.833 | N52: 46501.833 | Z52: 46557.833 | AL52: 46569.833 | AX52: Main track; author response period: June 15-18, 2027
A53: naacl27 | B53: 46308.833 | C53: 46380.833 | Z53: 46357.833 | AM53: 46429.833 | AX53: ARR Submission | AY53: NAACL commitment after ARR meta-reviews; reviewed papers only
A54: dcc2027 | B54: 46305.624 | AL54: 46349.833 | AX54: 单轮
A55: eurovis2027 | AX55: Full papers; submission deadline not yet announced
A56: eg27 | B56: 46297.833 | N56: 46291.833 | Z56: 46357.333 | AL56: 46428.333 | AX56: 单轮
A57: icassp27 | B57: 46289.833 | AL57: 46401.833 | AX57: 单轮
A58: icme27 | B58: 46387.833 | Z58: 46451.833 | AL58: 46471.833 | AX58: 单轮
A59: icmr27 | B59: 46419.833 | AL59: 46479.833 | AX59: 单轮
A60: interspeech27 | B60: 46428.333 | AL60: 46541.833 | AX60: 单轮
A61: sgp27 | AX61: 单轮
A62: spm27 | AX62: 单轮
A63: cade27 | B63: 46441.833 | N63: 46434.833 | Z63: 46508.833 | AL63: 46525.833 | AX63: 单轮
A64: ccc27 | AX64: 单轮
A65: hscc27 | B65: 46332.833 | N65: 46325.833 | Z65: 46403.833 | AL65: 46416.833 | AX65: 单轮
A66: icalp27 | B66: 46281.833 | Z66: 46336.833 | AL66: 46365.833 | AX66: Track B first round; Track A and Track B second round TBA
A67: socg27 | AX67: 单轮
A68: cidr27 | B68: 46239.624 | AL68: 46302.624 | AX68: 单轮
A69: dasfaa27 | B69: 46352.833 | AL69: 46413.833 | AX69: Research papers
A70: ecmlpkdd2027 | AX70: 单轮
A71: edbt27 | B71: 46058.375 | C71: 46184.333 | D71: 46303.333 | AN71: 46415.375 | AX71: Official February cutoff is 17:00 PST (UTC-8), represented as the equivalent 13:00 AoE. | AY71: 第2轮 | AZ71: 第3轮
A72: icdm2027 | B72: 46545.833 | AL72: 46616.833 | AX72: Full papers; dates are tentative and subject to change
A73: icdt27 | B73: 46092.833 | C73: 46276.833 | N73: 46085.833 | O73: 46269.833 | AA73: 46334.833 | AL73: 46175.833 | AM73: 46358.833 | AX73: 第1轮 | AY73: 第2轮
A74: pods27 | B74: 46173.833 | C74: 46367.833 | N74: 46166.833 | O74: 46360.833 | Z74: 46236.833 | AA74: 46417.833 | AL74: 46267.833 | AM74: 46448.833 | AX74: First Submission Cycle | AY74: Second Submission Cycle
A75: recsys27 | AX75: 单轮
A76: wsdm27 | B76: 46259.833 | N76: 46252.833 | AL76: 46329.833 | AX76: Full Paper
A77: date2027 | B77: 46286.833 | N77: 46279.833 | AL77: 46350.833 | AX77: 单轮
A78: fpga2027 | B78: 46304.833 | N78: 46297.833 | Z78: 46342.833 | AL78: 46351.833 | AX78: 单轮
A79: hipeac27 | B79: 46175.833 | AX79: 单轮
A80: icdcs27 | AX80: 单轮
A81: ics27 | B81: 46364.833 | N81: 46358.833 | AL81: 46459.833 | AX81: 单轮
A82: cgo2027 | B82: 46185.833 | C82: 46276.833 | Z82: 46227.833 | AX82: First Submission | AY82: Second Submission
A83: ipdps27 | B83: 46304.833 | N83: 46297.833 | Z83: 46360.833 | AL83: 46421.833 | AX83: 单轮
A84: iscas27 | B84: 46322.541 | AX84: 单轮
A85: msst2027 | AX85: 单轮
A86: rtas2027 | B86: 46332.833 | Z86: 46403.833 | AX86: Submission Deadline (Firm)
A87: sigmetrics27 | B87: 46214.833 | C87: 46305.833 | D87: 46399.833 | N87: 46207.833 | O87: 46298.833 | P87: 46392.833 | AX87: summer round | AY87: fall round | AZ87: winter round
A88: spaa27 | B88: 46291.833 | C88: 46417.833 | N88: 46284.833 | O88: 46410.833 | Z88: 46345.833 | AA88: 46471.833 | AL88: 46362.833 | AX88: Cycle 1 | AY88: Cycle 2
A89: group27 | B89: 45854.833 | C89: 46113.833 | N89: 45847.833 | O89: 46106.833 | AX89: Full Paper First Wave Submissions | AY89: Full Paper Second Wave Submissions (extended)
A90: icwsm2027 | B90: 46158.833 | C90: 46281.833 | D90: 46403.833 | AX90: 1st Full-paper Deadline | AY90: 2nd Full-paper Deadline | AZ90: 3rd Full-paper Deadline
A91: iui27 | B91: 46255.833 | N91: 46248.833 | Z91: 46332.833 | AL91: 46350.833 | AX91: 单轮
A92: mobilehci27 | B92: 46436.833 | N92: 46429.833 | AL92: 46556.833 | AX92: 单轮
A93: percom27 | B93: 46284.833 | N93: 46277.833 | Z93: 46354.833 | AL93: 46375.833 | AX93: Extended deadlines
A94: ismb27 | B94: 46402.833 | AL94: 46477.833 | AX94: Proceedings; conditional acceptance: March 2, 2027; revised papers due: March 18, 2027, 23:59 AoE; no extensions to submission or revision deadlines
A95: miccai27 | AX95: 单轮
A96: recomb27 | B96: 46331.833 | N96: 46324.833 | AL96: 46379.833 | AX96: 单轮
A97: conext27 | B97: 46361.833 | C97: 46543.833 | N97: 46354.833 | O97: 46536.833 | AX97: December Cycle | AY97: June Cycle
A98: imc27 | B98: 46344.833 | C98: 46485.833 | N98: 46337.833 | O98: 46478.833 | Z98: 46421.833 | AL98: 46444.833 | AM98: 46591.833 | AX98: Cycle 1; rebuttal period January 26-February 2, 2027 | AY98: Cycle 2
A99: mobisys27 | B99: 46361.833 | N99: 46354.833 | Z99: 46431.833 | AX99: 单轮
A100: nossdav27 | B100: 46399.833 | AL100: 46420.833 | AX100: 单轮
...
